Workbook

Sheet 00 CISC Dashboard
A1: M | C1: CHIEF INVESTMENT STEWARD CONSOLE (CISC) | S1: ='01 Dashboard Controls'!B6 -> 46229 | V1: CISC-001 EXECUTIVE CONSOLE v1.0
C3: MANIFEST INSTITUTIONAL INVESTMENT SYSTEM
A5: 1 EXECUTIVE STATUS | C5: MANIFEST COMPOSITE ALIGNMENT GAUGE | K5: INSTITUTIONAL COMPASS | Q5: EXECUTIVE RECOMMENDATION
K6: ↗ | N6: CURRENT POSTURE | Q6: =IF('02 Decision Center'!B6="COMMITTEE ACTION REQUIRED","REVIEW IDENTIFIED DECISIONS","MAINTAIN PORTFOLIO CONSTRUCTION") -> MAINTAIN PORTFOLIO CONSTRUCTION
N9: ='01 Dashboard Controls'!B29 -> MAINTAIN STRATEGIC ALLOCATION
Q10: =IF('02 Decision Center'!B6="DATA UPDATE REQUIRED","Actual weights must be loaded before live rebalancing review.",IF('02 Decision Center'!B6="COMMITTEE ACTION REQUIRED","Committee review required. No automatic trades are authorized.","No structural changes recommended. Continue disciplined monitoring.")) -> Actual weights must be loaded before live rebalancing review.
C12: ='01 Dashboard Controls'!B27 -> 0.62 | F12: TREND | G12: ='01 Dashboard Controls'!B28 -> 0.04
F13: CONFIDENCE | G13: ='01 Dashboard Controls'!B11 -> 0.72 | K13: ="DISCIPLINED • BALANCED • "&'01 Dashboard Controls'!B30 -> DISCIPLINED • BALANCED • OPPORTUNISTIC
F14: PREVIOUS WEEK | G14: ='01 Dashboard Controls'!B10 -> 0.58 | Q14: ="NEXT REVIEW: "&TEXT('01 Dashboard Controls'!B12,"dddd, mmm d, yyyy") -> NEXT REVIEW: Monday, Jul 27, 2026
F15: CLASSIFICATION | G15: ='01 Dashboard Controls'!B31 -> GREEN / STRONG ALIGNMENT
A17: 2 PORTFOLIO HEALTH | C17: SLEEVE ALLOCATION | J17: TOP 10 HOLDINGS | Q17: ALLOCATION ALERTS
J18: Rank | K18: Holding | M18: Weight | N18: Role | P18: Conviction | Q18: Rank | R18: Holding | S18: Actual | T18: Target | U18: Variance | V18: Status | X18: Action
J19: ='99 Dashboard Data'!R2 -> 1 | K19: ='99 Dashboard Data'!S2 -> BRK.B | M19: ='99 Dashboard Data'!U2 -> 0.0302 | N19: ='99 Dashboard Data'!V2 -> Diversified capital-allocation anchor | P19: ='99 Dashboard Data'!W2 -> Unassigned | Q19: =IF(R19="","",'99 Dashboard Data'!R15) -> 1 | R19: =IF(OR('99 Dashboard Data'!S15=0,'99 Dashboard Data'!S15=""),"",'99 Dashboard Data'!S15) -> BRK.B | S19: =IF(R19="","",'99 Dashboard Data'!T15) -> 0 | T19: =IF(R19="","",'99 Dashboard Data'!U15) -> 0.0302 | U19: =IF(R19="","",'99 Dashboard Data'!V15) -> -0.0302 | V19: =IF(R19="","",'99 Dashboard Data'!W15) -> Not entered | X19: =IF(R19="","",'99 Dashboard Data'!X15) -> Enter actual weight
J20: ='99 Dashboard Data'!R3 -> 2 | K20: ='99 Dashboard Data'!S3 -> COST | M20: ='99 Dashboard Data'!U3 -> 0.0302 | N20: ='99 Dashboard Data'!V3 -> Consumer-resilience anchor | P20: ='99 Dashboard Data'!W3 -> Unassigned | Q20: =IF(R20="","",'99 Dashboard Data'!R16) -> 2 | R20: =IF(OR('99 Dashboard Data'!S16=0,'99 Dashboard Data'!S16=""),"",'99 Dashboard Data'!S16) -> COST | S20: =IF(R20="","",'99 Dashboard Data'!T16) -> 0 | T20: =IF(R20="","",'99 Dashboard Data'!U16) -> 0.0302 | U20: =IF(R20="","",'99 Dashboard Data'!V16) -> -0.0302 | V20: =IF(R20="","",'99 Dashboard Data'!W16) -> Not entered | X20: =IF(R20="","",'99 Dashboard Data'!X16) -> Enter actual weight
J21: ='99 Dashboard Data'!R4 -> 3 | K21: ='99 Dashboard Data'!S4 -> JNJ | M21: ='99 Dashboard Data'!U4 -> 0.0302 | N21: ='99 Dashboard Data'!V4 -> Healthcare and life-sciences resilience anchor | P21: ='99 Dashboard Data'!W4 -> Unassigned | Q21: =IF(R21="","",'99 Dashboard Data'!R17) -> 3 | R21: =IF(OR('99 Dashboard Data'!S17=0,'99 Dashboard Data'!S17=""),"",'99 Dashboard Data'!S17) -> JNJ | S21: =IF(R21="","",'99 Dashboard Data'!T17) -> 0 | T21: =IF(R21="","",'99 Dashboard Data'!U17) -> 0.0302 | U21: =IF(R21="","",'99 Dashboard Data'!V17) -> -0.0302 | V21: =IF(R21="","",'99 Dashboard Data'!W17) -> Not entered | X21: =IF(R21="","",'99 Dashboard Data'!X17) -> Enter actual weight
J22: ='99 Dashboard Data'!R5 -> 4 | K22: ='99 Dashboard Data'!S5 -> MSFT | M22: ='99 Dashboard Data'!U5 -> 0.0302 | N22: ='99 Dashboard Data'!V5 -> Enterprise technology and AI platform anchor | P22: ='99 Dashboard Data'!W5 -> Unassigned | Q22: =IF(R22="","",'99 Dashboard Data'!R18) -> 4 | R22: =IF(OR('99 Dashboard Data'!S18=0,'99 Dashboard Data'!S18=""),"",'99 Dashboard Data'!S18) -> MSFT | S22: =IF(R22="","",'99 Dashboard Data'!T18) -> 0 | T22: =IF(R22="","",'99 Dashboard Data'!U18) -> 0.0302 | U22: =IF(R22="","",'99 Dashboard Data'!V18) -> -0.0302 | V22: =IF(R22="","",'99 Dashboard Data'!W18) -> Not entered | X22: =IF(R22="","",'99 Dashboard Data'!X18) -> Enter actual weight
J23: ='99 Dashboard Data'!R6 -> 5 | K23: ='99 Dashboard Data'!S6 -> AVGO | M23: ='99 Dashboard Data'!U6 -> 0.0302 | N23: ='99 Dashboard Data'!V6 -> Semiconductor and infrastructure-software compounder | P23: ='99 Dashboard Data'!W6 -> Unassigned | Q23: =IF(R23="","",'99 Dashboard Data'!R19) -> 5 | R23: =IF(OR('99 Dashboard Data'!S19=0,'99 Dashboard Data'!S19=""),"",'99 Dashboard Data'!S19) -> AVGO | S23: =IF(R23="","",'99 Dashboard Data'!T19) -> 0 | T23: =IF(R23="","",'99 Dashboard Data'!U19) -> 0.0302 | U23: =IF(R23="","",'99 Dashboard Data'!V19) -> -0.0302 | V23: =IF(R23="","",'99 Dashboard Data'!W19) -> Not entered | X23: =IF(R23="","",'99 Dashboard Data'!X19) -> Enter actual weight
J24: ='99 Dashboard Data'!R7 -> 6 | K24: ='99 Dashboard Data'!S7 -> LLY | M24: ='99 Dashboard Data'!U7 -> 0.0302 | N24: ='99 Dashboard Data'!V7 -> Healthcare innovation compounder | P24: ='99 Dashboard Data'!W7 -> Unassigned | Q24: =IF('99 Dashboard Data'!B61>0,'99 Dashboard Data'!B61&" actual weights are not loaded. Allocation alerts are not yet live.",IF('99 Dashboard Data'!B62=0,"All positions are within certified bands.","Committee review required for "&'99 Dashboard Data'!B62&" allocation-band exceptions.")) -> 47 actual weights are not loaded. Allocation alerts are not yet live.
J25: ='99 Dashboard Data'!R8 -> 7 | K25: ='99 Dashboard Data'!S8 -> CME | M25: ='99 Dashboard Data'!U8 -> 0.0302 | N25: ='99 Dashboard Data'!V8 -> Market infrastructure and derivatives exchange | P25: ='99 Dashboard Data'!W8 -> Unassigned
J26: ='99 Dashboard Data'!R9 -> 8 | K26: ='99 Dashboard Data'!S9 -> LNG | M26: ='99 Dashboard Data'!U9 -> 0.0302 | N26: ='99 Dashboard Data'!V9 -> LNG export infrastructure | P26: ='99 Dashboard Data'!W9 -> Unassigned
J27: ='99 Dashboard Data'!R10 -> 9 | K27: ='99 Dashboard Data'!S10 -> VPU | M27: ='99 Dashboard Data'!U10 -> 0.0302 | N27: ='99 Dashboard Data'!V10 -> Utilities and defensive infrastructure ETF | P27: ='99 Dashboard Data'!W10 -> Unassigned | Q27: OUTSIDE BAND = REVIEW REQUIRED • NO AUTOMATIC TRADING
J28: ='99 Dashboard Data'!R11 -> 10 | K28: ='99 Dashboard Data'!S11 -> JEPI | M28: ='99 Dashboard Data'!U11 -> 0.0302 | N28: ='99 Dashboard Data'!V11 -> Diversified equity income and volatility moderation | P28: ='99 Dashboard Data'!W11 -> Unassigned
J29: ="RANKING BASIS: "&'99 Dashboard Data'!B65 -> RANKING BASIS: Target Weight
Q30: ="DATA COMPLETENESS: "&TEXT('99 Dashboard Data'!B64,"0%")&" | ACTUAL TOTAL: "&TEXT('99 Dashboard Data'!B63,"0.00%") -> DATA COMPLETENESS: 0% | ACTUAL TOTAL: 0.00%
J31: =IF('99 Dashboard Data'!B61>0,"Actual weights incomplete — displaying certified target-weight ranking.","Actual weights complete — displaying live position ranking.") -> Actual weights incomplete — displaying certified target-weight ranking.
A34: 3 RESEARCH INTELLIGENCE | C34: COMPANIES REQUIRING REVIEW | G34: EARNINGS THIS WEEK | K34: ZACKS RANK CHANGES | O34: MERRILL RESEARCH UPDATES | S34: MIAR UPDATES | V34: THESIS / CONVICTION REVIEWS
C36: =IF('03 Research Intelligence'!A7="","No entry loaded",'03 Research Intelligence'!A7&" — "&'03 Research Intelligence'!C7) -> No entry loaded | G36: =IF('03 Research Intelligence'!B19="","No entry loaded",TEXT('03 Research Intelligence'!A19,"m/d")&" "&'03 Research Intelligence'!B19&" — "&'03 Research Intelligence'!D19) -> No entry loaded | K36: =IF('03 Research Intelligence'!B31="","No entry loaded",'03 Research Intelligence'!B31&" #"&'03 Research Intelligence'!C31&" → #"&'03 Research Intelligence'!D31) -> No entry loaded | O36: =IF('03 Research Intelligence'!B43="","No entry loaded",'03 Research Intelligence'!B43&" — "&'03 Research Intelligence'!C43) -> No entry loaded | S36: =IF('03 Research Intelligence'!A55="","No entry loaded",'03 Research Intelligence'!A55&" — "&'03 Research Intelligence'!B55&" / "&'03 Research Intelligence'!F55) -> No entry loaded | V36: =IF('03 Research Intelligence'!A67="","No entry loaded",'03 Research Intelligence'!A67&" — "&'03 Research Intelligence'!D67) -> No entry loaded
G38: =IF('03 Research Intelligence'!B20="","No entry loaded",TEXT('03 Research Intelligence'!A20,"m/d")&" "&'03 Research Intelligence'!B20&" — "&'03 Research Intelligence'!D20) -> No entry loaded | K38: =IF('03 Research Intelligence'!B32="","No entry loaded",'03 Research Intelligence'!B32&" #"&'03 Research Intelligence'!C32&" → #"&'03 Research Intelligence'!D32) -> No entry loaded | O38: =IF('03 Research Intelligence'!B44="","No entry loaded",'03 Research Intelligence'!B44&" — "&'03 Research Intelligence'!C44) -> No entry loaded
C39: =IF('03 Research Intelligence'!A8="","No entry loaded",'03 Research Intelligence'!A8&" — "&'03 Research Intelligence'!C8) -> No entry loaded | S39: =IF('03 Research Intelligence'!A56="","No entry loaded",'03 Research Intelligence'!A56&" — "&'03 Research Intelligence'!B56&" / "&'03 Research Intelligence'!F56) -> No entry loaded | V39: =IF('03 Research Intelligence'!A68="","No entry loaded",'03 Research Intelligence'!A68&" — "&'03 Research Intelligence'!D68) -> No entry loaded
G40: =IF('03 Research Intelligence'!B21="","No entry loaded",TEXT('03 Research Intelligence'!A21,"m/d")&" "&'03 Research Intelligence'!B21&" — "&'03 Research Intelligence'!D21) -> No entry loaded | K40: =IF('03 Research Intelligence'!B33="","No entry loaded",'03 Research Intelligence'!B33&" #"&'03 Research Intelligence'!C33&" → #"&'03 Research Intelligence'!D33) -> No entry loaded | O40: =IF('03 Research Intelligence'!B45="","No entry loaded",'03 Research Intelligence'!B45&" — "&'03 Research Intelligence'!C45) -> No entry loaded
C42: =IF('03 Research Intelligence'!A9="","No entry loaded",'03 Research Intelligence'!A9&" — "&'03 Research Intelligence'!C9) -> No entry loaded | G42: =IF('03 Research Intelligence'!B22="","No entry loaded",TEXT('03 Research Intelligence'!A22,"m/d")&" "&'03 Research Intelligence'!B22&" — "&'03 Research Intelligence'!D22) -> No entry loaded | K42: =IF('03 Research Intelligence'!B34="","No entry loaded",'03 Research Intelligence'!B34&" #"&'03 Research Intelligence'!C34&" → #"&'03 Research Intelligence'!D34) -> No entry loaded | O42: =IF('03 Research Intelligence'!B46="","No entry loaded",'03 Research Intelligence'!B46&" — "&'03 Research Intelligence'!C46) -> No entry loaded | S42: =IF('03 Research Intelligence'!A57="","No entry loaded",'03 Research Intelligence'!A57&" — "&'03 Research Intelligence'!B57&" / "&'03 Research Intelligence'!F57) -> No entry loaded | V42: =IF('03 Research Intelligence'!A69="","No entry loaded",'03 Research Intelligence'!A69&" — "&'03 Research Intelligence'!D69) -> No entry loaded
A47: 4 COMMITTEE OPERATIONS | C47: PENDING ACTIONS | H47: MWIR STATUS | M47: OPERATIONAL CALENDAR | R47: CERTIFICATION STATUS | V47: STEWARD'S NOTEBOOK
H48: ='04 Committee Operations'!A25 -> MWIR | M48: =IF('04 Committee Operations'!B37="","No event loaded",IF('04 Committee Operations'!A37="","TBD",TEXT('04 Committee Operations'!A37,"m/d"))&" — "&'04 Committee Operations'!B37) -> 7/27 — Monday workflow | R48: ='04 Committee Operations'!A51&" — "&'04 Committee Operations'!B51&" / "&'04 Committee Operations'!E51 -> Chief Investment Steward Console — CISC-001 / v1.0 / Frozen | V48: =COUNTIF('04 Committee Operations'!N8:N17,"Open")+COUNTIF('04 Committee Operations'!N8:N17,"Planned")&" priorities" -> 5 priorities
C49: Open / Planned Actions | G49: ='99 Dashboard Data'!B67 -> 4
C50: Research Decisions | G50: ='99 Dashboard Data'!B66 -> 0 | M50: =IF('04 Committee Operations'!B38="","No event loaded",IF('04 Committee Operations'!A38="","TBD",TEXT('04 Committee Operations'!A38,"m/d"))&" — "&'04 Committee Operations'!B38) -> 7/27 — MWIR publication | R50: ='04 Committee Operations'!A52&" — "&'04 Committee Operations'!B52&" / "&'04 Committee Operations'!E52 -> Manifest Flagship Portfolio Definition File — MFPDF v1.0 / Certified
C51: Allocation Decisions | G51: ='99 Dashboard Data'!B62 -> 0 | H51: ="STATUS: "&'04 Committee Operations'!E25 -> STATUS: Planned | V51: =COUNTIF('04 Committee Operations'!N21:N30,"Open")+COUNTIF('04 Committee Operations'!N21:N30,"Pending Data")&" committee questions" -> 5 committee questions
C52: Committee Decisions | G52: ='02 Decision Center'!B13 -> 0 | M52: =IF('04 Committee Operations'!B39="","No event loaded",IF('04 Committee Operations'!A39="","TBD",TEXT('04 Committee Operations'!A39,"m/d"))&" — "&'04 Committee Operations'!B39) -> TBD — Monthly allocation review | R52: ='04 Committee Operations'!A53&" — "&'04 Committee Operations'!B53&" / "&'04 Committee Operations'!E53 -> Manifest Visual Design System — MVDS v1.0 / Frozen
C53: Actual Weights Missing | G53: ='99 Dashboard Data'!B61 -> 47 | H53: ="LAST PUBLISHED: "&TEXT('04 Committee Operations'!C25,"m/d/yyyy") -> LAST PUBLISHED: 7/25/2026
C54: Data Completeness | G54: ='99 Dashboard Data'!B64 -> 0 | M54: =IF('04 Committee Operations'!B40="","No event loaded",IF('04 Committee Operations'!A40="","TBD",TEXT('04 Committee Operations'!A40,"m/d"))&" — "&'04 Committee Operations'!B40) -> TBD — Quarterly engineering review | R54: ='04 Committee Operations'!A54&" — "&'04 Committee Operations'!B54&" / "&'04 Committee Operations'!E54 -> Manifest Founders Edition — v1.0 / Complete | V54: =COUNTIF('04 Committee Operations'!N34:N43,"Planned")+COUNTIF('04 Committee Operations'!N34:N43,"In Progress")&" long-term projects" -> 5 long-term projects
C55: Decision State | G55: ='02 Decision Center'!B6 -> DATA UPDATE REQUIRED | H55: ="NEXT DUE: "&TEXT('04 Committee Operations'!D25,"m/d/yyyy") -> NEXT DUE: 7/27/2026
M56: VIEW FULL CALENDAR → | R56: OPEN CERTIFICATION CENTER →
H57: OPEN MWIR WORKSPACE → | V57: OPEN NOTEBOOK →
A60: 5 MANIFEST DECISION CENTER | C60: WHAT DECISIONS ARE ACTUALLY REQUIRED THIS WEEK?
C61: ='02 Decision Center'!B6 -> DATA UPDATE REQUIRED
C65: ="PRIMARY REQUIRED ACTION"&CHAR(10)&'02 Decision Center'!B14 -> PRIMARY REQUIRED ACTION Load current actual portfolio weights | H65: ="COMMITTEE DECISIONS"&CHAR(10)&TEXT('02 Decision Center'!B13,"0") -> COMMITTEE DECISIONS 0 | M65: ="MEETING STATUS"&CHAR(10)&'02 Decision Center'!E6 -> MEETING STATUS DEFER — COMPLETE DATA | R65: ="DATA COMPLETENESS"&CHAR(10)&TEXT('02 Decision Center'!B7,"0%") -> DATA COMPLETENESS 0% | W65: ="TRADING"&CHAR(10)&"PROHIBITED" -> TRADING PROHIBITED
C69: =IF('02 Decision Center'!B6="NO COMMITTEE ACTION REQUIRED","No structural portfolio or research decision is required. Continue monitoring and complete normal operating work.",IF('02 Decision Center'!B6="DATA UPDATE REQUIRED","Complete the data update before convening the committee. No allocation conclusion should be drawn from incomplete actual weights.","Review the identified decision queue. Committee review must precede any implementation.")) -> Complete the data update before convening the committee. No allocation conclusion should be drawn from incomplete actual weights.
A72: MANIFEST WORKBENCH | DASHBOARD • PORTFOLIO • RESEARCH • COMMITTEE ROOM • PUBLICATIONS • LIBRARY • SETTINGS

Sheet 01 Dashboard Controls
A1: MANIFEST WORKBENCH — DASHBOARD CONTROLS
A3: CISC-001 | Founders Edition v1.0 | Blue/yellow cells are weekly operating inputs
A5: Control Field | B5: Operating Value
A6: Report Date | B6: 46229
A7: Console ID | B7: CISC-001
A8: Edition | B8: Founders Edition v1.0
A9: Data Status | B9: PROTOTYPE VALUES — LIVE INPUTS REQUIRED
A10: Previous Week Score | B10: 0.58
A11: Confidence | B11: 0.72
A12: Next Review | B12: 46230
A13: MWIR Status | B13: Planned / not yet published
A15: Composite Component | B15: Score (-1 to +1) | C15: Weight | D15: Contribution | F15: Gauge Zone | G15: Value
A16: Macro Regime | B16: 0.6 | C16: 0.15 | D16: =B16*C16 -> 0.09 | F16: Positive / Green | G16: 40
A17: Credit Conditions | B17: 0.55 | C17: 0.15 | D17: =B17*C17 -> 0.0825 | F17: Neutral / Yellow | G17: 20
A18: Liquidity & Policy | B18: 0.45 | C18: 0.1 | D18: =B18*C18 -> 0.045 | F18: Caution / Orange | G18: 20
A19: Market Breadth | B19: 0.65 | C19: 0.1 | D19: =B19*C19 -> 0.065 | F19: Risk / Red | G19: 20
A20: Earnings & Fundamentals | B20: 0.7 | C20: 0.15 | D20: =B20*C20 -> 0.105
A21: Valuation Discipline | B21: 0.4 | C21: 0.1 | D21: =B21*C21 -> 0.04
A22: Portfolio Alignment | B22: 0.75 | C22: 0.15 | D22: =B22*C22 -> 0.1125 | F22: Score Floor | G22: Score Ceiling | H22: Posture
A23: Research Conviction | B23: 0.8 | C23: 0.1 | D23: =B23*C23 -> 0.08 | F23: 0.5 | G23: 1 | H23: Maintain / Opportunistic
A24: TOTAL / COMPOSITE | C24: =SUM(C16:C23) -> 1 | D24: =SUM(D16:D23) -> 0.62 | F24: 0.1 | G24: 0.49 | H24: Maintain / Balanced
F25: -0.09 | G25: 0.09 | H25: Hold / Disciplined
A26: Derived Indicator | B26: Result | F26: -0.34 | G26: -0.1 | H26: Defensive / Selective
A27: Composite Alignment Score | B27: =D24 -> 0.62 | F27: -1 | G27: -0.35 | H27: Reduce Risk
A28: Weekly Change | B28: =B27-B10 -> 0.04 | F28: Thresholds change only by committee action. | H28: Thresholds change only by committee action.
A29: Current Posture | B29: =IF(B27>=0.10,"MAINTAIN STRATEGIC ALLOCATION",IF(B27>-0.10,"HOLD / MONITOR",IF(B27>-0.35,"DEFENSIVE TILT","REDUCE RISK"))) -> MAINTAIN STRATEGIC ALLOCATION
A30: Compass Bias | B30: =IF(B27>=0.50,"OPPORTUNISTIC",IF(B27>=0.10,"BALANCED",IF(B27>-0.10,"DISCIPLINED",IF(B27>-0.35,"DEFENSIVE","CAPITAL PRESERVATION")))) -> OPPORTUNISTIC
A31: Score Classification | B31: =IF(B27>=0.50,"GREEN / STRONG ALIGNMENT",IF(B27>=0.10,"GREEN / POSITIVE ALIGNMENT",IF(B27>-0.10,"YELLOW / NEUTRAL",IF(B27>-0.35,"ORANGE / CAUTION","RED / RISK REDUCTION")))) -> GREEN / STRONG ALIGNMENT
A32: Prototype Note | B32: Replace component scores and confidence in each weekly run.

Sheet 02 Decision Center
A1: MANIFEST DECISION CENTER
A3: What decisions are actually required this week?
A5: Decision Metric | B5: Current State | D5: Governance Rule | E5: Result | F5: Meaning
A6: Decision State | B6: =IF(B8>0,"DATA UPDATE REQUIRED",IF(B13>0,"COMMITTEE ACTION REQUIRED","NO COMMITTEE ACTION REQUIRED")) -> DATA UPDATE REQUIRED | D6: Committee Meeting | E6: =IF(B6="COMMITTEE ACTION REQUIRED","CONVENE COMMITTEE",IF(B6="DATA UPDATE REQUIRED","DEFER — COMPLETE DATA","NO MEETING REQUIRED")) -> DEFER — COMPLETE DATA | F6: Convene only when a decision is actually required.
A7: Data Completeness | B7: ='99 Dashboard Data'!B64 -> 0 | D7: Automatic Trading | E7: PROHIBITED | F7: Committee review precedes implementation.
A8: Missing Actual Weights | B8: ='99 Dashboard Data'!B61 -> 47 | D8: Current Weight Basis | E8: ='99 Dashboard Data'!B65 -> Target Weight | F8: Top holdings use actual weights only when all 47 are loaded.
A9: Allocation Decisions | B9: ='99 Dashboard Data'!B62 -> 0 | D9: Rebalance Policy | E9: Band-Based | F9: Outside-band positions are reviewed, not automatically traded.
A10: Research / Conviction Decisions | B10: ='99 Dashboard Data'!B66 -> 0 | D10: No-Action State | E10: AUTHORIZED | F10: Display when data are complete and no decisions remain.
A11: Manual Committee Decisions | B11: =COUNTIFS(J28:J47,"Yes",K28:K47,"Open")+COUNTIFS(J28:J47,"Yes",K28:K47,"In Review") -> 0
A12: Open Operating Actions | B12: ='99 Dashboard Data'!B67 -> 4
A13: Total Committee Decisions | B13: =SUM(B9:B11) -> 0
A14: Highest Priority | B14: =IF(B8>0,"Load current actual portfolio weights",IF(B9>0,"Review allocation-band exceptions",IF(B10>0,"Resolve research or conviction decisions",IF(B11>0,"Resolve manual committee decisions","Continue disciplined monitoring")))) -> Load current actual portfolio weights
A17: SYSTEM DECISION QUEUE
A18: ID | B18: Category | C18: Trigger | D18: Decision Required | E18: Recommended Action | F18: Authority | G18: Status | H18: Evidence | I18: Owner | J18: Due | K18: Notes
A19: DC-SYS-001 | B19: Data Integrity | C19: =IF($B$8>0,$B$8&" actual weights missing","Actual weights complete") -> 47 actual weights missing | D19: =IF($B$8>0,"Data update required","No data decision") -> Data update required | E19: Load actual weights in Certified Allocation column I | F19: Portfolio Operations | G19: =IF($B$8>0,"ACTION REQUIRED","READY") -> ACTION REQUIRED | H19: MFPDF actual-weight fields | I19: Portfolio Operations | J19: 46230 | K19: Blocks live allocation decisions
A20: DC-SYS-002 | B20: Allocation | C20: =$B$9&" allocation-band exceptions" -> 0 allocation-band exceptions | D20: =IF($B$9>0,"Committee allocation decision","No allocation decision") -> No allocation decision | E20: Review each band exception; add/trim only after committee review | F20: Stewardship Committee | G20: =IF($B$8>0,"PENDING DATA",IF($B$9>0,"DECISION REQUIRED","NO DECISION")) -> PENDING DATA | H20: Certified bands and actual weights | I20: Portfolio Engineering | K20: No automatic rebalancing
A21: DC-SYS-003 | B21: Research | C21: =$B$10&" research / conviction decisions" -> 0 research / conviction decisions | D21: =IF($B$10>0,"Committee research decision","No research decision") -> No research decision | E21: Resolve items marked Decision Required | F21: Research / Stewardship Committee | G21: =IF($B$10>0,"DECISION REQUIRED","NO DECISION") -> NO DECISION | H21: Research Intelligence workspace | I21: Research Division
A22: DC-SYS-004 | B22: Manual Decisions | C22: =$B$11&" manual committee decisions" -> 0 manual committee decisions | D22: =IF($B$11>0,"Committee decision","No manual decision") -> No manual decision | E22: Resolve open manual committee decisions | F22: Stewardship Committee | G22: =IF($B$11>0,"DECISION REQUIRED","NO DECISION") -> NO DECISION | H22: Manual Decision Register | I22: Chief Investment Steward
A23: DC-SYS-005 | B23: Publication | C23: MWIR scheduled | D23: No committee decision unless recommendation changes | E23: Complete institutional publication workflow | F23: Publication Division | G23: Operational | H23: Committee Operations | I23: Publication Division | J23: 46230
A26: MANUAL DECISION REGISTER
A27: ID | B27: Date Opened | C27: Category | D27: Decision | E27: Evidence | F27: Recommendation | G27: Authority | H27: Owner | I27: Due Date | J27: Requires Committee Decision? | K27: Status
A28: DC-001 | B28: 46229 | C28: Governance | D28: Freeze CISC-001 as the five-panel visual reference standard | E28: Approved console design plus Manifest Decision Center | F28: Frozen as CISC-001 Founders Edition v1.0 | G28: Chief Investment Steward | H28: Chief Investment Steward | I28: 46229 | J28: No | K28: Closed
A29: DC-002 | B29: 46229 | C29: Operations | D29: Establish Manifest Workbench on the certified MFPDF foundation | E29: Canonical 47-position Portfolio B workbook | F29: Implement workbench without altering certified target weights | G29: Chief Investment Steward | H29: Portfolio Operations | I29: 46229 | J29: No | K29: Closed
A30: DC-003 | B30: 46229 | C30: Data | D30: Load current actual portfolio weights | E30: Certified Allocation column I is blank | F30: Complete data update before live band review | G30: Portfolio Operations | H30: Portfolio Operations | I30: 46230 | J30: No | K30: Open

Sheet 03 Research Intelligence
A1: RESEARCH INTELLIGENCE WORKSPACE
A3: Populate only verified current research. The dashboard reads the first active entries from each section.
A5: COMPANIES REQUIRING REVIEW
A6: Symbol | B6: Company | C6: Reason | D6: Trigger | E6: Priority | F6: Due Date | G6: Status
A17: EARNINGS / EVENT CALENDAR
A18: Date | B18: Symbol | C18: Company | D18: Event | E18: Status
A29: ZACKS RANK CHANGES
A30: Date | B30: Symbol | C30: Prior Rank | D30: Current Rank | E30: Direction | F30: Notes
A41: MERRILL RESEARCH UPDATES
A42: Date | B42: Symbol | C42: Rating / Action | D42: Price Target Change | E42: Thesis Impact | F42: Source Reference | G42: Status
A53: MIAR UPDATES
A54: Symbol | B54: Review Type | C54: Last Updated | D54: Due Date | E54: Owner | F54: Status
A65: THESIS / CONVICTION REVIEWS
A66: Symbol | B66: Current Conviction | C66: Proposed Conviction | D66: Reason | E66: Due Date | F66: Authority | G66: Status

Sheet 04 Committee Operations
A1: COMMITTEE OPERATIONS & STEWARD'S NOTEBOOK
A3: Operating actions remain distinct from committee decisions. Use the explicit decision flag.
A5: ACTION REGISTER | J5: STEWARD'S NOTEBOOK
A6: ID | B6: Category | C6: Action | D6: Owner | E6: Due Date | F6: Priority | G6: Status | H6: Requires Committee Decision? | I6: Linked Record
A7: OP-001 | B7: Governance | C7: Freeze CISC-001 visual dashboard with five panels | D7: Chief Investment Steward | E7: 46229 | F7: High | G7: Completed | H7: No | I7: CISC-001 | J7: THIS WEEK'S PRIORITIES
A8: OP-002 | B8: Operations | C8: Establish Manifest Workbench from canonical MFPDF | D8: Portfolio Operations | E8: 46229 | F8: High | G8: Completed | H8: No | I8: CISC-001 | J8: 1 | K8: Load current actual portfolio weights | L8: Portfolio Operations | M8: 46230 | N8: Open
A9: OP-003 | B9: Data | C9: Load current actual portfolio weights | D9: Portfolio Operations | E9: 46230 | F9: High | G9: Open | H9: No | I9: DC-SYS-001 | J9: 2 | K9: Populate current research intelligence | L9: Research Division | M9: 46230 | N9: Open
A10: OP-004 | B10: Research | C10: Populate current research intelligence | D10: Research Division | E10: 46230 | F10: High | G10: Open | H10: No | I10: DC-SYS-003 | J10: 3 | K10: Publish next MWIR | L10: Publication Division | M10: 46230 | N10: Planned
A11: OP-005 | B11: Publication | C11: Publish next MWIR | D11: Publication Division | E11: 46230 | F11: High | G11: Planned | H11: No | I11: MWIR | J11: 4 | K11: Run Monte Carlo on canonical Portfolio B | L11: Portfolio Engineering | N11: Planned
A12: OP-006 | B12: Analytics | C12: Run Monte Carlo on canonical Portfolio B | D12: Portfolio Engineering | F12: Medium | G12: Planned | H12: No | I12: MFPDF v1.0 | J12: 5 | K12: Assign conviction tiers | L12: Stewardship Committee | N12: Planned
J20: QUESTIONS FOR COMMITTEE
J21: Q1 | K21: Are any actual weights outside certified bands? | L21: Current weights | M21: Portfolio Operations | N21: Pending Data
J22: Q2 | K22: Does MU require a conviction change? | L22: Current research | M22: Research Division | N22: Open
A23: PUBLICATION STATUS | J23: Q3 | K23: Are any holdings carrying a Zacks #4 rating? | L23: Current Zacks file | M23: Research Division | N23: Open
A24: Publication | B24: Latest Issue | C24: Last Published | D24: Next Due | E24: Status | F24: Owner | J24: Q4 | K24: Are new candidates eligible for MASR review? | L24: Candidate dossiers | M24: Research Division | N24: Open
A25: MWIR | B25: Week ending Jul. 24, 2026 | C25: 46228 | D25: 46230 | E25: Planned | F25: Publication Division | J25: Q5 | K25: Is any sleeve outside its target allocation? | L25: Current weights | M25: Portfolio Engineering | N25: Pending Data
A26: MOR | B26: MOR-001 | C26: 46223 | E26: Scheduled | F26: Publication Division
A27: MIRD | B27: Weekly risk dashboard | C27: 46228 | D27: 46230 | E27: Scheduled | F27: Risk Division
A28: MIPR | B28: Institutional portfolio review | E28: Not Started | F28: Portfolio Division
J33: LONG-TERM PROJECTS
J34: P1 | K34: Monte Carlo Enhancement | L34: Portfolio Engineering | M34: Institutional simulation engine | N34: In Progress
A35: OPERATIONAL CALENDAR | J35: P2 | K35: Advisor Handbook | L35: Manifest Academy | M35: Operating handbook | N35: Planned
A36: Date | B36: Event | C36: Cadence | D36: Authority | E36: Status | J36: P3 | K36: Client Presentation | L36: Publication Division | M36: Client-ready deck | N36: Planned
A37: 46230 | B37: Monday workflow | C37: Weekly | D37: Chief Investment Steward | E37: Scheduled | J37: P4 | K37: Casebook Development | L37: Manifest Academy | M37: Founders casebook | N37: Planned
A38: 46230 | B38: MWIR publication | C38: Weekly | D38: Publication Division | E38: Scheduled | J38: P5 | K38: Library Expansion Plan | L38: Editorial Board | M38: Master library integration | N38: In Progress
B39: Monthly allocation review | C39: Monthly | D39: Stewardship Committee | E39: TBD
B40: Quarterly engineering review | C40: Quarterly | D40: Portfolio Engineering | E40: TBD
B41: MOR publication | C41: Monthly | D41: Publication Division | E41: TBD
A49: CERTIFICATION REGISTER
A50: Record | B50: Version | C50: Certified / Frozen | D50: Review Cadence | E50: Status | F50: Authority
A51: Chief Investment Steward Console | B51: CISC-001 / v1.0 | C51: 46229 | D51: Event-driven | E51: Frozen | F51: Chief Investment Steward
A52: Manifest Flagship Portfolio Definition File | B52: MFPDF v1.0 | C52: 46223 | D52: Quarterly + material event | E52: Certified | F52: Stewardship Committee
A53: Manifest Visual Design System | B53: MVDS v1.0 | C53: 46223 | D53: Amendment only | E53: Frozen | F53: Publication Committee
A54: Manifest Founders Edition | B54: v1.0 | C54: 46222 | D54: Constitutional amendment only | E54: Complete | F54: Founding Authority

Sheet 05 Workbench Guide
A1: MANIFEST WORKBENCH — OPERATING GUIDE & FREEZE RECORD
A3: CISC-001 is the frozen visual foundation. MFPDF v1.0 remains the sole portfolio-allocation authority.
A5: Freeze Field | B5: Adopted Standard | C5: Status | D5: Operating Effect | F5: Workbook Authority | G5: Standard | H5: Status
A6: Visual Standard | B6: Chief Investment Steward Console (CISC-001) | C6: Frozen | D6: All future executive interfaces inherit this architecture. | F6: Canonical Portfolio | G6: Portfolio B / 47 positions | H6: MFPDF v1.0
A7: Edition | B7: Founders Edition v1.0 | C7: Frozen | D7: Changes require explicit amendment. | F7: Certified Target Total | G7: 100.00% | H7: Locked
A8: Panel 1 | B8: Executive Status | C8: Required | D8: Composite gauge, institutional compass and executive recommendation. | F8: Lower Band | G8: MAX(1.00%, 75% of target) | H8: Active
A9: Panel 2 | B9: Portfolio Health | C9: Required | D9: Sleeves, top holdings and allocation alerts. | F9: Upper Band | G9: MIN(4.00%, 125% of target) | H9: Active
A10: Panel 3 | B10: Research Intelligence | C10: Required | D10: Current research queue, MIAR and conviction maintenance. | F10: Automatic Trading | G10: Not authorized | H10: Prohibited
A11: Panel 4 | B11: Committee Operations | C11: Required | D11: Actions, publications, calendar, certifications and steward notebook. | F11: Committee Review | G11: Precedes implementation | H11: Required when triggered
A12: Panel 5 | B12: Manifest Decision Center | C12: Required | D12: Answers what decisions are actually required this week. | F12: Actual Weights | G12: User-entered | H12: Currently required
A15: Weekly Workflow | B15: Action | C15: Primary Sheet | D15: Control | F15: Color / Entry Convention | G15: Meaning | H15: Use
A16: 1 | B16: Update report date, score components and confidence | C16: 01 Dashboard Controls | D16: Blue/yellow input cells | F16: Blue text + yellow fill | G16: Hardcoded operating input | H16: Update each reporting cycle
A17: 2 | B17: Load all 47 actual portfolio weights | C17: Certified Allocation — column I | D17: Required before live band decisions | F17: Green text | G17: Link to another worksheet | H17: Do not overwrite
A18: 3 | B18: Assign conviction and research status | C18: Certified Allocation — columns M–N | D18: Used by top-holdings and research panels | F18: Black text | G18: Formula / calculation | H18: Do not hardcode over formula
... A20: 5 | B20: Review the Manifest Decision Center | C20: 02 Decision Center | D20: No-action state is valid and explicit | F20: Green status | G20: Aligned / no decision required | H20: Continue monitoring
A21: 6 | B21: Publish the MWIR and related dashboards | C21: 00 CISC Dashboard | D21: No automatic trading
A24: Operating Rule: the workbench is an executive decision-support interface. It does not modify the frozen portfolio merely because a band is breached, and it never authorizes automatic trades. The correct weekly output may be “NO COMMITTEE ACTION REQUIRED.”
A26: MOPS-003 RESEARCH OPERATING ADDENDUM — RCC-001 & RCC-002 INSTALLED
A27: Research Step | B27: Action | C27: Primary Sheet | D27: Control | F27: Authority | G27: Output | H27: Portfolio Effect
A28: 1 | B28: Enter one verified or pending signal per row | C28: 18 RCC-002 Evidence Ledger | D28: Unique Evidence ID | F28: Research Operations | G28: Auditable intake record | H28: None
A29: 2 | B29: Review materiality, reliability and routing | C29: 17 RCC-002 Control Center | D29: Verification and referral gates | F29: Research Committee | G29: MIAR / thesis / conviction / PEW referral | H29: Scenario only
A30: 3 | B30: Monitor research readiness and exceptions | C30: 16 RCC-001 Control Center | D30: RCC-001 executive aggregation | F30: Chief Investment Steward | G30: Decision queue | H30: No direct allocation authority

Sheet Executive Summary
A1: MANIFEST FLAGSHIP PORTFOLIO DEFINITION FILE
A2: Founders Edition Version 1.0 — Canonical Implementation Workbook
A4: Certification Field | B4: Value | D4: Executive Certification
A5: Canonical portfolio | B5: Portfolio B | D5: This workbook supersedes all prior preliminary allocation workbooks. It reconciles the 47-symbol Portfolio B export with the MQOC-006 empirical optimizer. The optimizer's 2.00% placeholder has been assigned to MMC, the sole Portfolio B symbol absent from the provisional weight file. No other target weight was changed.
A6: Total positions | B6: 47
A7: Equities | B7: 40
A8: ETFs | B8: 7
A9: Certified target total | B9: ='Certified Allocation'!F53 -> 1
A10: Rebalancing policy | B10: Band-based; review before trade
A12: Operating Rules
A13: Rule | B13: Standard
A14: Target allocation | B14: 100.00%
A15: Position minimum | B15: 1.00% lower-band floor
A16: Position maximum | B16: 4.00% upper-band cap
A17: Review trigger | B17: Actual weight outside allowable band; committee review precedes implementation

Sheet Certified Allocation
A1: Manifest Flagship Portfolio Definition File (MFPDF) — Founders Edition v1.0
A2: Certified Target Allocation Schedule | Canonical Portfolio B | 47 positions
A4: Production Sleeve | B4: Symbol | C4: Security | D4: Security Type | E4: Portfolio Role | F4: Target Weight | G4: Lower Band | H4: Upper Band | I4: Actual Weight (Input) | J4: Variance to Target | K4: Band Status | L4: Rebalancing Action | M4: Conviction Tier (Input) | N4: Research Status (Input)
A5: Strategic Anchors | B5: BRK.B | C5: Berkshire Hathaway Inc. Class B | D5: Equity | E5: Diversified capital-allocation anchor | F5: 0.0302 | G5: =MAX(1%,F5*75%) -> 0.02265 | H5: =MIN(4%,F5*125%) -> 0.03775 | J5: =IF(I5="","",I5-F5) | K5: =IF(I5="","Not entered",IF(I5<G5,"Below band",IF(I5>H5,"Above band","Within band"))) -> Not entered | L5: =IF(I5="","Enter actual weight",IF(I5<G5,"Review / Add",IF(I5>H5,"Review / Trim","No action"))) -> Enter actual weight | M5: Unassigned | N5: Current
A6: Strategic Anchors | B6: COST | C6: Costco Wholesale Corporation | D6: Equity | E6: Consumer-resilience anchor | F6: 0.0302 | G6: =MAX(1%,F6*75%) -> 0.02265 | H6: =MIN(4%,F6*125%) -> 0.03775 | J6: =IF(I6="","",I6-F6) | K6: =IF(I6="","Not entered",IF(I6<G6,"Below band",IF(I6>H6,"Above band","Within band"))) -> Not entered | L6: =IF(I6="","Enter actual weight",IF(I6<G6,"Review / Add",IF(I6>H6,"Review / Trim","No action"))) -> Enter actual weight | M6: Unassigned | N6: Current
A7: Strategic Anchors | B7: JNJ | C7: Johnson & Johnson | D7: Equity | E7: Healthcare and life-sciences resilience anchor | F7: 0.0302 | G7: =MAX(1%,F7*75%) -> 0.02265 | H7: =MIN(4%,F7*125%) -> 0.03775 | J7: =IF(I7="","",I7-F7) | K7: =IF(I7="","Not entered",IF(I7<G7,"Below band",IF(I7>H7,"Above band","Within band"))) -> Not entered | L7: =IF(I7="","Enter actual weight",IF(I7<G7,"Review / Add",IF(I7>H7,"Review / Trim","No action"))) -> Enter actual weight | M7: Unassigned | N7: Current
A8: Strategic Anchors | B8: MSFT | C8: Microsoft Corporation | D8: Equity | E8: Enterprise technology and AI platform anchor | F8: 0.0302 | G8: =MAX(1%,F8*75%) -> 0.02265 | H8: =MIN(4%,F8*125%) -> 0.03775 | J8: =IF(I8="","",I8-F8) | K8: =IF(I8="","Not entered",IF(I8<G8,"Below band",IF(I8>H8,"Above band","Within band"))) -> Not entered | L8: =IF(I8="","Enter actual weight",IF(I8<G8,"Review / Add",IF(I8>H8,"Review / Trim","No action"))) -> Enter actual weight | M8: Unassigned | N8: Current
A9: Strategic Anchors | B9: V | C9: Visa Inc. | D9: Equity | E9: Global payments infrastructure anchor | F9: 0.0288 | G9: =MAX(1%,F9*75%) -> 0.0216 | H9: =MIN(4%,F9*125%) -> 0.036 | J9: =IF(I9="","",I9-F9) | K9: =IF(I9="","Not entered",IF(I9<G9,"Below band",IF(I9>H9,"Above band","Within band"))) -> Not entered | L9: =IF(I9="","Enter actual weight",IF(I9<G9,"Review / Add",IF(I9>H9,"Review / Trim","No action"))) -> Enter actual weight | M9: Unassigned | N9: Current
A10: Strategic Anchors | B10: GOOGL | C10: Alphabet Inc. Class A | D10: Equity | E10: Digital platform and AI anchor | F10: 0.0284 | G10: =MAX(1%,F10*75%) -> 0.0213 | H10: =MIN(4%,F10*125%) -> 0.0355 | J10: =IF(I10="","",I10-F10) | K10: =IF(I10="","Not entered",IF(I10<G10,"Below band",IF(I10>H10,"Above band","Within band"))) -> Not entered | L10: =IF(I10="","Enter actual weight",IF(I10<G10,"Review / Add",IF(I10>H10,"Review / Trim","No action"))) -> Enter actual weight | M10: Unassigned | N10: Current
A11: Strategic Anchors | B11: MA | C11: Mastercard Incorporated | D11: Equity | E11: Global payments infrastructure anchor | F11: 0.016 | G11: =MAX(1%,F11*75%) -> 0.012 | H11: =MIN(4%,F11*125%) -> 0.02 | J11: =IF(I11="","",I11-F11) | K11: =IF(I11="","Not entered",IF(I11<G11,"Below band",IF(I11>H11,"Above band","Within band"))) -> Not entered | L11: =IF(I11="","Enter actual weight",IF(I11<G11,"Review / Add",IF(I11>H11,"Review / Trim","No action"))) -> Enter actual weight | M11: Unassigned | N11: Current
A12: Strategic Anchors | B12: AAPL | C12: Apple Inc. | D12: Equity | E12: Consumer technology ecosystem anchor | F12: 0.0156 | G12: =MAX(1%,F12*75%) -> 0.0117 | H12: =MIN(4%,F12*125%) -> 0.0195 | J12: =IF(I12="","",I12-F12) | K12: =IF(I12="","Not entered",IF(I12<G12,"Below band",IF(I12>H12,"Above band","Within band"))) -> Not entered | L12: =IF(I12="","Enter actual weight",IF(I12<G12,"Review / Add",IF(I12>H12,"Review / Trim","No action"))) -> Enter actual weight | M12: Unassigned | N12: Current
A13: Strategic Anchors | B13: AMZN | C13: Amazon.com, Inc. | D13: Equity | E13: Cloud, commerce and logistics anchor | F13: 0.0155 | G13: =MAX(1%,F13*75%) -> 0.011625 | H13: =MIN(4%,F13*125%) -> 0.019375 | J13: =IF(I13="","",I13-F13) | K13: =IF(I13="","Not entered",IF(I13<G13,"Below band",IF(I13>H13,"Above band","Within band"))) -> Not entered | L13: =IF(I13="","Enter actual weight",IF(I13<G13,"Review / Add",IF(I13>H13,"Review / Trim","No action"))) -> Enter actual weight | M13: Unassigned | N13: Current
A14: Growth Compounders | B14: AVGO | C14: Broadcom Inc. | D14: Equity | E14: Semiconductor and infrastructure-software compounder | F14: 0.0302 | G14: =MAX(1%,F14*75%) -> 0.02265 | H14: =MIN(4%,F14*125%) -> 0.03775 | J14: =IF(I14="","",I14-F14) | K14: =IF(I14="","Not entered",IF(I14<G14,"Below band",IF(I14>H14,"Above band","Within band"))) -> Not entered | L14: =IF(I14="","Enter actual weight",IF(I14<G14,"Review / Add",IF(I14>H14,"Review / Trim","No action"))) -> Enter actual weight | M14: Unassigned | N14: Current
A15: Growth Compounders | B15: LLY | C15: Eli Lilly and Company | D15: Equity | E15: Healthcare innovation compounder | F15: 0.0302 | G15: =MAX(1%,F15*75%) -> 0.02265 | H15: =MIN(4%,F15*125%) -> 0.03775 | J15: =IF(I15="","",I15-F15) | K15: =IF(I15="","Not entered",IF(I15<G15,"Below band",IF(I15>H15,"Above band","Within band"))) -> Not entered | L15: =IF(I15="","Enter actual weight",IF(I15<G15,"Review / Add",IF(I15>H15,"Review / Trim","No action"))) -> Enter actual weight | M15: Unassigned | N15: Current
A16: Growth Compounders | B16: NVDA | C16: NVIDIA Corporation | D16: Equity | E16: AI compute growth engine | F16: 0.0268 | G16: =MAX(1%,F16*75%) -> 0.0201 | H16: =MIN(4%,F16*125%) -> 0.0335 | J16: =IF(I16="","",I16-F16) | K16: =IF(I16="","Not entered",IF(I16<G16,"Below band",IF(I16>H16,"Above band","Within band"))) -> Not entered | L16: =IF(I16="","Enter actual weight",IF(I16<G16,"Review / Add",IF(I16>H16,"Review / Trim","No action"))) -> Enter actual weight | M16: Unassigned | N16: Current
... A51: Income & Risk Management | B51: PFF | C51: iShares Preferred and Income Securities ETF | D51: ETF | E51: Preferred securities income diversification | F51: 0.0302 | G51: =MAX(1%,F51*75%) -> 0.02265 | H51: =MIN(4%,F51*125%) -> 0.03775 | J51: =IF(I51="","",I51-F51) | K51: =IF(I51="","Not entered",IF(I51<G51,"Below band",IF(I51>H51,"Above band","Within band"))) -> Not entered | L51: =IF(I51="","Enter actual weight",IF(I51<G51,"Review / Add",IF(I51>H51,"Review / Trim","No action"))) -> Enter actual weight | M51: Unassigned | N51: Current
A53: PORTFOLIO TOTAL | F53: =SUM(F5:F51) -> 1 | I53: =SUM(I5:I51) -> 0 | J53: =I53-F53 -> -1 | K53: =IF(ABS(F53-100%)<0.000001,"Certified 100.00%","ERROR") -> Certified 100.00%

Sheet Sleeve Summary
A1: MFPDF v1.0 — Sleeve Allocation Summary
A3: Production Sleeve | B3: Positions | C3: Equities | D3: ETFs | E3: Target Allocation | F3: Share of Portfolio
A4: Strategic Anchors | B4: =COUNTIF('Certified Allocation'!$A$5:$A$51,A4) -> 9 | C4: =COUNTIFS('Certified Allocation'!$A$5:$A$51,A4,'Certified Allocation'!$D$5:$D$51,"Equity") -> 9 | D4: =COUNTIFS('Certified Allocation'!$A$5:$A$51,A4,'Certified Allocation'!$D$5:$D$51,"ETF") -> 0 | E4: =SUMIF('Certified Allocation'!$A$5:$A$51,A4,'Certified Allocation'!$F$5:$F$51) -> 0.2251 | F4: =E4 -> 0.2251
A5: Growth Compounders | B5: =COUNTIF('Certified Allocation'!$A$5:$A$51,A5) -> 6 | C5: =COUNTIFS('Certified Allocation'!$A$5:$A$51,A5,'Certified Allocation'!$D$5:$D$51,"Equity") -> 6 | D5: =COUNTIFS('Certified Allocation'!$A$5:$A$51,A5,'Certified Allocation'!$D$5:$D$51,"ETF") -> 0 | E5: =SUMIF('Certified Allocation'!$A$5:$A$51,A5,'Certified Allocation'!$F$5:$F$51) -> 0.1339 | F5: =E5 -> 0.1339
A6: Digital Infrastructure & AI | B6: =COUNTIF('Certified Allocation'!$A$5:$A$51,A6) -> 8 | C6: =COUNTIFS('Certified Allocation'!$A$5:$A$51,A6,'Certified Allocation'!$D$5:$D$51,"Equity") -> 8 | D6: =COUNTIFS('Certified Allocation'!$A$5:$A$51,A6,'Certified Allocation'!$D$5:$D$51,"ETF") -> 0 | E6: =SUMIF('Certified Allocation'!$A$5:$A$51,A6,'Certified Allocation'!$F$5:$F$51) -> 0.129 | F6: =E6 -> 0.129
A7: Industrials & Infrastructure | B7: =COUNTIF('Certified Allocation'!$A$5:$A$51,A7) -> 9 | C7: =COUNTIFS('Certified Allocation'!$A$5:$A$51,A7,'Certified Allocation'!$D$5:$D$51,"Equity") -> 9 | D7: =COUNTIFS('Certified Allocation'!$A$5:$A$51,A7,'Certified Allocation'!$D$5:$D$51,"ETF") -> 0 | E7: =SUMIF('Certified Allocation'!$A$5:$A$51,A7,'Certified Allocation'!$F$5:$F$51) -> 0.1711 | F7: =E7 -> 0.1711
A8: Financial Infrastructure | B8: =COUNTIF('Certified Allocation'!$A$5:$A$51,A8) -> 5 | C8: =COUNTIFS('Certified Allocation'!$A$5:$A$51,A8,'Certified Allocation'!$D$5:$D$51,"Equity") -> 4 | D8: =COUNTIFS('Certified Allocation'!$A$5:$A$51,A8,'Certified Allocation'!$D$5:$D$51,"ETF") -> 1 | E8: =SUMIF('Certified Allocation'!$A$5:$A$51,A8,'Certified Allocation'!$F$5:$F$51) -> 0.097 | F8: =E8 -> 0.097
A9: Healthcare Leadership | B9: =COUNTIF('Certified Allocation'!$A$5:$A$51,A9) -> 2 | C9: =COUNTIFS('Certified Allocation'!$A$5:$A$51,A9,'Certified Allocation'!$D$5:$D$51,"Equity") -> 1 | D9: =COUNTIFS('Certified Allocation'!$A$5:$A$51,A9,'Certified Allocation'!$D$5:$D$51,"ETF") -> 1 | E9: =SUMIF('Certified Allocation'!$A$5:$A$51,A9,'Certified Allocation'!$F$5:$F$51) -> 0.0361 | F9: =E9 -> 0.0361
A10: Energy & Natural Resources | B10: =COUNTIF('Certified Allocation'!$A$5:$A$51,A10) -> 5 | C10: =COUNTIFS('Certified Allocation'!$A$5:$A$51,A10,'Certified Allocation'!$D$5:$D$51,"Equity") -> 3 | D10: =COUNTIFS('Certified Allocation'!$A$5:$A$51,A10,'Certified Allocation'!$D$5:$D$51,"ETF") -> 2 | E10: =SUMIF('Certified Allocation'!$A$5:$A$51,A10,'Certified Allocation'!$F$5:$F$51) -> 0.1172 | F10: =E10 -> 0.1172
A11: Income & Risk Management | B11: =COUNTIF('Certified Allocation'!$A$5:$A$51,A11) -> 3 | C11: =COUNTIFS('Certified Allocation'!$A$5:$A$51,A11,'Certified Allocation'!$D$5:$D$51,"Equity") -> 0 | D11: =COUNTIFS('Certified Allocation'!$A$5:$A$51,A11,'Certified Allocation'!$D$5:$D$51,"ETF") -> 3 | E11: =SUMIF('Certified Allocation'!$A$5:$A$51,A11,'Certified Allocation'!$F$5:$F$51) -> 0.0906 | F11: =E11 -> 0.0906
A12: TOTAL | B12: =SUM(B4:B11) -> 47 | C12: =SUM(C4:C11) -> 40 | D12: =SUM(D4:D11) -> 7 | E12: =SUM(E4:E11) -> 1 | F12: =SUM(F4:F11) -> 1

Sheet Rebalancing
A1: MFPDF v1.0 — Rebalancing Control Framework
A3: Control | B3: Definition | C3: Formula / Trigger | D3: Required Action | E3: Authority | F3: Frequency | G3: Status
A4: Target weight | B4: Certified strategic allocation for each holding | C4: Certified Allocation column F | D4: Benchmark actual portfolio | E4: MFPDF v1.0 | F4: Continuous | G4: Active
A5: Lower band | B5: 75% of target, floored at 1.00% | C5: MAX(1%, Target × 75%) | D5: Review potential add | E5: Stewardship Committee | F5: When breached | G5: Active
A6: Upper band | B6: 125% of target, capped at 4.00% | C6: MIN(4%, Target × 125%) | D6: Review potential trim | E6: Stewardship Committee | F6: When breached | G6: Active
A7: Actual weight | B7: Current account/model weight | C7: User-entered in column I | D7: Update before review | E7: Portfolio Operations | F7: Weekly / as needed | G7: Input required
A8: Automatic trading | B8: Not authorized | C8: No automatic execution | D8: Committee review required | E8: Stewardship Committee | F8: As needed | G8: Prohibited
A9: Scheduled review | B9: Portfolio-level reconciliation | C9: Quarterly plus material-event review | D9: Rebalance only when justified | E9: Stewardship Committee | F9: Quarterly | G9: Active

Sheet Sources & Certification
A1: Sources, Reconciliation Record & Certification
A3: Source / Record | B3: Use | C3: Key Finding | D3: Disposition | E3: Reference | F3: Status
A4: MQOC-005 Portfolio B YCharts Export | B4: Canonical constituent list | C4: 47 symbols including MMC | D4: Adopted as Portfolio B constituent control | E4: ChatGPT Library: MQOC-005_Portfolio_B_YCharts_Export.csv | F4: Certified
A5: MQOC-006 Provisional Optimized Portfolio Weights | B5: Empirical target weights | C5: 46 named positions + 2.00% placeholder | D5: Placeholder reconciled to MMC; all other weights unchanged | E5: ChatGPT Library: MQOC-006_Provisional_Optimized_Portfolio_Weights.xlsx | F5: Reconciled
A6: Prior allocation workbook | B6: Preliminary 56-position ranges | C6: Different draft portfolio; not Portfolio B | D6: Declared obsolete and superseded | E6: Manifest_Flagship_Portfolio_V1_0_Allocation_Schedule.xlsx | F6: Obsolete
A7: Position count reconciliation | B7: Constituent classification | C7: 40 equities + 7 ETFs = 47 positions | D7: Workbook reflects actual Portfolio B export | E7: Certified Allocation sheet | F7: Verified
A8: Weight reconciliation | B8: Portfolio total | C8: 100.00% after MMC substitution | D8: No residual or unallocated cash | E8: Certified Allocation total | F8: Verified
A9: Certification date | B9: Founders Edition operational record | C9: 46223 | D9: Effective upon publication | E9: MPEC / MFPDF record | F9: Certified
A11: Certification Statement
A12: Portfolio B is designated as the sole canonical Manifest Flagship Portfolio implementation. This workbook is the authoritative MFPDF Founders Edition v1.0 target allocation schedule for MWIR benchmarking, stewardship review, optimization, Monte Carlo analysis, performance attribution and institutional publication.
A15: MOPS-002 Workspace Certification
A16: Resolution | B16: Use | C16: Certified Scope | D16: Disposition | E16: Reference | F16: Status
A17: MOPS-002-FR-001 | B17: Workspace architecture certification | C17: PEW-001 through PEW-007, control principles and workflow | D17: Adopted, certified and frozen effective July 26, 2026 | E17: 15 MOPS-002 Freeze Record | F17: Certified & Frozen
A19: Workspace certification does not certify a portfolio scenario, a trade, or a new MFPDF issuance. The existing certified Portfolio B allocation remains unchanged.
A20: MOPS-003 Research Command Center — Construction Record
A21: Resolution / Module | B21: Use | C21: Installed Scope | D21: Disposition | E21: Reference | F21: Status
A22: MOPS-003 / RCC-001 | B22: Executive research command view | C22: Research readiness, exception queue, module roadmap and referrals | D22: Installed as construction candidate | E22: 16 RCC-001 Control Center | F22: Active — Installed
A23: MOPS-003 / RCC-002 | B23: Research intake and chain-of-evidence control | C23: Evidence ledger, verification, materiality, routing and referral gates | D23: Installed as construction candidate | E23: 17 RCC-002 Control Center / 18 RCC-002 Evidence Ledger | F23: Active — Installed
A24: MOPS-003 / RCC-003 | B24: MIAR dossier identity, freshness and review control | C24: 47-holding MIAR registry, review log, scores, cadence, exception controls and RCC-007 referral state | D24: Installed as construction candidate | E24: 19 RCC-003 Control Center / 20 RCC-003 MIAR Registry / 21 RCC-003 MIAR Review Log | F24: Active — Installed
A25: MOPS-003 / RCC-004 | B25: MASR registry, candidate stage-gate and PEW referral control | C25: 150-slot controlled MASR registry, 47 certified holdings seeded, 200-row candidate pipeline, eligibility and exception gates, committee disposition and PEW-004 linkage | D25: Installed as construction candidate | E25: 22 RCC-004 Control Center / 23 RCC-004 MASR Registry / 24 RCC-004 Candidate Pipeline | F25: Active — Installed
A26: MOPS-003 remains in construction and is not frozen. RCC-001 through RCC-004 certify neither a research conclusion nor a portfolio action. They create an auditable evidence-to-dossier-to-registry-to-candidate control path while preserving the certified MFPDF as the sole portfolio system of record.

Sheet 99 Dashboard Data
A1: Sleeve | B1: Target | C1: Actual | D1: Variance | R1: Rank | S1: Symbol | T1: Security | U1: Weight | V1: Portfolio Role | W1: Conviction
A2: ='Sleeve Summary'!A4 -> Strategic Anchors | B2: ='Sleeve Summary'!E4 -> 0.2251 | C2: =IF($B$61=0,SUMIF('Certified Allocation'!$A$5:$A$51,A2,'Certified Allocation'!$I$5:$I$51),0) -> 0 | D2: =C2-B2 -> -0.2251 | R2: 1 | S2: =IFERROR(INDEX($B$12:$B$58,MATCH(R2,$H$12:$H$58,0)),"") -> BRK.B | T2: =IFERROR(INDEX($C$12:$C$58,MATCH(R2,$H$12:$H$58,0)),"") -> Berkshire Hathaway Inc. Class B | U2: =IFERROR(INDEX($G$12:$G$58,MATCH(R2,$H$12:$H$58,0)),"") -> 0.0302 | V2: =IFERROR(INDEX($I$12:$I$58,MATCH(R2,$H$12:$H$58,0)),"") -> Diversified capital-allocation anchor | W2: =IFERROR(INDEX($J$12:$J$58,MATCH(R2,$H$12:$H$58,0)),"") -> Unassigned
A3: ='Sleeve Summary'!A5 -> Growth Compounders | B3: ='Sleeve Summary'!E5 -> 0.1339 | C3: =IF($B$61=0,SUMIF('Certified Allocation'!$A$5:$A$51,A3,'Certified Allocation'!$I$5:$I$51),0) -> 0 | D3: =C3-B3 -> -0.1339 | R3: 2 | S3: =IFERROR(INDEX($B$12:$B$58,MATCH(R3,$H$12:$H$58,0)),"") -> COST | T3: =IFERROR(INDEX($C$12:$C$58,MATCH(R3,$H$12:$H$58,0)),"") -> Costco Wholesale Corporation | U3: =IFERROR(INDEX($G$12:$G$58,MATCH(R3,$H$12:$H$58,0)),"") -> 0.0302 | V3: =IFERROR(INDEX($I$12:$I$58,MATCH(R3,$H$12:$H$58,0)),"") -> Consumer-resilience anchor | W3: =IFERROR(INDEX($J$12:$J$58,MATCH(R3,$H$12:$H$58,0)),"") -> Unassigned
A4: ='Sleeve Summary'!A6 -> Digital Infrastructure & AI | B4: ='Sleeve Summary'!E6 -> 0.129 | C4: =IF($B$61=0,SUMIF('Certified Allocation'!$A$5:$A$51,A4,'Certified Allocation'!$I$5:$I$51),0) -> 0 | D4: =C4-B4 -> -0.129 | R4: 3 | S4: =IFERROR(INDEX($B$12:$B$58,MATCH(R4,$H$12:$H$58,0)),"") -> JNJ | T4: =IFERROR(INDEX($C$12:$C$58,MATCH(R4,$H$12:$H$58,0)),"") -> Johnson & Johnson | U4: =IFERROR(INDEX($G$12:$G$58,MATCH(R4,$H$12:$H$58,0)),"") -> 0.0302 | V4: =IFERROR(INDEX($I$12:$I$58,MATCH(R4,$H$12:$H$58,0)),"") -> Healthcare and life-sciences resilience anchor | W4: =IFERROR(INDEX($J$12:$J$58,MATCH(R4,$H$12:$H$58,0)),"") -> Unassigned
A5: ='Sleeve Summary'!A7 -> Industrials & Infrastructure | B5: ='Sleeve Summary'!E7 -> 0.1711 | C5: =IF($B$61=0,SUMIF('Certified Allocation'!$A$5:$A$51,A5,'Certified Allocation'!$I$5:$I$51),0) -> 0 | D5: =C5-B5 -> -0.1711 | R5: 4 | S5: =IFERROR(INDEX($B$12:$B$58,MATCH(R5,$H$12:$H$58,0)),"") -> MSFT | T5: =IFERROR(INDEX($C$12:$C$58,MATCH(R5,$H$12:$H$58,0)),"") -> Microsoft Corporation | U5: =IFERROR(INDEX($G$12:$G$58,MATCH(R5,$H$12:$H$58,0)),"") -> 0.0302 | V5: =IFERROR(INDEX($I$12:$I$58,MATCH(R5,$H$12:$H$58,0)),"") -> Enterprise technology and AI platform anchor | W5: =IFERROR(INDEX($J$12:$J$58,MATCH(R5,$H$12:$H$58,0)),"") -> Unassigned
A6: ='Sleeve Summary'!A8 -> Financial Infrastructure | B6: ='Sleeve Summary'!E8 -> 0.097 | C6: =IF($B$61=0,SUMIF('Certified Allocation'!$A$5:$A$51,A6,'Certified Allocation'!$I$5:$I$51),0) -> 0 | D6: =C6-B6 -> -0.097 | R6: 5 | S6: =IFERROR(INDEX($B$12:$B$58,MATCH(R6,$H$12:$H$58,0)),"") -> AVGO | T6: =IFERROR(INDEX($C$12:$C$58,MATCH(R6,$H$12:$H$58,0)),"") -> Broadcom Inc. | U6: =IFERROR(INDEX($G$12:$G$58,MATCH(R6,$H$12:$H$58,0)),"") -> 0.0302 | V6: =IFERROR(INDEX($I$12:$I$58,MATCH(R6,$H$12:$H$58,0)),"") -> Semiconductor and infrastructure-software compounder | W6: =IFERROR(INDEX($J$12:$J$58,MATCH(R6,$H$12:$H$58,0)),"") -> Unassigned
A7: ='Sleeve Summary'!A9 -> Healthcare Leadership | B7: ='Sleeve Summary'!E9 -> 0.0361 | C7: =IF($B$61=0,SUMIF('Certified Allocation'!$A$5:$A$51,A7,'Certified Allocation'!$I$5:$I$51),0) -> 0 | D7: =C7-B7 -> -0.0361 | R7: 6 | S7: =IFERROR(INDEX($B$12:$B$58,MATCH(R7,$H$12:$H$58,0)),"") -> LLY | T7: =IFERROR(INDEX($C$12:$C$58,MATCH(R7,$H$12:$H$58,0)),"") -> Eli Lilly and Company | U7: =IFERROR(INDEX($G$12:$G$58,MATCH(R7,$H$12:$H$58,0)),"") -> 0.0302 | V7: =IFERROR(INDEX($I$12:$I$58,MATCH(R7,$H$12:$H$58,0)),"") -> Healthcare innovation compounder | W7: =IFERROR(INDEX($J$12:$J$58,MATCH(R7,$H$12:$H$58,0)),"") -> Unassigned
A8: ='Sleeve Summary'!A10 -> Energy & Natural Resources | B8: ='Sleeve Summary'!E10 -> 0.1172 | C8: =IF($B$61=0,SUMIF('Certified Allocation'!$A$5:$A$51,A8,'Certified Allocation'!$I$5:$I$51),0) -> 0 | D8: =C8-B8 -> -0.1172 | R8: 7 | S8: =IFERROR(INDEX($B$12:$B$58,MATCH(R8,$H$12:$H$58,0)),"") -> CME | T8: =IFERROR(INDEX($C$12:$C$58,MATCH(R8,$H$12:$H$58,0)),"") -> CME Group Inc. | U8: =IFERROR(INDEX($G$12:$G$58,MATCH(R8,$H$12:$H$58,0)),"") -> 0.0302 | V8: =IFERROR(INDEX($I$12:$I$58,MATCH(R8,$H$12:$H$58,0)),"") -> Market infrastructure and derivatives exchange | W8: =IFERROR(INDEX($J$12:$J$58,MATCH(R8,$H$12:$H$58,0)),"") -> Unassigned
A9: ='Sleeve Summary'!A11 -> Income & Risk Management | B9: ='Sleeve Summary'!E11 -> 0.0906 | C9: =IF($B$61=0,SUMIF('Certified Allocation'!$A$5:$A$51,A9,'Certified Allocation'!$I$5:$I$51),0) -> 0 | D9: =C9-B9 -> -0.0906 | R9: 8 | S9: =IFERROR(INDEX($B$12:$B$58,MATCH(R9,$H$12:$H$58,0)),"") -> LNG | T9: =IFERROR(INDEX($C$12:$C$58,MATCH(R9,$H$12:$H$58,0)),"") -> Cheniere Energy, Inc. | U9: =IFERROR(INDEX($G$12:$G$58,MATCH(R9,$H$12:$H$58,0)),"") -> 0.0302 | V9: =IFERROR(INDEX($I$12:$I$58,MATCH(R9,$H$12:$H$58,0)),"") -> LNG export infrastructure | W9: =IFERROR(INDEX($J$12:$J$58,MATCH(R9,$H$12:$H$58,0)),"") -> Unassigned
R10: 9 | S10: =IFERROR(INDEX($B$12:$B$58,MATCH(R10,$H$12:$H$58,0)),"") -> VPU | T10: =IFERROR(INDEX($C$12:$C$58,MATCH(R10,$H$12:$H$58,0)),"") -> Vanguard Utilities ETF | U10: =IFERROR(INDEX($G$12:$G$58,MATCH(R10,$H$12:$H$58,0)),"") -> 0.0302 | V10: =IFERROR(INDEX($I$12:$I$58,MATCH(R10,$H$12:$H$58,0)),"") -> Utilities and defensive infrastructure ETF | W10: =IFERROR(INDEX($J$12:$J$58,MATCH(R10,$H$12:$H$58,0)),"") -> Unassigned
A11: Source Row | B11: Symbol | C11: Security | D11: Sleeve | E11: Target | F11: Actual | G11: Ranking Weight | H11: Rank | I11: Portfolio Role | J11: Conviction | K11: Lower | L11: Upper | M11: Band Status | N11: Action | O11: Alert Score | P11: Alert Rank | R11: 10 | S11: =IFERROR(INDEX($B$12:$B$58,MATCH(R11,$H$12:$H$58,0)),"") -> JEPI | T11: =IFERROR(INDEX($C$12:$C$58,MATCH(R11,$H$12:$H$58,0)),"") -> JPMorgan Equity Premium Income ETF | U11: =IFERROR(INDEX($G$12:$G$58,MATCH(R11,$H$12:$H$58,0)),"") -> 0.0302 | V11: =IFERROR(INDEX($I$12:$I$58,MATCH(R11,$H$12:$H$58,0)),"") -> Diversified equity income and volatility moderation | W11: =IFERROR(INDEX($J$12:$J$58,MATCH(R11,$H$12:$H$58,0)),"") -> Unassigned
A12: 5 | B12: ='Certified Allocation'!B5 -> BRK.B | C12: ='Certified Allocation'!C5 -> Berkshire Hathaway Inc. Class B | D12: ='Certified Allocation'!A5 -> Strategic Anchors | E12: ='Certified Allocation'!F5 -> 0.0302 | F12: ='Certified Allocation'!I5 -> 0 | G12: =IF($B$61=0,F12,E12) -> 0.0302 | H12: =RANK(G12,$G$12:$G$58,0)+COUNTIF($G$12:G12,G12)-1 -> 1 | I12: ='Certified Allocation'!E5 -> Diversified capital-allocation anchor | J12: ='Certified Allocation'!M5 -> Unassigned | K12: ='Certified Allocation'!G5 -> 0.02265 | L12: ='Certified Allocation'!H5 -> 0.03775 | M12: ='Certified Allocation'!K5 -> Not entered | N12: ='Certified Allocation'!L5 -> Enter actual weight | O12: =IF(F12="",0,IF(OR(F12<K12,F12>L12),ABS(F12-E12),0)) -> 0.0302 | P12: =IF(O12=0,"",RANK(O12,$O$12:$O$58,0)+COUNTIF($O$12:O12,O12)-1) -> 1
A13: 6 | B13: ='Certified Allocation'!B6 -> COST | C13: ='Certified Allocation'!C6 -> Costco Wholesale Corporation | D13: ='Certified Allocation'!A6 -> Strategic Anchors | E13: ='Certified Allocation'!F6 -> 0.0302 | F13: ='Certified Allocation'!I6 -> 0 | G13: =IF($B$61=0,F13,E13) -> 0.0302 | H13: =RANK(G13,$G$12:$G$58,0)+COUNTIF($G$12:G13,G13)-1 -> 2 | I13: ='Certified Allocation'!E6 -> Consumer-resilience anchor | J13: ='Certified Allocation'!M6 -> Unassigned | K13: ='Certified Allocation'!G6 -> 0.02265 | L13: ='Certified Allocation'!H6 -> 0.03775 | M13: ='Certified Allocation'!K6 -> Not entered | N13: ='Certified Allocation'!L6 -> Enter actual weight | O13: =IF(F13="",0,IF(OR(F13<K13,F13>L13),ABS(F13-E13),0)) -> 0.0302 | P13: =IF(O13=0,"",RANK(O13,$O$12:$O$58,0)+COUNTIF($O$12:O13,O13)-1) -> 2
A14: 7 | B14: ='Certified Allocation'!B7 -> JNJ | C14: ='Certified Allocation'!C7 -> Johnson & Johnson | D14: ='Certified Allocation'!A7 -> Strategic Anchors | E14: ='Certified Allocation'!F7 -> 0.0302 | F14: ='Certified Allocation'!I7 -> 0 | G14: =IF($B$61=0,F14,E14) -> 0.0302 | H14: =RANK(G14,$G$12:$G$58,0)+COUNTIF($G$12:G14,G14)-1 -> 3 | I14: ='Certified Allocation'!E7 -> Healthcare and life-sciences resilience anchor | J14: ='Certified Allocation'!M7 -> Unassigned | K14: ='Certified Allocation'!G7 -> 0.02265 | L14: ='Certified Allocation'!H7 -> 0.03775 | M14: ='Certified Allocation'!K7 -> Not entered | N14: ='Certified Allocation'!L7 -> Enter actual weight | O14: =IF(F14="",0,IF(OR(F14<K14,F14>L14),ABS(F14-E14),0)) -> 0.0302 | P14: =IF(O14=0,"",RANK(O14,$O$12:$O$58,0)+COUNTIF($O$12:O14,O14)-1) -> 3 | R14: Rank | S14: Symbol | T14: Actual | U14: Target | V14: Variance | W14: Band Status | X14: Action
A15: 8 | B15: ='Certified Allocation'!B8 -> MSFT | C15: ='Certified Allocation'!C8 -> Microsoft Corporation | D15: ='Certified Allocation'!A8 -> Strategic Anchors | E15: ='Certified Allocation'!F8 -> 0.0302 | F15: ='Certified Allocation'!I8 -> 0 | G15: =IF($B$61=0,F15,E15) -> 0.0302 | H15: =RANK(G15,$G$12:$G$58,0)+COUNTIF($G$12:G15,G15)-1 -> 4 | I15: ='Certified Allocation'!E8 -> Enterprise technology and AI platform anchor | J15: ='Certified Allocation'!M8 -> Unassigned | K15: ='Certified Allocation'!G8 -> 0.02265 | L15: ='Certified Allocation'!H8 -> 0.03775 | M15: ='Certified Allocation'!K8 -> Not entered | N15: ='Certified Allocation'!L8 -> Enter actual weight | O15: =IF(F15="",0,IF(OR(F15<K15,F15>L15),ABS(F15-E15),0)) -> 0.0302 | P15: =IF(O15=0,"",RANK(O15,$O$12:$O$58,0)+COUNTIF($O$12:O15,O15)-1) -> 4 | R15: 1 | S15: =IFERROR(INDEX($B$12:$B$58,MATCH(R15,$P$12:$P$58,0)),"") -> BRK.B | T15: =IF(S15="","",INDEX($F$12:$F$58,MATCH(R15,$P$12:$P$58,0))) -> 0 | U15: =IF(S15="","",INDEX($E$12:$E$58,MATCH(R15,$P$12:$P$58,0))) -> 0.0302 | V15: =IF(S15="","",T15-U15) -> -0.0302 | W15: =IF(S15="","",INDEX($M$12:$M$58,MATCH(R15,$P$12:$P$58,0))) -> Not entered | X15: =IF(S15="","",INDEX($N$12:$N$58,MATCH(R15,$P$12:$P$58,0))) -> Enter actual weight
A16: 9 | B16: ='Certified Allocation'!B9 -> V | C16: ='Certified Allocation'!C9 -> Visa Inc. | D16: ='Certified Allocation'!A9 -> Strategic Anchors | E16: ='Certified Allocation'!F9 -> 0.0288 | F16: ='Certified Allocation'!I9 -> 0 | G16: =IF($B$61=0,F16,E16) -> 0.0288 | H16: =RANK(G16,$G$12:$G$58,0)+COUNTIF($G$12:G16,G16)-1 -> 15 | I16: ='Certified Allocation'!E9 -> Global payments infrastructure anchor | J16: ='Certified Allocation'!M9 -> Unassigned | K16: ='Certified Allocation'!G9 -> 0.0216 | L16: ='Certified Allocation'!H9 -> 0.036 | M16: ='Certified Allocation'!K9 -> Not entered | N16: ='Certified Allocation'!L9 -> Enter actual weight | O16: =IF(F16="",0,IF(OR(F16<K16,F16>L16),ABS(F16-E16),0)) -> 0.0288 | P16: =IF(O16=0,"",RANK(O16,$O$12:$O$58,0)+COUNTIF($O$12:O16,O16)-1) -> 15 | R16: 2 | S16: =IFERROR(INDEX($B$12:$B$58,MATCH(R16,$P$12:$P$58,0)),"") -> COST | T16: =IF(S16="","",INDEX($F$12:$F$58,MATCH(R16,$P$12:$P$58,0))) -> 0 | U16: =IF(S16="","",INDEX($E$12:$E$58,MATCH(R16,$P$12:$P$58,0))) -> 0.0302 | V16: =IF(S16="","",T16-U16) -> -0.0302 | W16: =IF(S16="","",INDEX($M$12:$M$58,MATCH(R16,$P$12:$P$58,0))) -> Not entered | X16: =IF(S16="","",INDEX($N$12:$N$58,MATCH(R16,$P$12:$P$58,0))) -> Enter actual weight
A17: 10 | B17: ='Certified Allocation'!B10 -> GOOGL | C17: ='Certified Allocation'!C10 -> Alphabet Inc. Class A | D17: ='Certified Allocation'!A10 -> Strategic Anchors | E17: ='Certified Allocation'!F10 -> 0.0284 | F17: ='Certified Allocation'!I10 -> 0 | G17: =IF($B$61=0,F17,E17) -> 0.0284 | H17: =RANK(G17,$G$12:$G$58,0)+COUNTIF($G$12:G17,G17)-1 -> 16 | I17: ='Certified Allocation'!E10 -> Digital platform and AI anchor | J17: ='Certified Allocation'!M10 -> Unassigned | K17: ='Certified Allocation'!G10 -> 0.0213 | L17: ='Certified Allocation'!H10 -> 0.0355 | M17: ='Certified Allocation'!K10 -> Not entered | N17: ='Certified Allocation'!L10 -> Enter actual weight | O17: =IF(F17="",0,IF(OR(F17<K17,F17>L17),ABS(F17-E17),0)) -> 0.0284 | P17: =IF(O17=0,"",RANK(O17,$O$12:$O$58,0)+COUNTIF($O$12:O17,O17)-1) -> 16 | R17: 3 | S17: =IFERROR(INDEX($B$12:$B$58,MATCH(R17,$P$12:$P$58,0)),"") -> JNJ | T17: =IF(S17="","",INDEX($F$12:$F$58,MATCH(R17,$P$12:$P$58,0))) -> 0 | U17: =IF(S17="","",INDEX($E$12:$E$58,MATCH(R17,$P$12:$P$58,0))) -> 0.0302 | V17: =IF(S17="","",T17-U17) -> -0.0302 | W17: =IF(S17="","",INDEX($M$12:$M$58,MATCH(R17,$P$12:$P$58,0))) -> Not entered | X17: =IF(S17="","",INDEX($N$12:$N$58,MATCH(R17,$P$12:$P$58,0))) -> Enter actual weight
A18: 11 | B18: ='Certified Allocation'!B11 -> MA | C18: ='Certified Allocation'!C11 -> Mastercard Incorporated | D18: ='Certified Allocation'!A11 -> Strategic Anchors | E18: ='Certified Allocation'!F11 -> 0.016 | F18: ='Certified Allocation'!I11 -> 0 | G18: =IF($B$61=0,F18,E18) -> 0.016 | H18: =RANK(G18,$G$12:$G$58,0)+COUNTIF($G$12:G18,G18)-1 -> 23 | I18: ='Certified Allocation'!E11 -> Global payments infrastructure anchor | J18: ='Certified Allocation'!M11 -> Unassigned | K18: ='Certified Allocation'!G11 -> 0.012 | L18: ='Certified Allocation'!H11 -> 0.02 | M18: ='Certified Allocation'!K11 -> Not entered | N18: ='Certified Allocation'!L11 -> Enter actual weight | O18: =IF(F18="",0,IF(OR(F18<K18,F18>L18),ABS(F18-E18),0)) -> 0.016 | P18: =IF(O18=0,"",RANK(O18,$O$12:$O$58,0)+COUNTIF($O$12:O18,O18)-1) -> 23 | R18: 4 | S18: =IFERROR(INDEX($B$12:$B$58,MATCH(R18,$P$12:$P$58,0)),"") -> MSFT | T18: =IF(S18="","",INDEX($F$12:$F$58,MATCH(R18,$P$12:$P$58,0))) -> 0 | U18: =IF(S18="","",INDEX($E$12:$E$58,MATCH(R18,$P$12:$P$58,0))) -> 0.0302 | V18: =IF(S18="","",T18-U18) -> -0.0302 | W18: =IF(S18="","",INDEX($M$12:$M$58,MATCH(R18,$P$12:$P$58,0))) -> Not entered | X18: =IF(S18="","",INDEX($N$12:$N$58,MATCH(R18,$P$12:$P$58,0))) -> Enter actual weight
A19: 12 | B19: ='Certified Allocation'!B12 -> AAPL | C19: ='Certified Allocation'!C12 -> Apple Inc. | D19: ='Certified Allocation'!A12 -> Strategic Anchors | E19: ='Certified Allocation'!F12 -> 0.0156 | F19: ='Certified Allocation'!I12 -> 0 | G19: =IF($B$61=0,F19,E19) -> 0.0156 | H19: =RANK(G19,$G$12:$G$58,0)+COUNTIF($G$12:G19,G19)-1 -> 24 | I19: ='Certified Allocation'!E12 -> Consumer technology ecosystem anchor | J19: ='Certified Allocation'!M12 -> Unassigned | K19: ='Certified Allocation'!G12 -> 0.0117 | L19: ='Certified Allocation'!H12 -> 0.0195 | M19: ='Certified Allocation'!K12 -> Not entered | N19: ='Certified Allocation'!L12 -> Enter actual weight | O19: =IF(F19="",0,IF(OR(F19<K19,F19>L19),ABS(F19-E19),0)) -> 0.0156 | P19: =IF(O19=0,"",RANK(O19,$O$12:$O$58,0)+COUNTIF($O$12:O19,O19)-1) -> 24 | R19: 5 | S19: =IFERROR(INDEX($B$12:$B$58,MATCH(R19,$P$12:$P$58,0)),"") -> AVGO | T19: =IF(S19="","",INDEX($F$12:$F$58,MATCH(R19,$P$12:$P$58,0))) -> 0 | U19: =IF(S19="","",INDEX($E$12:$E$58,MATCH(R19,$P$12:$P$58,0))) -> 0.0302 | V19: =IF(S19="","",T19-U19) -> -0.0302 | W19: =IF(S19="","",INDEX($M$12:$M$58,MATCH(R19,$P$12:$P$58,0))) -> Not entered | X19: =IF(S19="","",INDEX($N$12:$N$58,MATCH(R19,$P$12:$P$58,0))) -> Enter actual weight
A20: 13 | B20: ='Certified Allocation'!B13 -> AMZN | C20: ='Certified Allocation'!C13 -> Amazon.com, Inc. | D20: ='Certified Allocation'!A13 -> Strategic Anchors | E20: ='Certified Allocation'!F13 -> 0.0155 | F20: ='Certified Allocation'!I13 -> 0 | G20: =IF($B$61=0,F20,E20) -> 0.0155 | H20: =RANK(G20,$G$12:$G$58,0)+COUNTIF($G$12:G20,G20)-1 -> 43 | I20: ='Certified Allocation'!E13 -> Cloud, commerce and logistics anchor | J20: ='Certified Allocation'!M13 -> Unassigned | K20: ='Certified Allocation'!G13 -> 0.011625 | L20: ='Certified Allocation'!H13 -> 0.019375 | M20: ='Certified Allocation'!K13 -> Not entered | N20: ='Certified Allocation'!L13 -> Enter actual weight | O20: =IF(F20="",0,IF(OR(F20<K20,F20>L20),ABS(F20-E20),0)) -> 0.0155 | P20: =IF(O20=0,"",RANK(O20,$O$12:$O$58,0)+COUNTIF($O$12:O20,O20)-1) -> 43
A21: 14 | B21: ='Certified Allocation'!B14 -> AVGO | C21: ='Certified Allocation'!C14 -> Broadcom Inc. | D21: ='Certified Allocation'!A14 -> Growth Compounders | E21: ='Certified Allocation'!F14 -> 0.0302 | F21: ='Certified Allocation'!I14 -> 0 | G21: =IF($B$61=0,F21,E21) -> 0.0302 | H21: =RANK(G21,$G$12:$G$58,0)+COUNTIF($G$12:G21,G21)-1 -> 5 | I21: ='Certified Allocation'!E14 -> Semiconductor and infrastructure-software compounder | J21: ='Certified Allocation'!M14 -> Unassigned | K21: ='Certified Allocation'!G14 -> 0.02265 | L21: ='Certified Allocation'!H14 -> 0.03775 | M21: ='Certified Allocation'!K14 -> Not entered | N21: ='Certified Allocation'!L14 -> Enter actual weight | O21: =IF(F21="",0,IF(OR(F21<K21,F21>L21),ABS(F21-E21),0)) -> 0.0302 | P21: =IF(O21=0,"",RANK(O21,$O$12:$O$58,0)+COUNTIF($O$12:O21,O21)-1) -> 5
A22: 15 | B22: ='Certified Allocation'!B15 -> LLY | C22: ='Certified Allocation'!C15 -> Eli Lilly and Company | D22: ='Certified Allocation'!A15 -> Growth Compounders | E22: ='Certified Allocation'!F15 -> 0.0302 | F22: ='Certified Allocation'!I15 -> 0 | G22: =IF($B$61=0,F22,E22) -> 0.0302 | H22: =RANK(G22,$G$12:$G$58,0)+COUNTIF($G$12:G22,G22)-1 -> 6 | I22: ='Certified Allocation'!E15 -> Healthcare innovation compounder | J22: ='Certified Allocation'!M15 -> Unassigned | K22: ='Certified Allocation'!G15 -> 0.02265 | L22: ='Certified Allocation'!H15 -> 0.03775 | M22: ='Certified Allocation'!K15 -> Not entered | N22: ='Certified Allocation'!L15 -> Enter actual weight | O22: =IF(F22="",0,IF(OR(F22<K22,F22>L22),ABS(F22-E22),0)) -> 0.0302 | P22: =IF(O22=0,"",RANK(O22,$O$12:$O$58,0)+COUNTIF($O$12:O22,O22)-1) -> 6
A23: 16 | B23: ='Certified Allocation'!B16 -> NVDA | C23: ='Certified Allocation'!C16 -> NVIDIA Corporation | D23: ='Certified Allocation'!A16 -> Growth Compounders | E23: ='Certified Allocation'!F16 -> 0.0268 | F23: ='Certified Allocation'!I16 -> 0 | G23: =IF($B$61=0,F23,E23) -> 0.0268 | H23: =RANK(G23,$G$12:$G$58,0)+COUNTIF($G$12:G23,G23)-1 -> 17 | I23: ='Certified Allocation'!E16 -> AI compute growth engine | J23: ='Certified Allocation'!M16 -> Unassigned | K23: ='Certified Allocation'!G16 -> 0.0201 | L23: ='Certified Allocation'!H16 -> 0.0335 | M23: ='Certified Allocation'!K16 -> Not entered | N23: ='Certified Allocation'!L16 -> Enter actual weight | O23: =IF(F23="",0,IF(OR(F23<K23,F23>L23),ABS(F23-E23),0)) -> 0.0268 | P23: =IF(O23=0,"",RANK(O23,$O$12:$O$58,0)+COUNTIF($O$12:O23,O23)-1) -> 17
A24: 17 | B24: ='Certified Allocation'!B17 -> HD | C24: ='Certified Allocation'!C17 -> The Home Depot, Inc. | D24: ='Certified Allocation'!A17 -> Growth Compounders | E24: ='Certified Allocation'!F17 -> 0.0156 | F24: ='Certified Allocation'!I17 -> 0 | G24: =IF($B$61=0,F24,E24) -> 0.0156 | H24: =RANK(G24,$G$12:$G$58,0)+COUNTIF($G$12:G24,G24)-1 -> 25 | I24: ='Certified Allocation'!E17 -> Housing and professional distribution compounder | J24: ='Certified Allocation'!M17 -> Unassigned | K24: ='Certified Allocation'!G17 -> 0.0117 | L24: ='Certified Allocation'!H17 -> 0.0195 | M24: ='Certified Allocation'!K17 -> Not entered | N24: ='Certified Allocation'!L17 -> Enter actual weight | O24: =IF(F24="",0,IF(OR(F24<K24,F24>L24),ABS(F24-E24),0)) -> 0.0156 | P24: =IF(O24=0,"",RANK(O24,$O$12:$O$58,0)+COUNTIF($O$12:O24,O24)-1) -> 25
A25: 18 | B25: ='Certified Allocation'!B18 -> META | C25: ='Certified Allocation'!C18 -> Meta Platforms, Inc. | D25: ='Certified Allocation'!A18 -> Growth Compounders | E25: ='Certified Allocation'!F18 -> 0.0156 | F25: ='Certified Allocation'!I18 -> 0 | G25: =IF($B$61=0,F25,E25) -> 0.0156 | H25: =RANK(G25,$G$12:$G$58,0)+COUNTIF($G$12:G25,G25)-1 -> 26 | I25: ='Certified Allocation'!E18 -> Digital platform and AI compounder | J25: ='Certified Allocation'!M18 -> Unassigned | K25: ='Certified Allocation'!G18 -> 0.0117 | L25: ='Certified Allocation'!H18 -> 0.0195 | M25: ='Certified Allocation'!K18 -> Not entered | N25: ='Certified Allocation'!L18 -> Enter actual weight | O25: =IF(F25="",0,IF(OR(F25<K25,F25>L25),ABS(F25-E25),0)) -> 0.0156 | P25: =IF(O25=0,"",RANK(O25,$O$12:$O$58,0)+COUNTIF($O$12:O25,O25)-1) -> 26
A26: 19 | B26: ='Certified Allocation'!B19 -> ANET | C26: ='Certified Allocation'!C19 -> Arista Networks, Inc. | D26: ='Certified Allocation'!A19 -> Growth Compounders | E26: ='Certified Allocation'!F19 -> 0.0155 | F26: ='Certified Allocation'!I19 -> 0 | G26: =IF($B$61=0,F26,E26) -> 0.0155 | H26: =RANK(G26,$G$12:$G$58,0)+COUNTIF($G$12:G26,G26)-1 -> 44 | I26: ='Certified Allocation'!E19 -> AI networking compounder | J26: ='Certified Allocation'!M19 -> Unassigned | K26: ='Certified Allocation'!G19 -> 0.011625 | L26: ='Certified Allocation'!H19 -> 0.019375 | M26: ='Certified Allocation'!K19 -> Not entered | N26: ='Certified Allocation'!L19 -> Enter actual weight | O26: =IF(F26="",0,IF(OR(F26<K26,F26>L26),ABS(F26-E26),0)) -> 0.0155 | P26: =IF(O26=0,"",RANK(O26,$O$12:$O$58,0)+COUNTIF($O$12:O26,O26)-1) -> 44
A27: 20 | B27: ='Certified Allocation'!B20 -> PANW | C27: ='Certified Allocation'!C20 -> Palo Alto Networks, Inc. | D27: ='Certified Allocation'!A20 -> Digital Infrastructure & AI | E27: ='Certified Allocation'!F20 -> 0.0199 | F27: ='Certified Allocation'!I20 -> 0 | G27: =IF($B$61=0,F27,E27) -> 0.0199 | H27: =RANK(G27,$G$12:$G$58,0)+COUNTIF($G$12:G27,G27)-1 -> 21 | I27: ='Certified Allocation'!E20 -> Cybersecurity infrastructure leader | J27: ='Certified Allocation'!M20 -> Unassigned | K27: ='Certified Allocation'!G20 -> 0.014925 | L27: ='Certified Allocation'!H20 -> 0.024875 | M27: ='Certified Allocation'!K20 -> Not entered | N27: ='Certified Allocation'!L20 -> Enter actual weight | O27: =IF(F27="",0,IF(OR(F27<K27,F27>L27),ABS(F27-E27),0)) -> 0.0199 | P27: =IF(O27=0,"",RANK(O27,$O$12:$O$58,0)+COUNTIF($O$12:O27,O27)-1) -> 21
A28: 21 | B28: ='Certified Allocation'!B21 -> AMAT | C28: ='Certified Allocation'!C21 -> Applied Materials, Inc. | D28: ='Certified Allocation'!A21 -> Digital Infrastructure & AI | E28: ='Certified Allocation'!F21 -> 0.0156 | F28: ='Certified Allocation'!I21 -> 0 | G28: =IF($B$61=0,F28,E28) -> 0.0156 | H28: =RANK(G28,$G$12:$G$58,0)+COUNTIF($G$12:G28,G28)-1 -> 27 | I28: ='Certified Allocation'!E21 -> Semiconductor equipment enabler | J28: ='Certified Allocation'!M21 -> Unassigned | K28: ='Certified Allocation'!G21 -> 0.0117 | L28: ='Certified Allocation'!H21 -> 0.0195 | M28: ='Certified Allocation'!K21 -> Not entered | N28: ='Certified Allocation'!L21 -> Enter actual weight | O28: =IF(F28="",0,IF(OR(F28<K28,F28>L28),ABS(F28-E28),0)) -> 0.0156 | P28: =IF(O28=0,"",RANK(O28,$O$12:$O$58,0)+COUNTIF($O$12:O28,O28)-1) -> 27
A29: 22 | B29: ='Certified Allocation'!B22 -> CSCO | C29: ='Certified Allocation'!C22 -> Cisco Systems, Inc. | D29: ='Certified Allocation'!A22 -> Digital Infrastructure & AI | E29: ='Certified Allocation'!F22 -> 0.0156 | F29: ='Certified Allocation'!I22 -> 0 | G29: =IF($B$61=0,F29,E29) -> 0.0156 | H29: =RANK(G29,$G$12:$G$58,0)+COUNTIF($G$12:G29,G29)-1 -> 28 | I29: ='Certified Allocation'!E22 -> Enterprise networking and secure infrastructure | J29: ='Certified Allocation'!M22 -> Unassigned | K29: ='Certified Allocation'!G22 -> 0.0117 | L29: ='Certified Allocation'!H22 -> 0.0195 | M29: ='Certified Allocation'!K22 -> Not entered | N29: ='Certified Allocation'!L22 -> Enter actual weight | O29: =IF(F29="",0,IF(OR(F29<K29,F29>L29),ABS(F29-E29),0)) -> 0.0156 | P29: =IF(O29=0,"",RANK(O29,$O$12:$O$58,0)+COUNTIF($O$12:O29,O29)-1) -> 28
A30: 23 | B30: ='Certified Allocation'!B23 -> KLAC | C30: ='Certified Allocation'!C23 -> KLA Corporation | D30: ='Certified Allocation'!A23 -> Digital Infrastructure & AI | E30: ='Certified Allocation'!F23 -> 0.0156 | F30: ='Certified Allocation'!I23 -> 0 | G30: =IF($B$61=0,F30,E30) -> 0.0156 | H30: =RANK(G30,$G$12:$G$58,0)+COUNTIF($G$12:G30,G30)-1 -> 29 | I30: ='Certified Allocation'!E23 -> Semiconductor process-control enabler | J30: ='Certified Allocation'!M23 -> Unassigned | K30: ='Certified Allocation'!G23 -> 0.0117 | L30: ='Certified Allocation'!H23 -> 0.0195 | M30: ='Certified Allocation'!K23 -> Not entered | N30: ='Certified Allocation'!L23 -> Enter actual weight | O30: =IF(F30="",0,IF(OR(F30<K30,F30>L30),ABS(F30-E30),0)) -> 0.0156 | P30: =IF(O30=0,"",RANK(O30,$O$12:$O$58,0)+COUNTIF($O$12:O30,O30)-1) -> 29
A31: 24 | B31: ='Certified Allocation'!B24 -> MU | C31: ='Certified Allocation'!C24 -> Micron Technology, Inc. | D31: ='Certified Allocation'!A24 -> Digital Infrastructure & AI | E31: ='Certified Allocation'!F24 -> 0.0156 | F31: ='Certified Allocation'!I24 -> 0 | G31: =IF($B$61=0,F31,E31) -> 0.0156 | H31: =RANK(G31,$G$12:$G$58,0)+COUNTIF($G$12:G31,G31)-1 -> 30 | I31: ='Certified Allocation'!E24 -> Memory and AI data-cycle enabler | J31: ='Certified Allocation'!M24 -> Unassigned | K31: ='Certified Allocation'!G24 -> 0.0117 | L31: ='Certified Allocation'!H24 -> 0.0195 | M31: ='Certified Allocation'!K24 -> Not entered | N31: ='Certified Allocation'!L24 -> Enter actual weight | O31: =IF(F31="",0,IF(OR(F31<K31,F31>L31),ABS(F31-E31),0)) -> 0.0156 | P31: =IF(O31=0,"",RANK(O31,$O$12:$O$58,0)+COUNTIF($O$12:O31,O31)-1) -> 30
... A58: 51 | B58: ='Certified Allocation'!B51 -> PFF | C58: ='Certified Allocation'!C51 -> iShares Preferred and Income Securities ETF | D58: ='Certified Allocation'!A51 -> Income & Risk Management | E58: ='Certified Allocation'!F51 -> 0.0302 | F58: ='Certified Allocation'!I51 -> 0 | G58: =IF($B$61=0,F58,E58) -> 0.0302 | H58: =RANK(G58,$G$12:$G$58,0)+COUNTIF($G$12:G58,G58)-1 -> 12 | I58: ='Certified Allocation'!E51 -> Preferred securities income diversification | J58: ='Certified Allocation'!M51 -> Unassigned | K58: ='Certified Allocation'!G51 -> 0.02265 | L58: ='Certified Allocation'!H51 -> 0.03775 | M58: ='Certified Allocation'!K51 -> Not entered | N58: ='Certified Allocation'!L51 -> Enter actual weight | O58: =IF(F58="",0,IF(OR(F58<K58,F58>L58),ABS(F58-E58),0)) -> 0.0302 | P58: =IF(O58=0,"",RANK(O58,$O$12:$O$58,0)+COUNTIF($O$12:O58,O58)-1) -> 12
A60: Dashboard Metric | B60: Value
A61: Missing Actual Weights | B61: =COUNTBLANK('Certified Allocation'!I5:I51) -> 47
A62: Band Breaches | B62: =COUNTIF('Certified Allocation'!K5:K51,"Below band")+COUNTIF('Certified Allocation'!K5:K51,"Above band") -> 0
A63: Actual Portfolio Total | B63: =SUM('Certified Allocation'!I5:I51) -> 0
A64: Data Completeness | B64: =(47-B61)/47 -> 0
A65: Ranking Basis | B65: =IF(B61=0,"Actual Weight","Target Weight") -> Target Weight
A66: Open Research Decisions | B66: =COUNTIF('03 Research Intelligence'!G7:G14,"Decision Required")+COUNTIF('03 Research Intelligence'!G43:G50,"Decision Required")+COUNTIF('03 Research Intelligence'!G67:G74,"Decision Required")+COUNTIF('Certified Allocation'!N5:N51,"Decision Required") -> 0
A67: Open Operating Actions | B67: =COUNTIF('04 Committee Operations'!G7:G20,"Open")+COUNTIF('04 Committee Operations'!G7:G20,"In Progress")+COUNTIF('04 Committee Operations'!G7:G20,"Planned") -> 4
A68: Committee-Decision Actions | B68: =COUNTIFS('04 Committee Operations'!H7:H20,"Yes",'04 Committee Operations'!G7:G20,"Open")+COUNTIFS('04 Committee Operations'!H7:H20,"Yes",'04 Committee Operations'!G7:G20,"In Progress") -> 0

Sheet 06 PEW Control Center
A1: MOPS-002 — PORTFOLIO ENGINEERING WORKSPACE (PEW)
A2: Executive control center for mandate, sleeve, role, candidate, conviction, allocation and certification decisions
A3: PEW-001–PEW-007 | Founders Edition v1.0 — CERTIFIED & FROZEN | Certified MFPDF remains the sole system of record
A4: EXECUTIVE ENGINEERING STATE — WORKSPACE CERTIFIED & FROZEN | R4: Sleeve | S4: Certified Target | T4: Scenario Allocation
A5: CURRENT IMPLEMENTATION STATE | G5: PRIMARY REQUIRED ACTION | L5: GOVERNANCE | R5: ='08 Sleeve Architecture'!A5 -> Strategic Anchors | S5: ='08 Sleeve Architecture'!F5 -> 0.2251 | T5: ='08 Sleeve Architecture'!H5 -> 0.2251
A6: ='13 Validation & Cert'!J12 -> NOT READY | G6: =IF(COUNTA('Certified Allocation'!I5:I51)<47,"Load all 47 current actual portfolio weights",IF(COUNTIF('11 Conviction'!H5:H51,"<>Unassigned")<47,"Assign effective conviction tiers to all active holdings",IF('12 Allocation Lab'!K6=0,"No allocation redesign is currently proposed","Resolve scenario evidence and committee decisions"))) -> Load all 47 current actual portfolio weights | L6: Workspace architecture is certified and frozen. Scenario analysis does not modify the certified portfolio. No automatic trading. A new MFPDF version is required before implementation. | R6: ='08 Sleeve Architecture'!A6 -> Growth Compounders | S6: ='08 Sleeve Architecture'!F6 -> 0.1339 | T6: ='08 Sleeve Architecture'!H6 -> 0.1339
R7: ='08 Sleeve Architecture'!A7 -> Digital Infrastructure & AI | S7: ='08 Sleeve Architecture'!F7 -> 0.129 | T7: ='08 Sleeve Architecture'!H7 -> 0.129
R8: ='08 Sleeve Architecture'!A8 -> Industrials & Infrastructure | S8: ='08 Sleeve Architecture'!F8 -> 0.1711 | T8: ='08 Sleeve Architecture'!H8 -> 0.1711
R9: ='08 Sleeve Architecture'!A9 -> Financial Infrastructure | S9: ='08 Sleeve Architecture'!F9 -> 0.097 | T9: ='08 Sleeve Architecture'!H9 -> 0.097
A10: CERTIFIED POSITIONS | D10: ACTUAL WEIGHTS LOADED | G10: CONVICTION ASSIGNED | J10: SCENARIO CHANGES | M10: CERTIFICATION STATE | R10: ='08 Sleeve Architecture'!A10 -> Healthcare Leadership | S10: ='08 Sleeve Architecture'!F10 -> 0.0361 | T10: ='08 Sleeve Architecture'!H10 -> 0.0361
A11: =COUNTA('Certified Allocation'!B5:B51) -> 47 | D11: =COUNTA('Certified Allocation'!I5:I51)&" / 47" -> 0 / 47 | G11: =COUNTIF('11 Conviction'!H5:H51,"<>Unassigned")&" / 47" -> 0 / 47 | J11: ='12 Allocation Lab'!K6 -> 0 | M11: ='13 Validation & Cert'!L38 -> NOT READY | R11: ='08 Sleeve Architecture'!A11 -> Energy & Natural Resources | S11: ='08 Sleeve Architecture'!F11 -> 0.1172 | T11: ='08 Sleeve Architecture'!H11 -> 0.1172
R12: ='08 Sleeve Architecture'!A12 -> Income & Risk Management | S12: ='08 Sleeve Architecture'!F12 -> 0.0906 | T12: ='08 Sleeve Architecture'!H12 -> 0.0906
A14: 47-position canonical Portfolio B | D14: Required for live implementation review | G14: Required before certification | J14: Certified baseline currently preserved | M14: New MFPDF required for implementation
A16: MOPS-002 MODULE STATUS | J16: CERTIFIED VS. SCENARIO SLEEVE ALLOCATION
A17: Module | B17: Workspace | C17: Institutional Function | D17: Current Status | E17: Open Items | F17: Next Required Action | G17: Authority | H17: System of Record | I17: Operating Effect
A18: PEW-001 | B18: Mandate & Constraints | C18: Defines objective, guardrails and governance | D18: =IF(COUNTIF('07 Mandate & Constraints'!H6:H33,"FAIL")>0,"FAIL","ACTIVE") -> ACTIVE | E18: =COUNTIF('07 Mandate & Constraints'!H6:H33,"INPUT REQUIRED") -> 3 | F18: Maintain adopted controls; load objective-test analytics | G18: Chief Investment Steward | H18: 07 Mandate & Constraints | I18: All engineering must satisfy mandate
A19: PEW-002 | B19: Sleeve Architecture | C19: Tests purpose, capacity and sleeve allocation | D19: =IF(COUNTIF('08 Sleeve Architecture'!O5:O12,"SLEEVE REVIEW")>0,"REVIEW",IF(COUNTIF('08 Sleeve Architecture'!O5:O12,"CONVICTION INPUT REQUIRED")>0,"INPUT REQUIRED","BASELINE")) -> INPUT REQUIRED | E19: =COUNTIF('08 Sleeve Architecture'!O5:O12,"<>BASELINE") -> 8 | F19: Complete conviction inputs; review material sleeve shifts | G19: Stewardship Committee | H19: 08 Sleeve Architecture | I19: Preserves eight frozen sleeves
A20: PEW-003 | B20: Role Assignment | C20: Confirms each holding has institutional function | D20: =IF(COUNTIF('09 Role Assignment'!O5:O51,"<>PASS")=0,"PASS","REVIEW") -> PASS | E20: =COUNTIF('09 Role Assignment'!O5:O51,"<>PASS") -> 0 | F20: Resolve role, evidence or replacement exceptions | G20: Research Committee | H20: 09 Role Assignment | I20: Prevents role-free holdings
A21: PEW-004 | B21: Candidate Comparison | C21: Compares incumbents and replacements | D21: =IF(COUNTIF('10 Candidate Comparison'!D14:D33,"<>")=0,"READY — NO CANDIDATES",IF(COUNTIF('10 Candidate Comparison'!Y14:Y33,"COMMITTEE DECISION REQUIRED")>0,"COMMITTEE REVIEW","UNDER REVIEW")) -> READY — NO CANDIDATES | E21: =COUNTIF('10 Candidate Comparison'!Y14:Y33,"COMMITTEE DECISION REQUIRED") -> 0 | F21: Load candidates only when a defined role or replacement need exists | G21: Stewardship Committee | H21: 10 Candidate Comparison | I21: Evidence record; no automatic selection
A22: PEW-005 | B22: Conviction | C22: Assigns conviction, thesis, risk and horizon | D22: =IF(COUNTIF('11 Conviction'!H5:H51,"<>Unassigned")=47,"PASS","INPUT REQUIRED") -> INPUT REQUIRED | E22: =COUNTIF('11 Conviction'!H5:H51,"Unassigned") -> 47 | F22: Assign effective conviction to every active holding | G22: Stewardship Committee | H22: 11 Conviction | I22: Controls sizing and review intensity
A23: PEW-006 | B23: Allocation Lab | C23: Builds funded, band-aware scenario weights | D23: =IF('12 Allocation Lab'!K6=0,"BASELINE",IF(ABS('12 Allocation Lab'!E6-100%)>'13 Validation & Cert'!$B$9,"FAIL","COMMITTEE REVIEW")) -> BASELINE | E23: ='12 Allocation Lab'!K6 -> 0 | F23: Use yellow scenario cells; document rationale for every change | G23: Portfolio Engineering | H23: 12 Allocation Lab | I23: Certified weights remain unchanged
A24: PEW-007 | B24: Validation & Certification | C24: Tests and governs new portfolio version | D24: ='13 Validation & Cert'!J12 -> NOT READY | E24: =COUNTIF('13 Validation & Cert'!E16:E33,"<>PASS") -> 5 | F24: Complete evidence and approvals before issuing new MFPDF | G24: Chief Investment Steward | H24: 13 Validation & Cert | I24: Only certified output becomes operational
A27: ENGINEERING DECISION QUEUE
A28: Priority | B28: Category | C28: Trigger / Current State | D28: Decision Required | E28: Recommended Action | F28: Authority | G28: Status | H28: Evidence Source | I28: Owner | J28: Due / Cadence | K28: Scenario Impact | L28: Certification Impact | M28: Governance Note
A29: 1 | B29: Data Integrity | C29: =47-COUNTA('Certified Allocation'!I5:I51)&" actual weights missing" -> 47 actual weights missing | D29: Data update required | E29: Load Certified Allocation column I | F29: Portfolio Operations | G29: =IF(COUNTA('Certified Allocation'!I5:I51)=47,"CLOSED","ACTION REQUIRED") -> ACTION REQUIRED | H29: MFPDF actual-weight fields | I29: Portfolio Operations | J29: Before implementation review | K29: Blocks current-position funding analysis | L29: Blocks certification
A30: 2 | B30: Conviction | C30: =COUNTIF('11 Conviction'!H5:H51,"Unassigned")&" conviction tiers unassigned" -> 47 conviction tiers unassigned | D30: Conviction assignment required | E30: Complete PEW-005 effective conviction | F30: Stewardship Committee | G30: =IF(COUNTIF('11 Conviction'!H5:H51,"Unassigned")=0,"CLOSED","ACTION REQUIRED") -> ACTION REQUIRED | H30: PEW-005 Conviction | I30: Research / Stewardship | J30: Before certification | K30: Affects sizing and thesis review | L30: Blocks certification
A31: 3 | B31: Allocation | C31: ='12 Allocation Lab'!K6&" scenario positions changed" -> 0 scenario positions changed | D31: No allocation decision unless change exists | E31: Review funded scenario and bands | F31: Stewardship Committee | G31: =IF('12 Allocation Lab'!K6=0,"NO DECISION","COMMITTEE REVIEW") -> NO DECISION | H31: PEW-006 Allocation Lab | I31: Portfolio Engineering | J31: As proposed | K31: Baseline currently preserved | L31: Review required if changed
A32: 4 | B32: Candidate Selection | C32: =COUNTIF('10 Candidate Comparison'!Y14:Y33,"COMMITTEE DECISION REQUIRED")&" candidate decisions" -> 0 candidate decisions | D32: Candidate decision only when evidence is complete | E32: Approve, reject, defer or exception | F32: Stewardship Committee | G32: =IF(COUNTIF('10 Candidate Comparison'!Y14:Y33,"COMMITTEE DECISION REQUIRED")=0,"NO DECISION","COMMITTEE REVIEW") -> NO DECISION | H32: PEW-004 Candidate Comparison | I32: Research Committee | J32: As needed | K32: May add, remove or replace holding | L32: New MFPDF required
A33: 5 | B33: Validation | C33: ='13 Validation & Cert'!J12 -> NOT READY | D33: Certification readiness decision | E33: Complete failed / missing validation controls | F33: Chief Investment Steward | G33: ='13 Validation & Cert'!J12 -> NOT READY | H33: PEW-007 Validation & Certification | I33: Validation Committee | J33: Before MFPDF issuance | K33: Determines whether scenario is supportable | L33: Sole formal issuance gate
A35: MOPS-002 CONTROL PRINCIPLE — The certified portfolio remains the system of record. The Portfolio Engineering Workspace is a controlled scenario environment. No proposed change becomes operational until it is supported by evidence, approved through governance and incorporated into a newly certified MFPDF version.

Sheet 07 Mandate & Constraints
A1: MOPS-002 / PEW-001 — PORTFOLIO MANDATE & CONSTRAINTS
A2: Permanent engineering assumptions governing Portfolio B reviews, scenario construction, optimization and certification
A3: System of Record: MFPDF Founders Edition v1.0 | Status: Production Candidate
A4: ADOPTED PORTFOLIO MANDATE AND CONTROL REGISTER
A5: Control ID | B5: Domain | C5: Objective / Constraint | D5: Adopted Standard | E5: Classification | F5: Operating Value / Current State | G5: Test / Trigger | H5: Status | I5: Authority | J5: Engineering Effect | K5: Notes / Source
A6: PEW-001-01 | B6: Benchmark | C6: Primary comparison standard | D6: Russell 1000 | E6: Monitoring Control | F6: Russell 1000 | G6: All portfolio analytics compared to benchmark | H6: ACTIVE | I6: Chief Investment Steward | J6: Benchmark return, volatility, momentum and yield comparisons | K6: Adopted allocation objective
A7: PEW-001-02 | B7: Risk | C7: Volatility objective | D7: Lower volatility than Russell 1000 | E7: Soft Objective | F7: Analytics not loaded | G7: Rolling 3-year and 5-year realized volatility | H7: MONITOR — ANALYTICS REQUIRED | I7: Portfolio Engineering | J7: Scenario must demonstrate favorable risk profile before certification | K7: Adopted allocation objective
A8: PEW-001-03 | B8: Return | C8: Momentum objective | D8: Higher momentum than Russell 1000 | E8: Soft Objective | F8: Analytics not loaded | G8: Manifest momentum methodology versus benchmark | H8: MONITOR — ANALYTICS REQUIRED | I8: Portfolio Engineering | J8: Use empirical validation; do not optimize to a single period | K8: Adopted allocation objective
A9: PEW-001-04 | B9: Income | C9: Dividend-yield objective | D9: Higher dividend yield than Russell 1000 | E9: Soft Objective | F9: Analytics not loaded | G9: Portfolio yield versus benchmark yield | H9: MONITOR — ANALYTICS REQUIRED | I9: Portfolio Engineering | J9: Dividend growth preferred over static high yield | K9: Adopted allocation objective
A10: PEW-001-05 | B10: Income | C10: Annual portfolio income need | D10: 2.50% annual cash-flow objective | E10: Hard Constraint | F10: 0.025 | G10: Portfolio yield / distributable cash flow ≥ objective | H10: ACTIVE | I10: Chief Investment Steward | J10: Scenario income must be tested before certification | K10: Client / portfolio guardrail
A11: PEW-001-06 | B11: Risk | C11: Maximum acceptable drawdown | D11: 35% review ceiling; not a performance guarantee | E11: Hard Constraint | F11: 0.35 | G11: Empirical / Monte Carlo drawdown test | H11: ACTIVE | I11: Chief Investment Steward | J11: Failure requires redesign or explicit exception | K11: Adopted risk guardrail
A12: PEW-001-07 | B12: Horizon | C12: Investment horizon | D12: Long-term institutional horizon | E12: Governance Rule | F12: 5+ years | G12: Core holdings require durable long-horizon thesis | H12: ACTIVE | I12: Stewardship Committee | J12: Avoid short-term optimization of the core portfolio | K12: Founders Edition doctrine
A13: PEW-001-08 | B13: Liquidity | C13: Liquidity standard | D13: Daily liquidity required | E13: Hard Constraint | F13: Daily | G13: All holdings must be publicly traded and operationally liquid | H13: PASS | I13: Portfolio Operations | J13: Illiquid alternatives are not eligible | K13: Implementation standard
A14: PEW-001-09 | B14: Construction | C14: Preferred equity-core position count | D14: 32–38 equities; controlled exception permitted | E14: Preference | F14: =COUNTIF('Certified Allocation'!D5:D51,"Equity") -> 40 | G14: Monitor current equity count against preferred range | H14: =IF(F14<=38,"PASS",IF(F14<=41,"MONITOR — ABOVE PREFERRED RANGE","FAIL — ABOVE OPERATING CEILING")) -> MONITOR — ABOVE PREFERRED RANGE | I14: Stewardship Committee | J14: Above-range count requires concentration/complexity review | K14: Frozen construction preference
A15: PEW-001-10 | B15: Construction | C15: Operating equity ceiling | D15: Maximum 41 equities without formal amendment | E15: Hard Constraint | F15: =COUNTIF('Certified Allocation'!D5:D51,"Equity") -> 40 | G15: Certified equity count ≤ 41 | H15: =IF(F15<=41,"PASS","FAIL — ABOVE OPERATING CEILING") -> PASS | I15: Chief Investment Steward | J15: Exceeding ceiling blocks certification | K15: Operating interpretation of ±2–3 tolerance
A16: PEW-001-11 | B16: Construction | C16: Certified portfolio position count | D16: 47 positions in canonical Portfolio B | E16: Governance Rule | F16: =COUNTA('Certified Allocation'!B5:B51) -> 47 | G16: Position count must reconcile to MFPDF | H16: =IF(F16=47,"PASS","FAIL — DOES NOT RECONCILE") -> PASS | I16: MFPDF v1.0 | J16: Scenario begins from the certified 47-position baseline | K16: Canonical workbook
A17: PEW-001-12 | B17: Construction | C17: Certified target allocation | D17: Portfolio target must total 100% | E17: Hard Constraint | F17: =SUM('Certified Allocation'!F5:F51) -> 1 | G17: SUM of certified targets = 100% | H17: =IF(ABS(F17-100%)<0.000001,"PASS","FAIL — TARGET TOTAL") -> PASS | I17: MFPDF v1.0 | J17: No scenario may be certified if effective weights do not total 100% | K17: Canonical workbook
A18: PEW-001-13 | B18: Architecture | C18: One security / one sleeve | D18: Each security may belong to only one production sleeve | E18: Hard Constraint | F18: Certified baseline | G18: No duplicate symbol across sleeve assignments | H18: PASS | I18: Stewardship Committee | J18: Prevents double-counting of portfolio purpose | K18: Frozen sleeve rule
A19: PEW-001-14 | B19: Architecture | C19: Core-before-satellite | D19: Core role must be established before implementation exposure | E19: Governance Rule | F19: Required | G19: Portfolio-role review precedes satellite allocation | H19: ACTIVE | I19: Stewardship Committee | J19: A security must have an explicit institutional function | K19: Founders Edition doctrine
A20: PEW-001-15 | B20: Research | C20: Five-year rule for core | D20: Core eligibility requires a five-year operating / evidence record unless excepted | E20: Governance Rule | F20: Required | G20: Role Assignment documents evidence or exception | H20: ACTIVE | I20: Research Committee | J20: Exception requires written committee rationale | K20: Frozen research rule
A21: PEW-001-16 | B21: Income | C21: Dividend growth preference | D21: Dividend growth favored over headline yield | E21: Preference | F21: Required preference | G21: Compare payout durability, FCF and operating earnings growth | H21: ACTIVE | I21: Research Committee | J21: Avoid yield-only selection | K21: Frozen selection preference
A22: PEW-001-17 | B22: ETF / Income | C22: Permitted implementation exposures | D22: No mid/small cap, international or alternatives in this sleeve | E22: Hard Constraint | F22: Domestic large-cap / approved ETFs | G22: Candidate eligibility gate | H22: PASS — CERTIFIED BASELINE | I22: Stewardship Committee | J22: JEPI, JEPQ, PFF and approved Vanguard sector ETFs remain eligible | K22: Frozen implementation directive
A23: PEW-001-18 | B23: Selection | C23: Candidate market-cap preference | D23: Large cap above $50B for Zacks-driven elections unless excepted | E23: Preference | F23: 50 | G23: Candidate market capitalization ($B) | H23: ACTIVE | I23: Stewardship Committee | J23: Sub-$50B candidates require documented exception | K23: Adopted selection preference
A24: PEW-001-19 | B24: Selection | C24: Zacks decision bias | D24: Ranks #1/#2 favored; #3 neutral; #4/#5 require review / exception | E24: Governance Rule | F24: 80% close-decision overlay | G24: Applied only when Manifest comparison is close | H24: ACTIVE | I24: Stewardship Committee | J24: Overlay does not replace MIAR, MICS, empirical or role-fit evidence | K24: Adopted close-decision policy
A25: PEW-001-20 | B25: Selection | C25: Merrill research commonality | D25: Merrill-rated securities preferred; No Rating requires documented exception | E25: Preference | F25: Rated preferred | G25: Candidate eligibility / exception record | H25: ACTIVE | I25: Stewardship Committee | J25: Mega-cap Zacks #1/#2 may remain eligible under documented exception | K25: Research crosswalk policy
A26: PEW-001-21 | B26: Allocation | C26: Certified holding rebalance bands | D26: Lower MAX(1%, 75% of target); upper MIN(4%, 125% of target) | E26: Hard Constraint | F26: Active | G26: Compare actual and scenario weights with certified bands | H26: PASS | I26: MFPDF v1.0 | J26: Band breach triggers review, not automatic trade | K26: Canonical rebalancing framework
A27: PEW-001-22 | B27: Governance | C27: Automatic trading | D27: Not authorized | E27: Hard Constraint | F27: Prohibited | G27: No output may authorize automatic execution | H27: PASS — PROHIBITED | I27: Stewardship Committee | J27: Committee review precedes implementation | K27: Canonical rebalancing framework
A28: PEW-001-23 | B28: Governance | C28: Scenario isolation | D28: Engineering scenarios cannot overwrite the certified portfolio | E28: Hard Constraint | F28: Separate scenario layer | G28: Certified Allocation remains unchanged | H28: PASS | I28: Chief Investment Steward | J28: Only a newly certified MFPDF version becomes operational | K28: MOPS-002 control principle
A29: PEW-001-24 | B29: Validation | C29: Material-change validation | D29: Material allocation changes require empirical and/or Monte Carlo review | E29: Governance Rule | F29: Required when triggered | G29: Turnover, additions/removals, sleeve shift or risk change | H29: ACTIVE | I29: Validation Committee | J29: Optimization output is evidence, not authority | K29: MEVE / Monte Carlo protocol
A30: PEW-001-25 | B30: Operations | C30: Actual weights before live rebalance | D30: All 47 actual weights must be loaded | E30: Hard Constraint | F30: =COUNTA('Certified Allocation'!I5:I51)&" / 47 loaded" -> 0 / 47 loaded | G30: Count of nonblank Certified Allocation column I | H30: =IF(COUNTA('Certified Allocation'!I5:I51)=47,"PASS","INPUT REQUIRED") -> INPUT REQUIRED | I30: Portfolio Operations | J30: Blocks implementation funding and live band review | K30: CISC / MFPDF operating requirement
A31: PEW-001-26 | B31: Governance | C31: Conviction before certification | D31: Every active holding must have an assigned conviction tier | E31: Hard Constraint | F31: =COUNTIF('11 Conviction'!H5:H51,"<>Unassigned")&" / 47 assigned" -> 0 / 47 assigned | G31: Count of non-Unassigned effective convictions | H31: =IF(COUNTIF('11 Conviction'!H5:H51,"<>Unassigned")=47,"PASS","INPUT REQUIRED") -> INPUT REQUIRED | I31: Stewardship Committee | J31: Blocks final certification of a changed portfolio | K31: MOPS-002 PEW-005
A32: PEW-001-27 | B32: Validation | C32: Objective-test data | D32: Benchmark, income and risk analytics must be current | E32: Hard Constraint | F32: Not loaded | G32: Current empirical / risk evidence package | H32: INPUT REQUIRED | I32: Portfolio Engineering | J32: Required before substantive redesign certification | K32: Validation standard
A33: PEW-001-28 | B33: Governance | C33: Formal certification gate | D33: Engineering review, research sufficiency, allocation/risk and committee approval | E33: Hard Constraint | F33: Required | G33: All PEW-007 approvals completed | H33: ACTIVE | I33: Chief Investment Steward | J33: Scenario remains non-operational until MFPDF version is issued | K33: MOPS-002 control principle

Sheet 08 Sleeve Architecture
A1: MOPS-002 / PEW-002 — SLEEVE ARCHITECTURE
A2: Institutional purpose, capacity, certified allocation, scenario impact and control status for the eight frozen production sleeves
A3: Planning ranges use ±20% relative around certified sleeve targets for engineering review; certified holding bands remain authoritative
A4: Production Sleeve | B4: Institutional Purpose | C4: Positions | D4: Equities | E4: ETFs | F4: Certified Target | G4: Actual Allocation | H4: Scenario Allocation | I4: Scenario Delta | J4: Planning Range Low | K4: Planning Range High | L4: Role Control | M4: Conviction Assigned | N4: Conviction Completeness | O4: Sleeve Decision State | P4: Committee Note
A5: Strategic Anchors | B5: Durable capital compounders and portfolio-resilience anchors. | C5: ='Sleeve Summary'!B4 -> 9 | D5: ='Sleeve Summary'!C4 -> 9 | E5: ='Sleeve Summary'!D4 -> 0 | F5: ='Sleeve Summary'!E4 -> 0.2251 | G5: =SUMIF('12 Allocation Lab'!$A$11:$A$57,A5,'12 Allocation Lab'!$I$11:$I$57) -> 0 | H5: =SUMIF('12 Allocation Lab'!$A$11:$A$57,A5,'12 Allocation Lab'!$K$11:$K$57) -> 0.2251 | I5: =H5-F5 -> 0 | J5: =F5*80% -> 0.18008 | K5: =F5*120% -> 0.27012 | L5: =IF(COUNTIFS('09 Role Assignment'!$A$5:$A$51,A5,'09 Role Assignment'!$O$5:$O$51,"<>PASS")=0,"PASS","REVIEW") -> PASS | M5: =COUNTIFS('11 Conviction'!$A$5:$A$51,A5,'11 Conviction'!$H$5:$H$51,"<>Unassigned") -> 0 | N5: =IF(C5=0,0,M5/C5) -> 0 | O5: =IF(OR(H5<J5,H5>K5),"SLEEVE REVIEW",IF(N5<100%,"CONVICTION INPUT REQUIRED",IF(ABS(I5)<'13 Validation & Cert'!$B$9,"BASELINE","REVIEW PROPOSED SHIFT"))) -> CONVICTION INPUT REQUIRED
A6: Growth Compounders | B6: Above-market earnings, free-cash-flow and reinvestment compounders. | C6: ='Sleeve Summary'!B5 -> 6 | D6: ='Sleeve Summary'!C5 -> 6 | E6: ='Sleeve Summary'!D5 -> 0 | F6: ='Sleeve Summary'!E5 -> 0.1339 | G6: =SUMIF('12 Allocation Lab'!$A$11:$A$57,A6,'12 Allocation Lab'!$I$11:$I$57) -> 0 | H6: =SUMIF('12 Allocation Lab'!$A$11:$A$57,A6,'12 Allocation Lab'!$K$11:$K$57) -> 0.1339 | I6: =H6-F6 -> 0 | J6: =F6*80% -> 0.10712 | K6: =F6*120% -> 0.16068 | L6: =IF(COUNTIFS('09 Role Assignment'!$A$5:$A$51,A6,'09 Role Assignment'!$O$5:$O$51,"<>PASS")=0,"PASS","REVIEW") -> PASS | M6: =COUNTIFS('11 Conviction'!$A$5:$A$51,A6,'11 Conviction'!$H$5:$H$51,"<>Unassigned") -> 0 | N6: =IF(C6=0,0,M6/C6) -> 0 | O6: =IF(OR(H6<J6,H6>K6),"SLEEVE REVIEW",IF(N6<100%,"CONVICTION INPUT REQUIRED",IF(ABS(I6)<'13 Validation & Cert'!$B$9,"BASELINE","REVIEW PROPOSED SHIFT"))) -> CONVICTION INPUT REQUIRED
A7: Digital Infrastructure & AI | B7: Semiconductor, networking, cybersecurity and data-center backbone. | C7: ='Sleeve Summary'!B6 -> 8 | D7: ='Sleeve Summary'!C6 -> 8 | E7: ='Sleeve Summary'!D6 -> 0 | F7: ='Sleeve Summary'!E6 -> 0.129 | G7: =SUMIF('12 Allocation Lab'!$A$11:$A$57,A7,'12 Allocation Lab'!$I$11:$I$57) -> 0 | H7: =SUMIF('12 Allocation Lab'!$A$11:$A$57,A7,'12 Allocation Lab'!$K$11:$K$57) -> 0.129 | I7: =H7-F7 -> 0 | J7: =F7*80% -> 0.1032 | K7: =F7*120% -> 0.1548 | L7: =IF(COUNTIFS('09 Role Assignment'!$A$5:$A$51,A7,'09 Role Assignment'!$O$5:$O$51,"<>PASS")=0,"PASS","REVIEW") -> PASS | M7: =COUNTIFS('11 Conviction'!$A$5:$A$51,A7,'11 Conviction'!$H$5:$H$51,"<>Unassigned") -> 0 | N7: =IF(C7=0,0,M7/C7) -> 0 | O7: =IF(OR(H7<J7,H7>K7),"SLEEVE REVIEW",IF(N7<100%,"CONVICTION INPUT REQUIRED",IF(ABS(I7)<'13 Validation & Cert'!$B$9,"BASELINE","REVIEW PROPOSED SHIFT"))) -> CONVICTION INPUT REQUIRED
A8: Industrials & Infrastructure | B8: Aerospace, automation, transportation, electrification and capital spending. | C8: ='Sleeve Summary'!B7 -> 9 | D8: ='Sleeve Summary'!C7 -> 9 | E8: ='Sleeve Summary'!D7 -> 0 | F8: ='Sleeve Summary'!E7 -> 0.1711 | G8: =SUMIF('12 Allocation Lab'!$A$11:$A$57,A8,'12 Allocation Lab'!$I$11:$I$57) -> 0 | H8: =SUMIF('12 Allocation Lab'!$A$11:$A$57,A8,'12 Allocation Lab'!$K$11:$K$57) -> 0.1711 | I8: =H8-F8 -> 0 | J8: =F8*80% -> 0.13688 | K8: =F8*120% -> 0.20532 | L8: =IF(COUNTIFS('09 Role Assignment'!$A$5:$A$51,A8,'09 Role Assignment'!$O$5:$O$51,"<>PASS")=0,"PASS","REVIEW") -> PASS | M8: =COUNTIFS('11 Conviction'!$A$5:$A$51,A8,'11 Conviction'!$H$5:$H$51,"<>Unassigned") -> 0 | N8: =IF(C8=0,0,M8/C8) -> 0 | O8: =IF(OR(H8<J8,H8>K8),"SLEEVE REVIEW",IF(N8<100%,"CONVICTION INPUT REQUIRED",IF(ABS(I8)<'13 Validation & Cert'!$B$9,"BASELINE","REVIEW PROPOSED SHIFT"))) -> CONVICTION INPUT REQUIRED
A9: Financial Infrastructure | B9: Payments, exchanges, capital markets and quality financial intermediation. | C9: ='Sleeve Summary'!B8 -> 5 | D9: ='Sleeve Summary'!C8 -> 4 | E9: ='Sleeve Summary'!D8 -> 1 | F9: ='Sleeve Summary'!E8 -> 0.097 | G9: =SUMIF('12 Allocation Lab'!$A$11:$A$57,A9,'12 Allocation Lab'!$I$11:$I$57) -> 0 | H9: =SUMIF('12 Allocation Lab'!$A$11:$A$57,A9,'12 Allocation Lab'!$K$11:$K$57) -> 0.097 | I9: =H9-F9 -> 0 | J9: =F9*80% -> 0.0776 | K9: =F9*120% -> 0.1164 | L9: =IF(COUNTIFS('09 Role Assignment'!$A$5:$A$51,A9,'09 Role Assignment'!$O$5:$O$51,"<>PASS")=0,"PASS","REVIEW") -> PASS | M9: =COUNTIFS('11 Conviction'!$A$5:$A$51,A9,'11 Conviction'!$H$5:$H$51,"<>Unassigned") -> 0 | N9: =IF(C9=0,0,M9/C9) -> 0 | O9: =IF(OR(H9<J9,H9>K9),"SLEEVE REVIEW",IF(N9<100%,"CONVICTION INPUT REQUIRED",IF(ABS(I9)<'13 Validation & Cert'!$B$9,"BASELINE","REVIEW PROPOSED SHIFT"))) -> CONVICTION INPUT REQUIRED
A10: Healthcare Leadership | B10: Healthcare innovation, defensive growth and durable demand. | C10: ='Sleeve Summary'!B9 -> 2 | D10: ='Sleeve Summary'!C9 -> 1 | E10: ='Sleeve Summary'!D9 -> 1 | F10: ='Sleeve Summary'!E9 -> 0.0361 | G10: =SUMIF('12 Allocation Lab'!$A$11:$A$57,A10,'12 Allocation Lab'!$I$11:$I$57) -> 0 | H10: =SUMIF('12 Allocation Lab'!$A$11:$A$57,A10,'12 Allocation Lab'!$K$11:$K$57) -> 0.0361 | I10: =H10-F10 -> 0 | J10: =F10*80% -> 0.02888 | K10: =F10*120% -> 0.04332 | L10: =IF(COUNTIFS('09 Role Assignment'!$A$5:$A$51,A10,'09 Role Assignment'!$O$5:$O$51,"<>PASS")=0,"PASS","REVIEW") -> PASS | M10: =COUNTIFS('11 Conviction'!$A$5:$A$51,A10,'11 Conviction'!$H$5:$H$51,"<>Unassigned") -> 0 | N10: =IF(C10=0,0,M10/C10) -> 0 | O10: =IF(OR(H10<J10,H10>K10),"SLEEVE REVIEW",IF(N10<100%,"CONVICTION INPUT REQUIRED",IF(ABS(I10)<'13 Validation & Cert'!$B$9,"BASELINE","REVIEW PROPOSED SHIFT"))) -> CONVICTION INPUT REQUIRED
A11: Energy & Natural Resources | B11: Energy security, real assets, inflation sensitivity and resource exposure. | C11: ='Sleeve Summary'!B10 -> 5 | D11: ='Sleeve Summary'!C10 -> 3 | E11: ='Sleeve Summary'!D10 -> 2 | F11: ='Sleeve Summary'!E10 -> 0.1172 | G11: =SUMIF('12 Allocation Lab'!$A$11:$A$57,A11,'12 Allocation Lab'!$I$11:$I$57) -> 0 | H11: =SUMIF('12 Allocation Lab'!$A$11:$A$57,A11,'12 Allocation Lab'!$K$11:$K$57) -> 0.1172 | I11: =H11-F11 -> 0 | J11: =F11*80% -> 0.09376 | K11: =F11*120% -> 0.14064 | L11: =IF(COUNTIFS('09 Role Assignment'!$A$5:$A$51,A11,'09 Role Assignment'!$O$5:$O$51,"<>PASS")=0,"PASS","REVIEW") -> PASS | M11: =COUNTIFS('11 Conviction'!$A$5:$A$51,A11,'11 Conviction'!$H$5:$H$51,"<>Unassigned") -> 0 | N11: =IF(C11=0,0,M11/C11) -> 0 | O11: =IF(OR(H11<J11,H11>K11),"SLEEVE REVIEW",IF(N11<100%,"CONVICTION INPUT REQUIRED",IF(ABS(I11)<'13 Validation & Cert'!$B$9,"BASELINE","REVIEW PROPOSED SHIFT"))) -> CONVICTION INPUT REQUIRED
A12: Income & Risk Management | B12: Income generation, volatility moderation and preferred-security diversification. | C12: ='Sleeve Summary'!B11 -> 3 | D12: ='Sleeve Summary'!C11 -> 0 | E12: ='Sleeve Summary'!D11 -> 3 | F12: ='Sleeve Summary'!E11 -> 0.0906 | G12: =SUMIF('12 Allocation Lab'!$A$11:$A$57,A12,'12 Allocation Lab'!$I$11:$I$57) -> 0 | H12: =SUMIF('12 Allocation Lab'!$A$11:$A$57,A12,'12 Allocation Lab'!$K$11:$K$57) -> 0.0906 | I12: =H12-F12 -> 0 | J12: =F12*80% -> 0.07248 | K12: =F12*120% -> 0.10872 | L12: =IF(COUNTIFS('09 Role Assignment'!$A$5:$A$51,A12,'09 Role Assignment'!$O$5:$O$51,"<>PASS")=0,"PASS","REVIEW") -> PASS | M12: =COUNTIFS('11 Conviction'!$A$5:$A$51,A12,'11 Conviction'!$H$5:$H$51,"<>Unassigned") -> 0 | N12: =IF(C12=0,0,M12/C12) -> 0 | O12: =IF(OR(H12<J12,H12>K12),"SLEEVE REVIEW",IF(N12<100%,"CONVICTION INPUT REQUIRED",IF(ABS(I12)<'13 Validation & Cert'!$B$9,"BASELINE","REVIEW PROPOSED SHIFT"))) -> CONVICTION INPUT REQUIRED
A13: TOTAL / PORTFOLIO CONTROL | C13: =SUM(C5:C12) -> 47 | D13: =SUM(D5:D12) -> 40 | E13: =SUM(E5:E12) -> 7 | F13: =SUM(F5:F12) -> 1 | G13: =SUM(G5:G12) -> 0 | H13: =SUM(H5:H12) -> 1 | I13: =SUM(I5:I12) -> 0 | M13: =SUM(M5:M12) -> 0 | N13: =IF(SUM(C5:C12)=0,0,M13/SUM(C5:C12)) -> 0 | O13: =IF(ABS(H13-100%)<'13 Validation & Cert'!$B$9,"SCENARIO TOTAL PASS","SCENARIO TOTAL FAIL") -> SCENARIO TOTAL PASS

Sheet 09 Role Assignment
A1: MOPS-002 / PEW-003 — PORTFOLIO ROLE ASSIGNMENT
A2: Every holding must perform an explicit institutional function; attractive securities without a portfolio role do not receive allocation
A3: One security / one sleeve | Core before satellite | Five-year evidence rule | Certified baseline preserved
A4: Production Sleeve | B4: Symbol | C4: Security | D4: Type | E4: Certified Portfolio Role | F4: Functional Role | G4: Role Priority | H4: Core Eligibility | I4: Five-Year Evidence Status | J4: Thesis Horizon | K4: Duplication Risk | L4: Complementarity Score (1–5) | M4: Role Decision | N4: Role / Replacement Notes | O4: Control Status
A5: ='Certified Allocation'!A5 -> Strategic Anchors | B5: ='Certified Allocation'!B5 -> BRK.B | C5: ='Certified Allocation'!C5 -> Berkshire Hathaway Inc. Class B | D5: ='Certified Allocation'!D5 -> Equity | E5: ='Certified Allocation'!E5 -> Diversified capital-allocation anchor | F5: Constitutional Anchor | G5: Primary | H5: Core | I5: Certified Baseline | J5: 5+ years | K5: Not Assessed | M5: Retain — Certified Baseline | O5: =IF(F5="","ROLE REQUIRED",IF(I5="Review","EVIDENCE REVIEW",IF(M5="Replacement Candidate","COMMITTEE REVIEW","PASS"))) -> PASS
A6: ='Certified Allocation'!A6 -> Strategic Anchors | B6: ='Certified Allocation'!B6 -> COST | C6: ='Certified Allocation'!C6 -> Costco Wholesale Corporation | D6: ='Certified Allocation'!D6 -> Equity | E6: ='Certified Allocation'!E6 -> Consumer-resilience anchor | F6: Core Compounder | G6: Primary | H6: Core | I6: Certified Baseline | J6: 5+ years | K6: Not Assessed | M6: Retain — Certified Baseline | O6: =IF(F6="","ROLE REQUIRED",IF(I6="Review","EVIDENCE REVIEW",IF(M6="Replacement Candidate","COMMITTEE REVIEW","PASS"))) -> PASS
A7: ='Certified Allocation'!A7 -> Strategic Anchors | B7: ='Certified Allocation'!B7 -> JNJ | C7: ='Certified Allocation'!C7 -> Johnson & Johnson | D7: ='Certified Allocation'!D7 -> Equity | E7: ='Certified Allocation'!E7 -> Healthcare and life-sciences resilience anchor | F7: Defensive Healthcare | G7: Primary | H7: Core | I7: Certified Baseline | J7: 5+ years | K7: Not Assessed | M7: Retain — Certified Baseline | O7: =IF(F7="","ROLE REQUIRED",IF(I7="Review","EVIDENCE REVIEW",IF(M7="Replacement Candidate","COMMITTEE REVIEW","PASS"))) -> PASS
A8: ='Certified Allocation'!A8 -> Strategic Anchors | B8: ='Certified Allocation'!B8 -> MSFT | C8: ='Certified Allocation'!C8 -> Microsoft Corporation | D8: ='Certified Allocation'!D8 -> Equity | E8: ='Certified Allocation'!E8 -> Enterprise technology and AI platform anchor | F8: Core Compounder | G8: Primary | H8: Core | I8: Certified Baseline | J8: 5+ years | K8: Not Assessed | M8: Retain — Certified Baseline | O8: =IF(F8="","ROLE REQUIRED",IF(I8="Review","EVIDENCE REVIEW",IF(M8="Replacement Candidate","COMMITTEE REVIEW","PASS"))) -> PASS
A9: ='Certified Allocation'!A9 -> Strategic Anchors | B9: ='Certified Allocation'!B9 -> V | C9: ='Certified Allocation'!C9 -> Visa Inc. | D9: ='Certified Allocation'!D9 -> Equity | E9: ='Certified Allocation'!E9 -> Global payments infrastructure anchor | F9: Quality Financial | G9: Primary | H9: Core | I9: Certified Baseline | J9: 5+ years | K9: Not Assessed | M9: Retain — Certified Baseline | O9: =IF(F9="","ROLE REQUIRED",IF(I9="Review","EVIDENCE REVIEW",IF(M9="Replacement Candidate","COMMITTEE REVIEW","PASS"))) -> PASS
A10: ='Certified Allocation'!A10 -> Strategic Anchors | B10: ='Certified Allocation'!B10 -> GOOGL | C10: ='Certified Allocation'!C10 -> Alphabet Inc. Class A | D10: ='Certified Allocation'!D10 -> Equity | E10: ='Certified Allocation'!E10 -> Digital platform and AI anchor | F10: Core Compounder | G10: Primary | H10: Core | I10: Certified Baseline | J10: 5+ years | K10: Not Assessed | M10: Retain — Certified Baseline | O10: =IF(F10="","ROLE REQUIRED",IF(I10="Review","EVIDENCE REVIEW",IF(M10="Replacement Candidate","COMMITTEE REVIEW","PASS"))) -> PASS
A11: ='Certified Allocation'!A11 -> Strategic Anchors | B11: ='Certified Allocation'!B11 -> MA | C11: ='Certified Allocation'!C11 -> Mastercard Incorporated | D11: ='Certified Allocation'!D11 -> Equity | E11: ='Certified Allocation'!E11 -> Global payments infrastructure anchor | F11: Quality Financial | G11: Primary | H11: Core | I11: Certified Baseline | J11: 5+ years | K11: Not Assessed | M11: Retain — Certified Baseline | O11: =IF(F11="","ROLE REQUIRED",IF(I11="Review","EVIDENCE REVIEW",IF(M11="Replacement Candidate","COMMITTEE REVIEW","PASS"))) -> PASS
A12: ='Certified Allocation'!A12 -> Strategic Anchors | B12: ='Certified Allocation'!B12 -> AAPL | C12: ='Certified Allocation'!C12 -> Apple Inc. | D12: ='Certified Allocation'!D12 -> Equity | E12: ='Certified Allocation'!E12 -> Consumer technology ecosystem anchor | F12: Core Compounder | G12: Primary | H12: Core | I12: Certified Baseline | J12: 5+ years | K12: Not Assessed | M12: Retain — Certified Baseline | O12: =IF(F12="","ROLE REQUIRED",IF(I12="Review","EVIDENCE REVIEW",IF(M12="Replacement Candidate","COMMITTEE REVIEW","PASS"))) -> PASS
A13: ='Certified Allocation'!A13 -> Strategic Anchors | B13: ='Certified Allocation'!B13 -> AMZN | C13: ='Certified Allocation'!C13 -> Amazon.com, Inc. | D13: ='Certified Allocation'!D13 -> Equity | E13: ='Certified Allocation'!E13 -> Cloud, commerce and logistics anchor | F13: Core Compounder | G13: Primary | H13: Core | I13: Certified Baseline | J13: 5+ years | K13: Not Assessed | M13: Retain — Certified Baseline | O13: =IF(F13="","ROLE REQUIRED",IF(I13="Review","EVIDENCE REVIEW",IF(M13="Replacement Candidate","COMMITTEE REVIEW","PASS"))) -> PASS
A14: ='Certified Allocation'!A14 -> Growth Compounders | B14: ='Certified Allocation'!B14 -> AVGO | C14: ='Certified Allocation'!C14 -> Broadcom Inc. | D14: ='Certified Allocation'!D14 -> Equity | E14: ='Certified Allocation'!E14 -> Semiconductor and infrastructure-software compounder | F14: Growth Engine | G14: Primary | H14: Core | I14: Certified Baseline | J14: 5+ years | K14: Not Assessed | M14: Retain — Certified Baseline | O14: =IF(F14="","ROLE REQUIRED",IF(I14="Review","EVIDENCE REVIEW",IF(M14="Replacement Candidate","COMMITTEE REVIEW","PASS"))) -> PASS
A15: ='Certified Allocation'!A15 -> Growth Compounders | B15: ='Certified Allocation'!B15 -> LLY | C15: ='Certified Allocation'!C15 -> Eli Lilly and Company | D15: ='Certified Allocation'!D15 -> Equity | E15: ='Certified Allocation'!E15 -> Healthcare innovation compounder | F15: Defensive Healthcare | G15: Primary | H15: Core | I15: Certified Baseline | J15: 5+ years | K15: Not Assessed | M15: Retain — Certified Baseline | O15: =IF(F15="","ROLE REQUIRED",IF(I15="Review","EVIDENCE REVIEW",IF(M15="Replacement Candidate","COMMITTEE REVIEW","PASS"))) -> PASS
A16: ='Certified Allocation'!A16 -> Growth Compounders | B16: ='Certified Allocation'!B16 -> NVDA | C16: ='Certified Allocation'!C16 -> NVIDIA Corporation | D16: ='Certified Allocation'!D16 -> Equity | E16: ='Certified Allocation'!E16 -> AI compute growth engine | F16: Growth Engine | G16: Primary | H16: Core | I16: Certified Baseline | J16: 5+ years | K16: Not Assessed | M16: Retain — Certified Baseline | O16: =IF(F16="","ROLE REQUIRED",IF(I16="Review","EVIDENCE REVIEW",IF(M16="Replacement Candidate","COMMITTEE REVIEW","PASS"))) -> PASS
... A51: ='Certified Allocation'!A51 -> Income & Risk Management | B51: ='Certified Allocation'!B51 -> PFF | C51: ='Certified Allocation'!C51 -> iShares Preferred and Income Securities ETF | D51: ='Certified Allocation'!D51 -> ETF | E51: ='Certified Allocation'!E51 -> Preferred securities income diversification | F51: Income Generator | G51: Implementation | H51: Satellite / Implementation | I51: Certified Baseline | J51: 3–5 years | K51: Not Assessed | M51: Retain — Certified Baseline | O51: =IF(F51="","ROLE REQUIRED",IF(I51="Review","EVIDENCE REVIEW",IF(M51="Replacement Candidate","COMMITTEE REVIEW","PASS"))) -> PASS
A52: ROLE CONTROL SUMMARY | F52: =COUNTIF(O5:O51,"PASS") -> 47 | G52: Passed | I52: =COUNTIF(O5:O51,"<>PASS") -> 0 | J52: Review Items | M52: =COUNTIF(M5:M51,"Replacement Candidate") -> 0 | N52: Replacement Candidates

Sheet 10 Candidate Comparison
A1: MOPS-002 / PEW-004 — SECURITY SELECTION & CANDIDATE COMPARISON
A2: Evidence-weighted incumbent / replacement analysis with controlled Zacks close-decision overlay and Merrill commonality exceptions
A3: MIAR + MICS + Empirical Evidence + Portfolio Role Fit remain primary. Zacks overlay applies only to genuinely close decisions.
A4: BASE MANIFEST SCORING WEIGHTS | D4: CLOSE-DECISION / ELIGIBILITY CONTROLS | H4: OPERATING PRINCIPLE
A5: MICS Score | B5: 0.25 | D5: Close-decision score spread | E5: ≤ 5 points | F5: Used to determine whether overlay is appropriate | H5: Candidate comparison is a controlled evidence record—not an automatic optimizer. A high score does not authorize selection. Each candidate must satisfy portfolio-role fit, research sufficiency, eligibility controls, funding logic and committee governance. Zacks #1/#2 receives a strong tie-breaking bias only after the primary Manifest evidence establishes a close decision. Merrill No Rating and sub-$50B market capitalization require a written exception rather than an unrecorded override.
A6: MIAR / Integrity Score | B6: 0.2 | D6: Zacks overlay weight | E6: 0.8 | F6: Applied only when Close Decision = Yes
A7: Empirical Rank | B7: 0.2 | D7: Zacks-election market-cap preference ($B) | E7: 50 | F7: Sub-$50B requires documented exception
A8: Portfolio Role Fit | B8: 0.15 | D8: Zacks Rank #1 / #2 | E8: Favored | F8: Ranks #4 / #5 require exception review
A9: Valuation | B9: 0.1 | D9: Merrill No Rating | E9: Document exception | F9: Not an automatic rejection where other evidence is compelling
A10: Diversification Contribution | B10: 0.1 | D10: Automatic selection | E10: Prohibited | F10: Committee decision remains required
A11: TOTAL | B11: =SUM(B5:B10) -> 1
A12: CANDIDATE COMPARISON REGISTER — INPUT IN YELLOW CELLS
A13: Candidate ID | B13: Comparison Group | C13: Candidate Type | D13: Symbol | E13: Security | F13: Proposed Sleeve | G13: Proposed Role | H13: Market Cap ($B) | I13: Merrill Status | J13: Zacks Rank | K13: MICS | L13: MIAR / Integrity | M13: Empirical Rank | N13: Role Fit | O13: Valuation | P13: Diversification | Q13: Base Score | R13: Close Decision? | S13: Zacks Overlay | T13: Final Score | U13: Eligibility Gate | V13: Recommended Action | W13: Committee Decision | X13: Evidence / Notes | Y13: Status
A14: CAND-001 | Q14: =IF(COUNTA(K14:P14)<6,"",K14*$B$5+L14*$B$6+M14*$B$7+N14*$B$8+O14*$B$9+P14*$B$10) | S14: =IF(J14="","",IF(J14=1,100,IF(J14=2,85,IF(J14=3,60,IF(J14=4,25,0))))) | T14: =IF(Q14="","",IF(R14="Yes",Q14*(1-$E$6)+S14*$E$6,Q14)) | U14: =IF(D14="","",IF(OR(H14="",I14="",J14="",COUNTA(K14:P14)<6),"DATA MISSING",IF(AND(C14="Candidate",H14<$E$7),"MARKET CAP EXCEPTION",IF(I14="No Rating","MERRILL EXCEPTION",IF(J14>=4,"ZACKS EXCEPTION","ELIGIBLE"))))) | V14: =IF(D14="","",IF(Q14="","COMPLETE SCORING",IF(U14<>"ELIGIBLE","DOCUMENT / COMMITTEE EXCEPTION",IF(T14>=85,"ADVANCE",IF(T14>=75,"RETAIN ON SHORT LIST",IF(T14>=65,"WATCH","REJECT / REPLACE")))))) | Y14: =IF(D14="","Open Slot",IF(AND(W14<>"",W14<>"No Decision"),"Decision Recorded",IF(OR(V14="ADVANCE",ISNUMBER(SEARCH("EXCEPTION",V14))),"COMMITTEE DECISION REQUIRED","Under Review"))) -> Open Slot
A15: CAND-002 | Q15: =IF(COUNTA(K15:P15)<6,"",K15*$B$5+L15*$B$6+M15*$B$7+N15*$B$8+O15*$B$9+P15*$B$10) | S15: =IF(J15="","",IF(J15=1,100,IF(J15=2,85,IF(J15=3,60,IF(J15=4,25,0))))) | T15: =IF(Q15="","",IF(R15="Yes",Q15*(1-$E$6)+S15*$E$6,Q15)) | U15: =IF(D15="","",IF(OR(H15="",I15="",J15="",COUNTA(K15:P15)<6),"DATA MISSING",IF(AND(C15="Candidate",H15<$E$7),"MARKET CAP EXCEPTION",IF(I15="No Rating","MERRILL EXCEPTION",IF(J15>=4,"ZACKS EXCEPTION","ELIGIBLE"))))) | V15: =IF(D15="","",IF(Q15="","COMPLETE SCORING",IF(U15<>"ELIGIBLE","DOCUMENT / COMMITTEE EXCEPTION",IF(T15>=85,"ADVANCE",IF(T15>=75,"RETAIN ON SHORT LIST",IF(T15>=65,"WATCH","REJECT / REPLACE")))))) | Y15: =IF(D15="","Open Slot",IF(AND(W15<>"",W15<>"No Decision"),"Decision Recorded",IF(OR(V15="ADVANCE",ISNUMBER(SEARCH("EXCEPTION",V15))),"COMMITTEE DECISION REQUIRED","Under Review"))) -> Open Slot
A16: CAND-003 | Q16: =IF(COUNTA(K16:P16)<6,"",K16*$B$5+L16*$B$6+M16*$B$7+N16*$B$8+O16*$B$9+P16*$B$10) | S16: =IF(J16="","",IF(J16=1,100,IF(J16=2,85,IF(J16=3,60,IF(J16=4,25,0))))) | T16: =IF(Q16="","",IF(R16="Yes",Q16*(1-$E$6)+S16*$E$6,Q16)) | U16: =IF(D16="","",IF(OR(H16="",I16="",J16="",COUNTA(K16:P16)<6),"DATA MISSING",IF(AND(C16="Candidate",H16<$E$7),"MARKET CAP EXCEPTION",IF(I16="No Rating","MERRILL EXCEPTION",IF(J16>=4,"ZACKS EXCEPTION","ELIGIBLE"))))) | V16: =IF(D16="","",IF(Q16="","COMPLETE SCORING",IF(U16<>"ELIGIBLE","DOCUMENT / COMMITTEE EXCEPTION",IF(T16>=85,"ADVANCE",IF(T16>=75,"RETAIN ON SHORT LIST",IF(T16>=65,"WATCH","REJECT / REPLACE")))))) | Y16: =IF(D16="","Open Slot",IF(AND(W16<>"",W16<>"No Decision"),"Decision Recorded",IF(OR(V16="ADVANCE",ISNUMBER(SEARCH("EXCEPTION",V16))),"COMMITTEE DECISION REQUIRED","Under Review"))) -> Open Slot
A17: CAND-004 | Q17: =IF(COUNTA(K17:P17)<6,"",K17*$B$5+L17*$B$6+M17*$B$7+N17*$B$8+O17*$B$9+P17*$B$10) | S17: =IF(J17="","",IF(J17=1,100,IF(J17=2,85,IF(J17=3,60,IF(J17=4,25,0))))) | T17: =IF(Q17="","",IF(R17="Yes",Q17*(1-$E$6)+S17*$E$6,Q17)) | U17: =IF(D17="","",IF(OR(H17="",I17="",J17="",COUNTA(K17:P17)<6),"DATA MISSING",IF(AND(C17="Candidate",H17<$E$7),"MARKET CAP EXCEPTION",IF(I17="No Rating","MERRILL EXCEPTION",IF(J17>=4,"ZACKS EXCEPTION","ELIGIBLE"))))) | V17: =IF(D17="","",IF(Q17="","COMPLETE SCORING",IF(U17<>"ELIGIBLE","DOCUMENT / COMMITTEE EXCEPTION",IF(T17>=85,"ADVANCE",IF(T17>=75,"RETAIN ON SHORT LIST",IF(T17>=65,"WATCH","REJECT / REPLACE")))))) | Y17: =IF(D17="","Open Slot",IF(AND(W17<>"",W17<>"No Decision"),"Decision Recorded",IF(OR(V17="ADVANCE",ISNUMBER(SEARCH("EXCEPTION",V17))),"COMMITTEE DECISION REQUIRED","Under Review"))) -> Open Slot
A18: CAND-005 | Q18: =IF(COUNTA(K18:P18)<6,"",K18*$B$5+L18*$B$6+M18*$B$7+N18*$B$8+O18*$B$9+P18*$B$10) | S18: =IF(J18="","",IF(J18=1,100,IF(J18=2,85,IF(J18=3,60,IF(J18=4,25,0))))) | T18: =IF(Q18="","",IF(R18="Yes",Q18*(1-$E$6)+S18*$E$6,Q18)) | U18: =IF(D18="","",IF(OR(H18="",I18="",J18="",COUNTA(K18:P18)<6),"DATA MISSING",IF(AND(C18="Candidate",H18<$E$7),"MARKET CAP EXCEPTION",IF(I18="No Rating","MERRILL EXCEPTION",IF(J18>=4,"ZACKS EXCEPTION","ELIGIBLE"))))) | V18: =IF(D18="","",IF(Q18="","COMPLETE SCORING",IF(U18<>"ELIGIBLE","DOCUMENT / COMMITTEE EXCEPTION",IF(T18>=85,"ADVANCE",IF(T18>=75,"RETAIN ON SHORT LIST",IF(T18>=65,"WATCH","REJECT / REPLACE")))))) | Y18: =IF(D18="","Open Slot",IF(AND(W18<>"",W18<>"No Decision"),"Decision Recorded",IF(OR(V18="ADVANCE",ISNUMBER(SEARCH("EXCEPTION",V18))),"COMMITTEE DECISION REQUIRED","Under Review"))) -> Open Slot
A19: CAND-006 | Q19: =IF(COUNTA(K19:P19)<6,"",K19*$B$5+L19*$B$6+M19*$B$7+N19*$B$8+O19*$B$9+P19*$B$10) | S19: =IF(J19="","",IF(J19=1,100,IF(J19=2,85,IF(J19=3,60,IF(J19=4,25,0))))) | T19: =IF(Q19="","",IF(R19="Yes",Q19*(1-$E$6)+S19*$E$6,Q19)) | U19: =IF(D19="","",IF(OR(H19="",I19="",J19="",COUNTA(K19:P19)<6),"DATA MISSING",IF(AND(C19="Candidate",H19<$E$7),"MARKET CAP EXCEPTION",IF(I19="No Rating","MERRILL EXCEPTION",IF(J19>=4,"ZACKS EXCEPTION","ELIGIBLE"))))) | V19: =IF(D19="","",IF(Q19="","COMPLETE SCORING",IF(U19<>"ELIGIBLE","DOCUMENT / COMMITTEE EXCEPTION",IF(T19>=85,"ADVANCE",IF(T19>=75,"RETAIN ON SHORT LIST",IF(T19>=65,"WATCH","REJECT / REPLACE")))))) | Y19: =IF(D19="","Open Slot",IF(AND(W19<>"",W19<>"No Decision"),"Decision Recorded",IF(OR(V19="ADVANCE",ISNUMBER(SEARCH("EXCEPTION",V19))),"COMMITTEE DECISION REQUIRED","Under Review"))) -> Open Slot
A20: CAND-007 | Q20: =IF(COUNTA(K20:P20)<6,"",K20*$B$5+L20*$B$6+M20*$B$7+N20*$B$8+O20*$B$9+P20*$B$10) | S20: =IF(J20="","",IF(J20=1,100,IF(J20=2,85,IF(J20=3,60,IF(J20=4,25,0))))) | T20: =IF(Q20="","",IF(R20="Yes",Q20*(1-$E$6)+S20*$E$6,Q20)) | U20: =IF(D20="","",IF(OR(H20="",I20="",J20="",COUNTA(K20:P20)<6),"DATA MISSING",IF(AND(C20="Candidate",H20<$E$7),"MARKET CAP EXCEPTION",IF(I20="No Rating","MERRILL EXCEPTION",IF(J20>=4,"ZACKS EXCEPTION","ELIGIBLE"))))) | V20: =IF(D20="","",IF(Q20="","COMPLETE SCORING",IF(U20<>"ELIGIBLE","DOCUMENT / COMMITTEE EXCEPTION",IF(T20>=85,"ADVANCE",IF(T20>=75,"RETAIN ON SHORT LIST",IF(T20>=65,"WATCH","REJECT / REPLACE")))))) | Y20: =IF(D20="","Open Slot",IF(AND(W20<>"",W20<>"No Decision"),"Decision Recorded",IF(OR(V20="ADVANCE",ISNUMBER(SEARCH("EXCEPTION",V20))),"COMMITTEE DECISION REQUIRED","Under Review"))) -> Open Slot
A21: CAND-008 | Q21: =IF(COUNTA(K21:P21)<6,"",K21*$B$5+L21*$B$6+M21*$B$7+N21*$B$8+O21*$B$9+P21*$B$10) | S21: =IF(J21="","",IF(J21=1,100,IF(J21=2,85,IF(J21=3,60,IF(J21=4,25,0))))) | T21: =IF(Q21="","",IF(R21="Yes",Q21*(1-$E$6)+S21*$E$6,Q21)) | U21: =IF(D21="","",IF(OR(H21="",I21="",J21="",COUNTA(K21:P21)<6),"DATA MISSING",IF(AND(C21="Candidate",H21<$E$7),"MARKET CAP EXCEPTION",IF(I21="No Rating","MERRILL EXCEPTION",IF(J21>=4,"ZACKS EXCEPTION","ELIGIBLE"))))) | V21: =IF(D21="","",IF(Q21="","COMPLETE SCORING",IF(U21<>"ELIGIBLE","DOCUMENT / COMMITTEE EXCEPTION",IF(T21>=85,"ADVANCE",IF(T21>=75,"RETAIN ON SHORT LIST",IF(T21>=65,"WATCH","REJECT / REPLACE")))))) | Y21: =IF(D21="","Open Slot",IF(AND(W21<>"",W21<>"No Decision"),"Decision Recorded",IF(OR(V21="ADVANCE",ISNUMBER(SEARCH("EXCEPTION",V21))),"COMMITTEE DECISION REQUIRED","Under Review"))) -> Open Slot
A22: CAND-009 | Q22: =IF(COUNTA(K22:P22)<6,"",K22*$B$5+L22*$B$6+M22*$B$7+N22*$B$8+O22*$B$9+P22*$B$10) | S22: =IF(J22="","",IF(J22=1,100,IF(J22=2,85,IF(J22=3,60,IF(J22=4,25,0))))) | T22: =IF(Q22="","",IF(R22="Yes",Q22*(1-$E$6)+S22*$E$6,Q22)) | U22: =IF(D22="","",IF(OR(H22="",I22="",J22="",COUNTA(K22:P22)<6),"DATA MISSING",IF(AND(C22="Candidate",H22<$E$7),"MARKET CAP EXCEPTION",IF(I22="No Rating","MERRILL EXCEPTION",IF(J22>=4,"ZACKS EXCEPTION","ELIGIBLE"))))) | V22: =IF(D22="","",IF(Q22="","COMPLETE SCORING",IF(U22<>"ELIGIBLE","DOCUMENT / COMMITTEE EXCEPTION",IF(T22>=85,"ADVANCE",IF(T22>=75,"RETAIN ON SHORT LIST",IF(T22>=65,"WATCH","REJECT / REPLACE")))))) | Y22: =IF(D22="","Open Slot",IF(AND(W22<>"",W22<>"No Decision"),"Decision Recorded",IF(OR(V22="ADVANCE",ISNUMBER(SEARCH("EXCEPTION",V22))),"COMMITTEE DECISION REQUIRED","Under Review"))) -> Open Slot
A23: CAND-010 | Q23: =IF(COUNTA(K23:P23)<6,"",K23*$B$5+L23*$B$6+M23*$B$7+N23*$B$8+O23*$B$9+P23*$B$10) | S23: =IF(J23="","",IF(J23=1,100,IF(J23=2,85,IF(J23=3,60,IF(J23=4,25,0))))) | T23: =IF(Q23="","",IF(R23="Yes",Q23*(1-$E$6)+S23*$E$6,Q23)) | U23: =IF(D23="","",IF(OR(H23="",I23="",J23="",COUNTA(K23:P23)<6),"DATA MISSING",IF(AND(C23="Candidate",H23<$E$7),"MARKET CAP EXCEPTION",IF(I23="No Rating","MERRILL EXCEPTION",IF(J23>=4,"ZACKS EXCEPTION","ELIGIBLE"))))) | V23: =IF(D23="","",IF(Q23="","COMPLETE SCORING",IF(U23<>"ELIGIBLE","DOCUMENT / COMMITTEE EXCEPTION",IF(T23>=85,"ADVANCE",IF(T23>=75,"RETAIN ON SHORT LIST",IF(T23>=65,"WATCH","REJECT / REPLACE")))))) | Y23: =IF(D23="","Open Slot",IF(AND(W23<>"",W23<>"No Decision"),"Decision Recorded",IF(OR(V23="ADVANCE",ISNUMBER(SEARCH("EXCEPTION",V23))),"COMMITTEE DECISION REQUIRED","Under Review"))) -> Open Slot
A24: CAND-011 | Q24: =IF(COUNTA(K24:P24)<6,"",K24*$B$5+L24*$B$6+M24*$B$7+N24*$B$8+O24*$B$9+P24*$B$10) | S24: =IF(J24="","",IF(J24=1,100,IF(J24=2,85,IF(J24=3,60,IF(J24=4,25,0))))) | T24: =IF(Q24="","",IF(R24="Yes",Q24*(1-$E$6)+S24*$E$6,Q24)) | U24: =IF(D24="","",IF(OR(H24="",I24="",J24="",COUNTA(K24:P24)<6),"DATA MISSING",IF(AND(C24="Candidate",H24<$E$7),"MARKET CAP EXCEPTION",IF(I24="No Rating","MERRILL EXCEPTION",IF(J24>=4,"ZACKS EXCEPTION","ELIGIBLE"))))) | V24: =IF(D24="","",IF(Q24="","COMPLETE SCORING",IF(U24<>"ELIGIBLE","DOCUMENT / COMMITTEE EXCEPTION",IF(T24>=85,"ADVANCE",IF(T24>=75,"RETAIN ON SHORT LIST",IF(T24>=65,"WATCH","REJECT / REPLACE")))))) | Y24: =IF(D24="","Open Slot",IF(AND(W24<>"",W24<>"No Decision"),"Decision Recorded",IF(OR(V24="ADVANCE",ISNUMBER(SEARCH("EXCEPTION",V24))),"COMMITTEE DECISION REQUIRED","Under Review"))) -> Open Slot
A25: CAND-012 | Q25: =IF(COUNTA(K25:P25)<6,"",K25*$B$5+L25*$B$6+M25*$B$7+N25*$B$8+O25*$B$9+P25*$B$10) | S25: =IF(J25="","",IF(J25=1,100,IF(J25=2,85,IF(J25=3,60,IF(J25=4,25,0))))) | T25: =IF(Q25="","",IF(R25="Yes",Q25*(1-$E$6)+S25*$E$6,Q25)) | U25: =IF(D25="","",IF(OR(H25="",I25="",J25="",COUNTA(K25:P25)<6),"DATA MISSING",IF(AND(C25="Candidate",H25<$E$7),"MARKET CAP EXCEPTION",IF(I25="No Rating","MERRILL EXCEPTION",IF(J25>=4,"ZACKS EXCEPTION","ELIGIBLE"))))) | V25: =IF(D25="","",IF(Q25="","COMPLETE SCORING",IF(U25<>"ELIGIBLE","DOCUMENT / COMMITTEE EXCEPTION",IF(T25>=85,"ADVANCE",IF(T25>=75,"RETAIN ON SHORT LIST",IF(T25>=65,"WATCH","REJECT / REPLACE")))))) | Y25: =IF(D25="","Open Slot",IF(AND(W25<>"",W25<>"No Decision"),"Decision Recorded",IF(OR(V25="ADVANCE",ISNUMBER(SEARCH("EXCEPTION",V25))),"COMMITTEE DECISION REQUIRED","Under Review"))) -> Open Slot
... A33: CAND-020 | Q33: =IF(COUNTA(K33:P33)<6,"",K33*$B$5+L33*$B$6+M33*$B$7+N33*$B$8+O33*$B$9+P33*$B$10) | S33: =IF(J33="","",IF(J33=1,100,IF(J33=2,85,IF(J33=3,60,IF(J33=4,25,0))))) | T33: =IF(Q33="","",IF(R33="Yes",Q33*(1-$E$6)+S33*$E$6,Q33)) | U33: =IF(D33="","",IF(OR(H33="",I33="",J33="",COUNTA(K33:P33)<6),"DATA MISSING",IF(AND(C33="Candidate",H33<$E$7),"MARKET CAP EXCEPTION",IF(I33="No Rating","MERRILL EXCEPTION",IF(J33>=4,"ZACKS EXCEPTION","ELIGIBLE"))))) | V33: =IF(D33="","",IF(Q33="","COMPLETE SCORING",IF(U33<>"ELIGIBLE","DOCUMENT / COMMITTEE EXCEPTION",IF(T33>=85,"ADVANCE",IF(T33>=75,"RETAIN ON SHORT LIST",IF(T33>=65,"WATCH","REJECT / REPLACE")))))) | Y33: =IF(D33="","Open Slot",IF(AND(W33<>"",W33<>"No Decision"),"Decision Recorded",IF(OR(V33="ADVANCE",ISNUMBER(SEARCH("EXCEPTION",V33))),"COMMITTEE DECISION REQUIRED","Under Review"))) -> Open Slot

Sheet 11 Conviction
A1: MOPS-002 / PEW-005 — CONVICTION ASSIGNMENT & THESIS CONTROL
A2: Separates security quality from portfolio conviction and documents thesis, risk, horizon and review requirements
A3: Conviction tiers: Tier 1 Anchor | Tier 2 Core | Tier 3 Opportunistic | Unassigned blocks certification
A4: Production Sleeve | B4: Symbol | C4: Security | D4: Type | E4: Certified Weight | F4: Current Conviction | G4: Proposed Conviction (Input) | H4: Effective Conviction | I4: Conviction Score | J4: Thesis Status (Input) | K4: Research Status | L4: Risk Classification (Input) | M4: Expected Holding Period (Input) | N4: Next Review Date (Input) | O4: Decision State | P4: Committee Rationale
A5: ='Certified Allocation'!A5 -> Strategic Anchors | B5: ='Certified Allocation'!B5 -> BRK.B | C5: ='Certified Allocation'!C5 -> Berkshire Hathaway Inc. Class B | D5: ='Certified Allocation'!D5 -> Equity | E5: ='Certified Allocation'!F5 -> 0.0302 | F5: ='Certified Allocation'!M5 -> Unassigned | H5: =IF(G5="",F5,G5) -> Unassigned | I5: =IF(H5="Tier 1 — Anchor",3,IF(H5="Tier 2 — Core",2,IF(H5="Tier 3 — Opportunistic",1,0))) -> 0 | K5: ='Certified Allocation'!N5 -> Current | O5: =IF(H5="Unassigned","ASSIGN CONVICTION",IF(J5="Impaired","REDUCE / REPLACE REVIEW",IF(G5<>"","COMMITTEE REVIEW",IF(OR(K5="Update Due",K5="Review Due",K5="Decision Required"),"RESEARCH REVIEW","NO CHANGE")))) -> ASSIGN CONVICTION
A6: ='Certified Allocation'!A6 -> Strategic Anchors | B6: ='Certified Allocation'!B6 -> COST | C6: ='Certified Allocation'!C6 -> Costco Wholesale Corporation | D6: ='Certified Allocation'!D6 -> Equity | E6: ='Certified Allocation'!F6 -> 0.0302 | F6: ='Certified Allocation'!M6 -> Unassigned | H6: =IF(G6="",F6,G6) -> Unassigned | I6: =IF(H6="Tier 1 — Anchor",3,IF(H6="Tier 2 — Core",2,IF(H6="Tier 3 — Opportunistic",1,0))) -> 0 | K6: ='Certified Allocation'!N6 -> Current | O6: =IF(H6="Unassigned","ASSIGN CONVICTION",IF(J6="Impaired","REDUCE / REPLACE REVIEW",IF(G6<>"","COMMITTEE REVIEW",IF(OR(K6="Update Due",K6="Review Due",K6="Decision Required"),"RESEARCH REVIEW","NO CHANGE")))) -> ASSIGN CONVICTION
A7: ='Certified Allocation'!A7 -> Strategic Anchors | B7: ='Certified Allocation'!B7 -> JNJ | C7: ='Certified Allocation'!C7 -> Johnson & Johnson | D7: ='Certified Allocation'!D7 -> Equity | E7: ='Certified Allocation'!F7 -> 0.0302 | F7: ='Certified Allocation'!M7 -> Unassigned | H7: =IF(G7="",F7,G7) -> Unassigned | I7: =IF(H7="Tier 1 — Anchor",3,IF(H7="Tier 2 — Core",2,IF(H7="Tier 3 — Opportunistic",1,0))) -> 0 | K7: ='Certified Allocation'!N7 -> Current | O7: =IF(H7="Unassigned","ASSIGN CONVICTION",IF(J7="Impaired","REDUCE / REPLACE REVIEW",IF(G7<>"","COMMITTEE REVIEW",IF(OR(K7="Update Due",K7="Review Due",K7="Decision Required"),"RESEARCH REVIEW","NO CHANGE")))) -> ASSIGN CONVICTION
A8: ='Certified Allocation'!A8 -> Strategic Anchors | B8: ='Certified Allocation'!B8 -> MSFT | C8: ='Certified Allocation'!C8 -> Microsoft Corporation | D8: ='Certified Allocation'!D8 -> Equity | E8: ='Certified Allocation'!F8 -> 0.0302 | F8: ='Certified Allocation'!M8 -> Unassigned | H8: =IF(G8="",F8,G8) -> Unassigned | I8: =IF(H8="Tier 1 — Anchor",3,IF(H8="Tier 2 — Core",2,IF(H8="Tier 3 — Opportunistic",1,0))) -> 0 | K8: ='Certified Allocation'!N8 -> Current | O8: =IF(H8="Unassigned","ASSIGN CONVICTION",IF(J8="Impaired","REDUCE / REPLACE REVIEW",IF(G8<>"","COMMITTEE REVIEW",IF(OR(K8="Update Due",K8="Review Due",K8="Decision Required"),"RESEARCH REVIEW","NO CHANGE")))) -> ASSIGN CONVICTION
A9: ='Certified Allocation'!A9 -> Strategic Anchors | B9: ='Certified Allocation'!B9 -> V | C9: ='Certified Allocation'!C9 -> Visa Inc. | D9: ='Certified Allocation'!D9 -> Equity | E9: ='Certified Allocation'!F9 -> 0.0288 | F9: ='Certified Allocation'!M9 -> Unassigned | H9: =IF(G9="",F9,G9) -> Unassigned | I9: =IF(H9="Tier 1 — Anchor",3,IF(H9="Tier 2 — Core",2,IF(H9="Tier 3 — Opportunistic",1,0))) -> 0 | K9: ='Certified Allocation'!N9 -> Current | O9: =IF(H9="Unassigned","ASSIGN CONVICTION",IF(J9="Impaired","REDUCE / REPLACE REVIEW",IF(G9<>"","COMMITTEE REVIEW",IF(OR(K9="Update Due",K9="Review Due",K9="Decision Required"),"RESEARCH REVIEW","NO CHANGE")))) -> ASSIGN CONVICTION
A10: ='Certified Allocation'!A10 -> Strategic Anchors | B10: ='Certified Allocation'!B10 -> GOOGL | C10: ='Certified Allocation'!C10 -> Alphabet Inc. Class A | D10: ='Certified Allocation'!D10 -> Equity | E10: ='Certified Allocation'!F10 -> 0.0284 | F10: ='Certified Allocation'!M10 -> Unassigned | H10: =IF(G10="",F10,G10) -> Unassigned | I10: =IF(H10="Tier 1 — Anchor",3,IF(H10="Tier 2 — Core",2,IF(H10="Tier 3 — Opportunistic",1,0))) -> 0 | K10: ='Certified Allocation'!N10 -> Current | O10: =IF(H10="Unassigned","ASSIGN CONVICTION",IF(J10="Impaired","REDUCE / REPLACE REVIEW",IF(G10<>"","COMMITTEE REVIEW",IF(OR(K10="Update Due",K10="Review Due",K10="Decision Required"),"RESEARCH REVIEW","NO CHANGE")))) -> ASSIGN CONVICTION
A11: ='Certified Allocation'!A11 -> Strategic Anchors | B11: ='Certified Allocation'!B11 -> MA | C11: ='Certified Allocation'!C11 -> Mastercard Incorporated | D11: ='Certified Allocation'!D11 -> Equity | E11: ='Certified Allocation'!F11 -> 0.016 | F11: ='Certified Allocation'!M11 -> Unassigned | H11: =IF(G11="",F11,G11) -> Unassigned | I11: =IF(H11="Tier 1 — Anchor",3,IF(H11="Tier 2 — Core",2,IF(H11="Tier 3 — Opportunistic",1,0))) -> 0 | K11: ='Certified Allocation'!N11 -> Current | O11: =IF(H11="Unassigned","ASSIGN CONVICTION",IF(J11="Impaired","REDUCE / REPLACE REVIEW",IF(G11<>"","COMMITTEE REVIEW",IF(OR(K11="Update Due",K11="Review Due",K11="Decision Required"),"RESEARCH REVIEW","NO CHANGE")))) -> ASSIGN CONVICTION
A12: ='Certified Allocation'!A12 -> Strategic Anchors | B12: ='Certified Allocation'!B12 -> AAPL | C12: ='Certified Allocation'!C12 -> Apple Inc. | D12: ='Certified Allocation'!D12 -> Equity | E12: ='Certified Allocation'!F12 -> 0.0156 | F12: ='Certified Allocation'!M12 -> Unassigned | H12: =IF(G12="",F12,G12) -> Unassigned | I12: =IF(H12="Tier 1 — Anchor",3,IF(H12="Tier 2 — Core",2,IF(H12="Tier 3 — Opportunistic",1,0))) -> 0 | K12: ='Certified Allocation'!N12 -> Current | O12: =IF(H12="Unassigned","ASSIGN CONVICTION",IF(J12="Impaired","REDUCE / REPLACE REVIEW",IF(G12<>"","COMMITTEE REVIEW",IF(OR(K12="Update Due",K12="Review Due",K12="Decision Required"),"RESEARCH REVIEW","NO CHANGE")))) -> ASSIGN CONVICTION
A13: ='Certified Allocation'!A13 -> Strategic Anchors | B13: ='Certified Allocation'!B13 -> AMZN | C13: ='Certified Allocation'!C13 -> Amazon.com, Inc. | D13: ='Certified Allocation'!D13 -> Equity | E13: ='Certified Allocation'!F13 -> 0.0155 | F13: ='Certified Allocation'!M13 -> Unassigned | H13: =IF(G13="",F13,G13) -> Unassigned | I13: =IF(H13="Tier 1 — Anchor",3,IF(H13="Tier 2 — Core",2,IF(H13="Tier 3 — Opportunistic",1,0))) -> 0 | K13: ='Certified Allocation'!N13 -> Current | O13: =IF(H13="Unassigned","ASSIGN CONVICTION",IF(J13="Impaired","REDUCE / REPLACE REVIEW",IF(G13<>"","COMMITTEE REVIEW",IF(OR(K13="Update Due",K13="Review Due",K13="Decision Required"),"RESEARCH REVIEW","NO CHANGE")))) -> ASSIGN CONVICTION
A14: ='Certified Allocation'!A14 -> Growth Compounders | B14: ='Certified Allocation'!B14 -> AVGO | C14: ='Certified Allocation'!C14 -> Broadcom Inc. | D14: ='Certified Allocation'!D14 -> Equity | E14: ='Certified Allocation'!F14 -> 0.0302 | F14: ='Certified Allocation'!M14 -> Unassigned | H14: =IF(G14="",F14,G14) -> Unassigned | I14: =IF(H14="Tier 1 — Anchor",3,IF(H14="Tier 2 — Core",2,IF(H14="Tier 3 — Opportunistic",1,0))) -> 0 | K14: ='Certified Allocation'!N14 -> Current | O14: =IF(H14="Unassigned","ASSIGN CONVICTION",IF(J14="Impaired","REDUCE / REPLACE REVIEW",IF(G14<>"","COMMITTEE REVIEW",IF(OR(K14="Update Due",K14="Review Due",K14="Decision Required"),"RESEARCH REVIEW","NO CHANGE")))) -> ASSIGN CONVICTION
A15: ='Certified Allocation'!A15 -> Growth Compounders | B15: ='Certified Allocation'!B15 -> LLY | C15: ='Certified Allocation'!C15 -> Eli Lilly and Company | D15: ='Certified Allocation'!D15 -> Equity | E15: ='Certified Allocation'!F15 -> 0.0302 | F15: ='Certified Allocation'!M15 -> Unassigned | H15: =IF(G15="",F15,G15) -> Unassigned | I15: =IF(H15="Tier 1 — Anchor",3,IF(H15="Tier 2 — Core",2,IF(H15="Tier 3 — Opportunistic",1,0))) -> 0 | K15: ='Certified Allocation'!N15 -> Current | O15: =IF(H15="Unassigned","ASSIGN CONVICTION",IF(J15="Impaired","REDUCE / REPLACE REVIEW",IF(G15<>"","COMMITTEE REVIEW",IF(OR(K15="Update Due",K15="Review Due",K15="Decision Required"),"RESEARCH REVIEW","NO CHANGE")))) -> ASSIGN CONVICTION
A16: ='Certified Allocation'!A16 -> Growth Compounders | B16: ='Certified Allocation'!B16 -> NVDA | C16: ='Certified Allocation'!C16 -> NVIDIA Corporation | D16: ='Certified Allocation'!D16 -> Equity | E16: ='Certified Allocation'!F16 -> 0.0268 | F16: ='Certified Allocation'!M16 -> Unassigned | H16: =IF(G16="",F16,G16) -> Unassigned | I16: =IF(H16="Tier 1 — Anchor",3,IF(H16="Tier 2 — Core",2,IF(H16="Tier 3 — Opportunistic",1,0))) -> 0 | K16: ='Certified Allocation'!N16 -> Current | O16: =IF(H16="Unassigned","ASSIGN CONVICTION",IF(J16="Impaired","REDUCE / REPLACE REVIEW",IF(G16<>"","COMMITTEE REVIEW",IF(OR(K16="Update Due",K16="Review Due",K16="Decision Required"),"RESEARCH REVIEW","NO CHANGE")))) -> ASSIGN CONVICTION
... A51: ='Certified Allocation'!A51 -> Income & Risk Management | B51: ='Certified Allocation'!B51 -> PFF | C51: ='Certified Allocation'!C51 -> iShares Preferred and Income Securities ETF | D51: ='Certified Allocation'!D51 -> ETF | E51: ='Certified Allocation'!F51 -> 0.0302 | F51: ='Certified Allocation'!M51 -> Unassigned | H51: =IF(G51="",F51,G51) -> Unassigned | I51: =IF(H51="Tier 1 — Anchor",3,IF(H51="Tier 2 — Core",2,IF(H51="Tier 3 — Opportunistic",1,0))) -> 0 | K51: ='Certified Allocation'!N51 -> Current | O51: =IF(H51="Unassigned","ASSIGN CONVICTION",IF(J51="Impaired","REDUCE / REPLACE REVIEW",IF(G51<>"","COMMITTEE REVIEW",IF(OR(K51="Update Due",K51="Review Due",K51="Decision Required"),"RESEARCH REVIEW","NO CHANGE")))) -> ASSIGN CONVICTION
A52: CONVICTION COMPLETENESS / DECISION CONTROL | F52: =COUNTIF(F5:F51,"<>Unassigned") -> 0 | G52: Current Assigned | H52: =COUNTIF(H5:H51,"<>Unassigned") -> 0 | I52: Effective Assigned | N52: Open Decisions | O52: =COUNTIF(O5:O51,"<>NO CHANGE") -> 47

Sheet 12 Allocation Lab
A1: MOPS-002 / PEW-006 — ALLOCATION ENGINEERING LAB
A2: Controlled scenario layer. The certified MFPDF portfolio remains unchanged until a new version is formally approved.
A3: Scenario Baseline: Certified Portfolio B | No automatic trading | All proposed changes require evidence and governance
A4: Scenario ID | B4: PEW-SCN-001 | D4: Scenario Name | E4: Certified Baseline / No Change | I4: Prepared Date | J4: 46229 | L4: Scenario Status | M4: =IF(COUNTA('Certified Allocation'!I5:I51)<47,"DATA SETUP REQUIRED",IF(ABS(E6-100%)>'13 Validation & Cert'!$B$9,"REVISION REQUIRED",IF(K6=0,"BASELINE / NO CHANGE","COMMITTEE REVIEW REQUIRED"))) -> DATA SETUP REQUIRED
A6: Certified Total | B6: =SUM(F11:F57) -> 1 | D6: Scenario Total | E6: =SUM(K11:K57) -> 1 | G6: Funding Balance | H6: =E6-B6 -> 0 | J6: Changed Positions | K6: =COUNTIF(L11:L57,"<>0") -> 0 | M6: Gross Turnover | N6: =SUM(R11:R57)/2 -> 0 | P6: Band Exceptions | Q6: =COUNTIF(N11:N57,"<>Within Certified Band") -> 0
A7: Current Actual Total | B7: =SUM('Certified Allocation'!I5:I51) -> 0 | D7: Actual Weights Loaded | E7: =COUNTA('Certified Allocation'!I5:I51)&" / 47" -> 0 / 47 | G7: Implementation Readiness | H7: =IF(COUNTA('Certified Allocation'!I5:I51)<47,"INPUT REQUIRED — LOAD ACTUAL WEIGHTS",IF(ABS(E6-100%)>'13 Validation & Cert'!$B$9,"REVISION REQUIRED — SCENARIO MUST TOTAL 100%",IF(COUNTIF(Q11:Q57,"Rationale Required")>0,"INPUT REQUIRED — COMPLETE RATIONALES","READY FOR VALIDATION"))) -> INPUT REQUIRED — LOAD ACTUAL WEIGHTS
A9: SCENARIO ALLOCATION SCHEDULE — INPUT ONLY IN YELLOW CELLS
A10: Production Sleeve | B10: Symbol | C10: Security | D10: Type | E10: Certified Portfolio Role | F10: Certified Target | G10: Lower Band | H10: Upper Band | I10: Actual Weight | J10: Scenario Weight Input | K10: Effective Scenario Weight | L10: Change vs Certified | M10: Funding / Use | N10: Certified Band Test | O10: Decision Trigger | P10: Committee Rationale | Q10: Validation State | R10: Absolute Change
A11: ='Certified Allocation'!A5 -> Strategic Anchors | B11: ='Certified Allocation'!B5 -> BRK.B | C11: ='Certified Allocation'!C5 -> Berkshire Hathaway Inc. Class B | D11: ='Certified Allocation'!D5 -> Equity | E11: ='Certified Allocation'!E5 -> Diversified capital-allocation anchor | F11: ='Certified Allocation'!F5 -> 0.0302 | G11: ='Certified Allocation'!G5 -> 0.02265 | H11: ='Certified Allocation'!H5 -> 0.03775 | I11: ='Certified Allocation'!I5 -> 0 | K11: =IF(J11="",F11,J11) -> 0.0302 | L11: =K11-F11 -> 0 | M11: =IF(ABS(L11)<'13 Validation & Cert'!$B$9,"No Change",IF(L11>0,"Funding Required","Source of Funds")) -> No Change | N11: =IF(K11<G11,"Below Certified Band",IF(K11>H11,"Above Certified Band","Within Certified Band")) -> Within Certified Band | O11: =IF(ABS(L11)<'13 Validation & Cert'!$B$9,"No scenario change",IF(N11<>"Within Certified Band","BAND EXCEPTION — COMMITTEE DECISION",IF(ABS(L11)>='13 Validation & Cert'!$B$7,"MATERIAL POSITION CHANGE","REVIEW PROPOSED CHANGE"))) -> No scenario change | Q11: =IF(ABS(L11)<'13 Validation & Cert'!$B$9,"Baseline",IF(P11="","Rationale Required","Ready for Validation")) -> Baseline | R11: =ABS(L11) -> 0
A12: ='Certified Allocation'!A6 -> Strategic Anchors | B12: ='Certified Allocation'!B6 -> COST | C12: ='Certified Allocation'!C6 -> Costco Wholesale Corporation | D12: ='Certified Allocation'!D6 -> Equity | E12: ='Certified Allocation'!E6 -> Consumer-resilience anchor | F12: ='Certified Allocation'!F6 -> 0.0302 | G12: ='Certified Allocation'!G6 -> 0.02265 | H12: ='Certified Allocation'!H6 -> 0.03775 | I12: ='Certified Allocation'!I6 -> 0 | K12: =IF(J12="",F12,J12) -> 0.0302 | L12: =K12-F12 -> 0 | M12: =IF(ABS(L12)<'13 Validation & Cert'!$B$9,"No Change",IF(L12>0,"Funding Required","Source of Funds")) -> No Change | N12: =IF(K12<G12,"Below Certified Band",IF(K12>H12,"Above Certified Band","Within Certified Band")) -> Within Certified Band | O12: =IF(ABS(L12)<'13 Validation & Cert'!$B$9,"No scenario change",IF(N12<>"Within Certified Band","BAND EXCEPTION — COMMITTEE DECISION",IF(ABS(L12)>='13 Validation & Cert'!$B$7,"MATERIAL POSITION CHANGE","REVIEW PROPOSED CHANGE"))) -> No scenario change | Q12: =IF(ABS(L12)<'13 Validation & Cert'!$B$9,"Baseline",IF(P12="","Rationale Required","Ready for Validation")) -> Baseline | R12: =ABS(L12) -> 0
A13: ='Certified Allocation'!A7 -> Strategic Anchors | B13: ='Certified Allocation'!B7 -> JNJ | C13: ='Certified Allocation'!C7 -> Johnson & Johnson | D13: ='Certified Allocation'!D7 -> Equity | E13: ='Certified Allocation'!E7 -> Healthcare and life-sciences resilience anchor | F13: ='Certified Allocation'!F7 -> 0.0302 | G13: ='Certified Allocation'!G7 -> 0.02265 | H13: ='Certified Allocation'!H7 -> 0.03775 | I13: ='Certified Allocation'!I7 -> 0 | K13: =IF(J13="",F13,J13) -> 0.0302 | L13: =K13-F13 -> 0 | M13: =IF(ABS(L13)<'13 Validation & Cert'!$B$9,"No Change",IF(L13>0,"Funding Required","Source of Funds")) -> No Change | N13: =IF(K13<G13,"Below Certified Band",IF(K13>H13,"Above Certified Band","Within Certified Band")) -> Within Certified Band | O13: =IF(ABS(L13)<'13 Validation & Cert'!$B$9,"No scenario change",IF(N13<>"Within Certified Band","BAND EXCEPTION — COMMITTEE DECISION",IF(ABS(L13)>='13 Validation & Cert'!$B$7,"MATERIAL POSITION CHANGE","REVIEW PROPOSED CHANGE"))) -> No scenario change | Q13: =IF(ABS(L13)<'13 Validation & Cert'!$B$9,"Baseline",IF(P13="","Rationale Required","Ready for Validation")) -> Baseline | R13: =ABS(L13) -> 0
A14: ='Certified Allocation'!A8 -> Strategic Anchors | B14: ='Certified Allocation'!B8 -> MSFT | C14: ='Certified Allocation'!C8 -> Microsoft Corporation | D14: ='Certified Allocation'!D8 -> Equity | E14: ='Certified Allocation'!E8 -> Enterprise technology and AI platform anchor | F14: ='Certified Allocation'!F8 -> 0.0302 | G14: ='Certified Allocation'!G8 -> 0.02265 | H14: ='Certified Allocation'!H8 -> 0.03775 | I14: ='Certified Allocation'!I8 -> 0 | K14: =IF(J14="",F14,J14) -> 0.0302 | L14: =K14-F14 -> 0 | M14: =IF(ABS(L14)<'13 Validation & Cert'!$B$9,"No Change",IF(L14>0,"Funding Required","Source of Funds")) -> No Change | N14: =IF(K14<G14,"Below Certified Band",IF(K14>H14,"Above Certified Band","Within Certified Band")) -> Within Certified Band | O14: =IF(ABS(L14)<'13 Validation & Cert'!$B$9,"No scenario change",IF(N14<>"Within Certified Band","BAND EXCEPTION — COMMITTEE DECISION",IF(ABS(L14)>='13 Validation & Cert'!$B$7,"MATERIAL POSITION CHANGE","REVIEW PROPOSED CHANGE"))) -> No scenario change | Q14: =IF(ABS(L14)<'13 Validation & Cert'!$B$9,"Baseline",IF(P14="","Rationale Required","Ready for Validation")) -> Baseline | R14: =ABS(L14) -> 0
A15: ='Certified Allocation'!A9 -> Strategic Anchors | B15: ='Certified Allocation'!B9 -> V | C15: ='Certified Allocation'!C9 -> Visa Inc. | D15: ='Certified Allocation'!D9 -> Equity | E15: ='Certified Allocation'!E9 -> Global payments infrastructure anchor | F15: ='Certified Allocation'!F9 -> 0.0288 | G15: ='Certified Allocation'!G9 -> 0.0216 | H15: ='Certified Allocation'!H9 -> 0.036 | I15: ='Certified Allocation'!I9 -> 0 | K15: =IF(J15="",F15,J15) -> 0.0288 | L15: =K15-F15 -> 0 | M15: =IF(ABS(L15)<'13 Validation & Cert'!$B$9,"No Change",IF(L15>0,"Funding Required","Source of Funds")) -> No Change | N15: =IF(K15<G15,"Below Certified Band",IF(K15>H15,"Above Certified Band","Within Certified Band")) -> Within Certified Band | O15: =IF(ABS(L15)<'13 Validation & Cert'!$B$9,"No scenario change",IF(N15<>"Within Certified Band","BAND EXCEPTION — COMMITTEE DECISION",IF(ABS(L15)>='13 Validation & Cert'!$B$7,"MATERIAL POSITION CHANGE","REVIEW PROPOSED CHANGE"))) -> No scenario change | Q15: =IF(ABS(L15)<'13 Validation & Cert'!$B$9,"Baseline",IF(P15="","Rationale Required","Ready for Validation")) -> Baseline | R15: =ABS(L15) -> 0
A16: ='Certified Allocation'!A10 -> Strategic Anchors | B16: ='Certified Allocation'!B10 -> GOOGL | C16: ='Certified Allocation'!C10 -> Alphabet Inc. Class A | D16: ='Certified Allocation'!D10 -> Equity | E16: ='Certified Allocation'!E10 -> Digital platform and AI anchor | F16: ='Certified Allocation'!F10 -> 0.0284 | G16: ='Certified Allocation'!G10 -> 0.0213 | H16: ='Certified Allocation'!H10 -> 0.0355 | I16: ='Certified Allocation'!I10 -> 0 | K16: =IF(J16="",F16,J16) -> 0.0284 | L16: =K16-F16 -> 0 | M16: =IF(ABS(L16)<'13 Validation & Cert'!$B$9,"No Change",IF(L16>0,"Funding Required","Source of Funds")) -> No Change | N16: =IF(K16<G16,"Below Certified Band",IF(K16>H16,"Above Certified Band","Within Certified Band")) -> Within Certified Band | O16: =IF(ABS(L16)<'13 Validation & Cert'!$B$9,"No scenario change",IF(N16<>"Within Certified Band","BAND EXCEPTION — COMMITTEE DECISION",IF(ABS(L16)>='13 Validation & Cert'!$B$7,"MATERIAL POSITION CHANGE","REVIEW PROPOSED CHANGE"))) -> No scenario change | Q16: =IF(ABS(L16)<'13 Validation & Cert'!$B$9,"Baseline",IF(P16="","Rationale Required","Ready for Validation")) -> Baseline | R16: =ABS(L16) -> 0
A17: ='Certified Allocation'!A11 -> Strategic Anchors | B17: ='Certified Allocation'!B11 -> MA | C17: ='Certified Allocation'!C11 -> Mastercard Incorporated | D17: ='Certified Allocation'!D11 -> Equity | E17: ='Certified Allocation'!E11 -> Global payments infrastructure anchor | F17: ='Certified Allocation'!F11 -> 0.016 | G17: ='Certified Allocation'!G11 -> 0.012 | H17: ='Certified Allocation'!H11 -> 0.02 | I17: ='Certified Allocation'!I11 -> 0 | K17: =IF(J17="",F17,J17) -> 0.016 | L17: =K17-F17 -> 0 | M17: =IF(ABS(L17)<'13 Validation & Cert'!$B$9,"No Change",IF(L17>0,"Funding Required","Source of Funds")) -> No Change | N17: =IF(K17<G17,"Below Certified Band",IF(K17>H17,"Above Certified Band","Within Certified Band")) -> Within Certified Band | O17: =IF(ABS(L17)<'13 Validation & Cert'!$B$9,"No scenario change",IF(N17<>"Within Certified Band","BAND EXCEPTION — COMMITTEE DECISION",IF(ABS(L17)>='13 Validation & Cert'!$B$7,"MATERIAL POSITION CHANGE","REVIEW PROPOSED CHANGE"))) -> No scenario change | Q17: =IF(ABS(L17)<'13 Validation & Cert'!$B$9,"Baseline",IF(P17="","Rationale Required","Ready for Validation")) -> Baseline | R17: =ABS(L17) -> 0
A18: ='Certified Allocation'!A12 -> Strategic Anchors | B18: ='Certified Allocation'!B12 -> AAPL | C18: ='Certified Allocation'!C12 -> Apple Inc. | D18: ='Certified Allocation'!D12 -> Equity | E18: ='Certified Allocation'!E12 -> Consumer technology ecosystem anchor | F18: ='Certified Allocation'!F12 -> 0.0156 | G18: ='Certified Allocation'!G12 -> 0.0117 | H18: ='Certified Allocation'!H12 -> 0.0195 | I18: ='Certified Allocation'!I12 -> 0 | K18: =IF(J18="",F18,J18) -> 0.0156 | L18: =K18-F18 -> 0 | M18: =IF(ABS(L18)<'13 Validation & Cert'!$B$9,"No Change",IF(L18>0,"Funding Required","Source of Funds")) -> No Change | N18: =IF(K18<G18,"Below Certified Band",IF(K18>H18,"Above Certified Band","Within Certified Band")) -> Within Certified Band | O18: =IF(ABS(L18)<'13 Validation & Cert'!$B$9,"No scenario change",IF(N18<>"Within Certified Band","BAND EXCEPTION — COMMITTEE DECISION",IF(ABS(L18)>='13 Validation & Cert'!$B$7,"MATERIAL POSITION CHANGE","REVIEW PROPOSED CHANGE"))) -> No scenario change | Q18: =IF(ABS(L18)<'13 Validation & Cert'!$B$9,"Baseline",IF(P18="","Rationale Required","Ready for Validation")) -> Baseline | R18: =ABS(L18) -> 0
A19: ='Certified Allocation'!A13 -> Strategic Anchors | B19: ='Certified Allocation'!B13 -> AMZN | C19: ='Certified Allocation'!C13 -> Amazon.com, Inc. | D19: ='Certified Allocation'!D13 -> Equity | E19: ='Certified Allocation'!E13 -> Cloud, commerce and logistics anchor | F19: ='Certified Allocation'!F13 -> 0.0155 | G19: ='Certified Allocation'!G13 -> 0.011625 | H19: ='Certified Allocation'!H13 -> 0.019375 | I19: ='Certified Allocation'!I13 -> 0 | K19: =IF(J19="",F19,J19) -> 0.0155 | L19: =K19-F19 -> 0 | M19: =IF(ABS(L19)<'13 Validation & Cert'!$B$9,"No Change",IF(L19>0,"Funding Required","Source of Funds")) -> No Change | N19: =IF(K19<G19,"Below Certified Band",IF(K19>H19,"Above Certified Band","Within Certified Band")) -> Within Certified Band | O19: =IF(ABS(L19)<'13 Validation & Cert'!$B$9,"No scenario change",IF(N19<>"Within Certified Band","BAND EXCEPTION — COMMITTEE DECISION",IF(ABS(L19)>='13 Validation & Cert'!$B$7,"MATERIAL POSITION CHANGE","REVIEW PROPOSED CHANGE"))) -> No scenario change | Q19: =IF(ABS(L19)<'13 Validation & Cert'!$B$9,"Baseline",IF(P19="","Rationale Required","Ready for Validation")) -> Baseline | R19: =ABS(L19) -> 0
A20: ='Certified Allocation'!A14 -> Growth Compounders | B20: ='Certified Allocation'!B14 -> AVGO | C20: ='Certified Allocation'!C14 -> Broadcom Inc. | D20: ='Certified Allocation'!D14 -> Equity | E20: ='Certified Allocation'!E14 -> Semiconductor and infrastructure-software compounder | F20: ='Certified Allocation'!F14 -> 0.0302 | G20: ='Certified Allocation'!G14 -> 0.02265 | H20: ='Certified Allocation'!H14 -> 0.03775 | I20: ='Certified Allocation'!I14 -> 0 | K20: =IF(J20="",F20,J20) -> 0.0302 | L20: =K20-F20 -> 0 | M20: =IF(ABS(L20)<'13 Validation & Cert'!$B$9,"No Change",IF(L20>0,"Funding Required","Source of Funds")) -> No Change | N20: =IF(K20<G20,"Below Certified Band",IF(K20>H20,"Above Certified Band","Within Certified Band")) -> Within Certified Band | O20: =IF(ABS(L20)<'13 Validation & Cert'!$B$9,"No scenario change",IF(N20<>"Within Certified Band","BAND EXCEPTION — COMMITTEE DECISION",IF(ABS(L20)>='13 Validation & Cert'!$B$7,"MATERIAL POSITION CHANGE","REVIEW PROPOSED CHANGE"))) -> No scenario change | Q20: =IF(ABS(L20)<'13 Validation & Cert'!$B$9,"Baseline",IF(P20="","Rationale Required","Ready for Validation")) -> Baseline | R20: =ABS(L20) -> 0
A21: ='Certified Allocation'!A15 -> Growth Compounders | B21: ='Certified Allocation'!B15 -> LLY | C21: ='Certified Allocation'!C15 -> Eli Lilly and Company | D21: ='Certified Allocation'!D15 -> Equity | E21: ='Certified Allocation'!E15 -> Healthcare innovation compounder | F21: ='Certified Allocation'!F15 -> 0.0302 | G21: ='Certified Allocation'!G15 -> 0.02265 | H21: ='Certified Allocation'!H15 -> 0.03775 | I21: ='Certified Allocation'!I15 -> 0 | K21: =IF(J21="",F21,J21) -> 0.0302 | L21: =K21-F21 -> 0 | M21: =IF(ABS(L21)<'13 Validation & Cert'!$B$9,"No Change",IF(L21>0,"Funding Required","Source of Funds")) -> No Change | N21: =IF(K21<G21,"Below Certified Band",IF(K21>H21,"Above Certified Band","Within Certified Band")) -> Within Certified Band | O21: =IF(ABS(L21)<'13 Validation & Cert'!$B$9,"No scenario change",IF(N21<>"Within Certified Band","BAND EXCEPTION — COMMITTEE DECISION",IF(ABS(L21)>='13 Validation & Cert'!$B$7,"MATERIAL POSITION CHANGE","REVIEW PROPOSED CHANGE"))) -> No scenario change | Q21: =IF(ABS(L21)<'13 Validation & Cert'!$B$9,"Baseline",IF(P21="","Rationale Required","Ready for Validation")) -> Baseline | R21: =ABS(L21) -> 0
A22: ='Certified Allocation'!A16 -> Growth Compounders | B22: ='Certified Allocation'!B16 -> NVDA | C22: ='Certified Allocation'!C16 -> NVIDIA Corporation | D22: ='Certified Allocation'!D16 -> Equity | E22: ='Certified Allocation'!E16 -> AI compute growth engine | F22: ='Certified Allocation'!F16 -> 0.0268 | G22: ='Certified Allocation'!G16 -> 0.0201 | H22: ='Certified Allocation'!H16 -> 0.0335 | I22: ='Certified Allocation'!I16 -> 0 | K22: =IF(J22="",F22,J22) -> 0.0268 | L22: =K22-F22 -> 0 | M22: =IF(ABS(L22)<'13 Validation & Cert'!$B$9,"No Change",IF(L22>0,"Funding Required","Source of Funds")) -> No Change | N22: =IF(K22<G22,"Below Certified Band",IF(K22>H22,"Above Certified Band","Within Certified Band")) -> Within Certified Band | O22: =IF(ABS(L22)<'13 Validation & Cert'!$B$9,"No scenario change",IF(N22<>"Within Certified Band","BAND EXCEPTION — COMMITTEE DECISION",IF(ABS(L22)>='13 Validation & Cert'!$B$7,"MATERIAL POSITION CHANGE","REVIEW PROPOSED CHANGE"))) -> No scenario change | Q22: =IF(ABS(L22)<'13 Validation & Cert'!$B$9,"Baseline",IF(P22="","Rationale Required","Ready for Validation")) -> Baseline | R22: =ABS(L22) -> 0
... A57: ='Certified Allocation'!A51 -> Income & Risk Management | B57: ='Certified Allocation'!B51 -> PFF | C57: ='Certified Allocation'!C51 -> iShares Preferred and Income Securities ETF | D57: ='Certified Allocation'!D51 -> ETF | E57: ='Certified Allocation'!E51 -> Preferred securities income diversification | F57: ='Certified Allocation'!F51 -> 0.0302 | G57: ='Certified Allocation'!G51 -> 0.02265 | H57: ='Certified Allocation'!H51 -> 0.03775 | I57: ='Certified Allocation'!I51 -> 0 | K57: =IF(J57="",F57,J57) -> 0.0302 | L57: =K57-F57 -> 0 | M57: =IF(ABS(L57)<'13 Validation & Cert'!$B$9,"No Change",IF(L57>0,"Funding Required","Source of Funds")) -> No Change | N57: =IF(K57<G57,"Below Certified Band",IF(K57>H57,"Above Certified Band","Within Certified Band")) -> Within Certified Band | O57: =IF(ABS(L57)<'13 Validation & Cert'!$B$9,"No scenario change",IF(N57<>"Within Certified Band","BAND EXCEPTION — COMMITTEE DECISION",IF(ABS(L57)>='13 Validation & Cert'!$B$7,"MATERIAL POSITION CHANGE","REVIEW PROPOSED CHANGE"))) -> No scenario change | Q57: =IF(ABS(L57)<'13 Validation & Cert'!$B$9,"Baseline",IF(P57="","Rationale Required","Ready for Validation")) -> Baseline | R57: =ABS(L57) -> 0
A58: PORTFOLIO TOTAL / SCENARIO CONTROL | F58: =SUM(F11:F57) -> 1 | I58: =SUM(I11:I57) -> 0 | J58: =SUM(J11:J57) -> 0 | K58: =SUM(K11:K57) -> 1 | L58: =SUM(L11:L57) -> 0 | R58: =SUM(R11:R57)/2 -> 0

Sheet 13 Validation & Cert
A1: MOPS-002 / PEW-007 — PORTFOLIO SCENARIO VALIDATION & CERTIFICATION
A2: Automated engineering tests, evidence requirements, governance approvals and controlled issuance of a new MFPDF version
A3: The workspace architecture is certified and frozen. A portfolio scenario remains non-operational until every required review is complete and the Chief Investment Steward issues a newly certified MFPDF version.
A4: MATERIALITY AND CONSTRUCTION CONTROLS | I4: CURRENT ENGINEERING STATE
A5: Validation Control | B5: Value | C5: Operating Meaning | I5: Scenario ID | J5: ='12 Allocation Lab'!B4 -> PEW-SCN-001
A6: Gross turnover materiality threshold | B6: 0.1 | C6: Empirical / Monte Carlo review is required above this level. | I6: Scenario Name | J6: ='12 Allocation Lab'!E4 -> Certified Baseline / No Change
A7: Single-position materiality threshold | B7: 0.0075 | C7: Absolute target change at or above this level is material. | I7: Scenario Status | J7: ='12 Allocation Lab'!M4 -> DATA SETUP REQUIRED
A8: Sleeve-shift materiality threshold | B8: 0.02 | C8: Absolute sleeve allocation change at or above this level is material. | I8: Certified Total | J8: ='12 Allocation Lab'!B6 -> 1
A9: Target-total tolerance | B9: 1e-06 | C9: Scenario effective weights must reconcile to 100% within tolerance. | I9: Scenario Total | J9: ='12 Allocation Lab'!E6 -> 1
A10: Preferred equity minimum | B10: 32 | C10: Soft construction objective. | I10: Changed Positions | J10: ='12 Allocation Lab'!K6 -> 0
A11: Preferred equity maximum | B11: 38 | C11: Soft construction objective. | I11: Gross Turnover | J11: ='12 Allocation Lab'!N6 -> 0
A12: Operating equity ceiling | B12: 41 | C12: Hard certification ceiling without formal amendment. | I12: Overall Readiness | J12: =IF(OR(COUNTIF(E16:E33,"FAIL")>0,COUNTIF(E16:E33,"INPUT REQUIRED")>0),"NOT READY",IF(OR(COUNTIF(E16:E33,"COMMITTEE REVIEW")>0,COUNTIF(E16:E33,"REVIEW")>0,COUNTIF(E16:E33,"REQUIRED")>0),"COMMITTEE REVIEW","READY")) -> NOT READY
A14: AUTOMATED VALIDATION TESTS
A15: Test ID | B15: Validation Test | C15: Current Result | D15: Standard / Threshold | E15: Status | F15: Required Evidence / Action | G15: Authority
A16: VAL-001 | B16: Scenario effective weights total | C16: ='12 Allocation Lab'!E6 -> 1 | D16: 100.00% ± tolerance | E16: =IF(ABS(C16-100%)<=$B$9,"PASS","FAIL") -> PASS | F16: Reconcile scenario weights before review | G16: Portfolio Engineering
A17: VAL-002 | B17: Funding balance | C17: ='12 Allocation Lab'!H6 -> 0 | D17: 0.00% ± tolerance | E17: =IF(ABS(C17)<=$B$9,"PASS","FAIL") -> PASS | F17: Adds must be fully funded by trims / cash source | G17: Portfolio Engineering
A18: VAL-003 | B18: No negative scenario weights | C18: =MIN('12 Allocation Lab'!K11:K57) -> 0.0155 | D18: Minimum weight ≥ 0.00% | E18: =IF(C18>=0,"PASS","FAIL") -> PASS | F18: Correct any negative allocation | G18: Portfolio Engineering
A19: VAL-004 | B19: Changed-position rationales complete | C19: =COUNTIF('12 Allocation Lab'!Q11:Q57,"Rationale Required") -> 0 | D19: 0 missing rationales | E19: =IF(C19=0,"PASS","INPUT REQUIRED") -> PASS | F19: Complete evidence for every changed position | G19: Chief Investment Steward
A20: VAL-005 | B20: Certified holding-band exceptions | C20: =COUNTIF('12 Allocation Lab'!N11:N57,"<>Within Certified Band") -> 0 | D20: Review each exception; no automatic trade | E20: =IF(C20=0,"PASS","COMMITTEE REVIEW") -> PASS | F20: Document add / trim decision or accepted exception | G20: Stewardship Committee
A21: VAL-006 | B21: Gross turnover materiality | C21: ='12 Allocation Lab'!N6 -> 0 | D21: ≤ materiality threshold | E21: =IF(C21<=$B$6,"PASS","COMMITTEE REVIEW") -> PASS | F21: Run empirical / Monte Carlo review if exceeded | G21: Validation Committee
A22: VAL-007 | B22: Maximum single-position change | C22: =MAX('12 Allocation Lab'!R11:R57) -> 0 | D22: < single-position threshold unless validated | E22: =IF(C22<$B$7,"PASS","COMMITTEE REVIEW") -> PASS | F22: Document material position changes | G22: Validation Committee
A23: VAL-008 | B23: Maximum sleeve allocation shift | C23: =MAX(MAX('08 Sleeve Architecture'!I5:I12),-MIN('08 Sleeve Architecture'!I5:I12)) -> 0 | D23: < sleeve-shift threshold unless validated | E23: =IF(C23<$B$8,"PASS","COMMITTEE REVIEW") -> PASS | F23: Document sleeve-level risk / purpose change | G23: Validation Committee
A24: VAL-009 | B24: Positive-weight position count | C24: =COUNTIF('12 Allocation Lab'!K11:K57,">0") -> 47 | D24: Baseline 47 unless add / remove is approved | E24: =IF(C24=47,"PASS","COMMITTEE REVIEW") -> PASS | F24: Document any removal or candidate addition | G24: Stewardship Committee
A25: VAL-010 | B25: Equity-core position count | C25: =COUNTIFS('12 Allocation Lab'!D11:D57,"Equity",'12 Allocation Lab'!K11:K57,">0") -> 40 | D25: Preferred 32–38; hard ceiling 41 | E25: =IF(C25>$B$12,"FAIL",IF(AND(C25>=$B$10,C25<=$B$11),"PASS","MONITOR — OUTSIDE PREFERRED RANGE")) -> MONITOR — OUTSIDE PREFERRED RANGE | F25: Review complexity above preferred range | G25: Stewardship Committee
A26: VAL-011 | B26: ETF position count | C26: =COUNTIFS('12 Allocation Lab'!D11:D57,"ETF",'12 Allocation Lab'!K11:K57,">0") -> 7 | D26: Approved implementation exposures only | E26: =IF(C26=7,"PASS","COMMITTEE REVIEW") -> PASS | F26: Confirm eligible ETF architecture | G26: Stewardship Committee
A27: VAL-012 | B27: Actual portfolio weights loaded | C27: =COUNTA('Certified Allocation'!I5:I51) -> 0 | D27: 47 of 47 | E27: =IF(C27=47,"PASS","INPUT REQUIRED") -> INPUT REQUIRED | F27: Load actual weights before implementation review | G27: Portfolio Operations
A28: VAL-013 | B28: Effective conviction tiers assigned | C28: =COUNTIF('11 Conviction'!H5:H51,"<>Unassigned") -> 0 | D28: 47 of 47 | E28: =IF(C28=47,"PASS","INPUT REQUIRED") -> INPUT REQUIRED | F28: Assign conviction before certification | G28: Stewardship Committee
A29: VAL-014 | B29: Portfolio-role controls passed | C29: =COUNTIF('09 Role Assignment'!O5:O51,"PASS") -> 47 | D29: 47 of 47 | E29: =IF(C29=47,"PASS","REVIEW") -> PASS | F29: Resolve role / evidence exceptions | G29: Research Committee
A30: VAL-015 | B30: Candidate committee decisions outstanding | C30: =COUNTIF('10 Candidate Comparison'!Y14:Y33,"COMMITTEE DECISION REQUIRED") -> 0 | D30: 0 unresolved committee decisions | E30: =IF(C30=0,"PASS","COMMITTEE REVIEW") -> PASS | F30: Resolve candidate / replacement decisions | G30: Stewardship Committee
A31: VAL-016 | B31: Research / conviction decisions outstanding | C31: =COUNTIF('11 Conviction'!O5:O51,"<>NO CHANGE") -> 47 | D31: 0 unresolved research / conviction decisions | E31: =IF(C31=0,"PASS","REVIEW") -> REVIEW | F31: Complete thesis and conviction review | G31: Research Committee
A32: VAL-017 | B32: Implementation data readiness | C32: ='12 Allocation Lab'!H7 -> INPUT REQUIRED — LOAD ACTUAL WEIGHTS | D32: READY FOR VALIDATION | E32: =IF(C32="READY FOR VALIDATION","PASS","INPUT REQUIRED") -> INPUT REQUIRED | F32: Complete required workbook inputs | G32: Portfolio Operations
A33: VAL-018 | B33: Empirical / Monte Carlo requirement | C33: =IF(OR(C21>$B$6,C22>=$B$7,C23>=$B$8,C24<>47,COUNTIF('10 Candidate Comparison'!V14:V33,"ADVANCE")>0),"REQUIRED","NOT REQUIRED") -> NOT REQUIRED | D33: Required when any materiality trigger is breached | E33: =IF(C33="NOT REQUIRED","PASS","REQUIRED") -> PASS | F33: Attach validation package when required | G33: Validation Committee
A36: FORMAL PORTFOLIO SCENARIO CERTIFICATION WORKFLOW
A37: Review Stage | B37: Status (Input) | C37: Reviewed By | D37: Review Date | E37: Evidence Reference | F37: Decision / Notes | G37: Blocking? | H37: Scenario ID | I37: Scenario Name | J37: Proposed MFPDF Version | K37: Effective Date | L37: Certification State | M37: Governance Rule
A38: Portfolio Engineering Review | B38: Pending | G38: Yes | H38: ='12 Allocation Lab'!B4 -> PEW-SCN-001 | I38: ='12 Allocation Lab'!E4 -> Certified Baseline / No Change | J38: MFPDF v1.1 (proposed) | L38: =IF(COUNTIF(B38:B44,"Rejected")>0,"REJECTED",IF(OR(COUNTIF(B38:B44,"Pending")>0,COUNTIF(E16:E33,"FAIL")>0,COUNTIF(E16:E33,"INPUT REQUIRED")>0,AND(E33="REQUIRED",B41<>"Approved")),"NOT READY","READY TO ISSUE NEW MFPDF")) -> NOT READY | M38: No scenario becomes operational until the new MFPDF is issued. Automatic trading remains prohibited.
A39: Research Sufficiency Review | B39: Pending | G39: Yes | H39: ='12 Allocation Lab'!B4 -> PEW-SCN-001 | I39: ='12 Allocation Lab'!E4 -> Certified Baseline / No Change
A40: Allocation & Risk Review | B40: Pending | G40: Yes | H40: ='12 Allocation Lab'!B4 -> PEW-SCN-001 | I40: ='12 Allocation Lab'!E4 -> Certified Baseline / No Change
A41: Empirical / Monte Carlo Review | B41: Not Required | G41: When Required | H41: ='12 Allocation Lab'!B4 -> PEW-SCN-001 | I41: ='12 Allocation Lab'!E4 -> Certified Baseline / No Change
A42: Stewardship Committee Decision | B42: Pending | G42: Yes | H42: ='12 Allocation Lab'!B4 -> PEW-SCN-001 | I42: ='12 Allocation Lab'!E4 -> Certified Baseline / No Change
A43: Chief Investment Steward Certification | B43: Pending | G43: Yes | H43: ='12 Allocation Lab'!B4 -> PEW-SCN-001 | I43: ='12 Allocation Lab'!E4 -> Certified Baseline / No Change
A44: MFPDF Version Issuance | B44: Pending | G44: Yes | H44: ='12 Allocation Lab'!B4 -> PEW-SCN-001 | I44: ='12 Allocation Lab'!E4 -> Certified Baseline / No Change
A47: CERTIFICATION CHANGE REGISTER
A48: Change ID | B48: Symbol / Sleeve | C48: Change Type | D48: Certified Weight | E48: Proposed Weight | F48: Delta | G48: Rationale / Evidence | H48: Certification Outcome
A49: CHG-001 | F49: =IF(OR(D49="",E49=""),"",E49-D49)
A50: CHG-002 | F50: =IF(OR(D50="",E50=""),"",E50-D50)
A51: CHG-003 | F51: =IF(OR(D51="",E51=""),"",E51-D51)
A52: CHG-004 | F52: =IF(OR(D52="",E52=""),"",E52-D52)
A53: CHG-005 | F53: =IF(OR(D53="",E53=""),"",E53-D53)
A54: CHG-006 | F54: =IF(OR(D54="",E54=""),"",E54-D54)
A55: CHG-007 | F55: =IF(OR(D55="",E55=""),"",E55-D55)
A56: CHG-008 | F56: =IF(OR(D56="",E56=""),"",E56-D56)
A57: CHG-009 | F57: =IF(OR(D57="",E57=""),"",E57-D57)
A58: CHG-010 | F58: =IF(OR(D58="",E58=""),"",E58-D58)

Sheet 14 PEW Guide
A1: MOPS-002 — PORTFOLIO ENGINEERING WORKSPACE OPERATING GUIDE
A2: How to use PEW-001 through PEW-007 without disturbing the frozen CISC architecture or the certified MFPDF portfolio
A3: Founders Edition v1.0 — CERTIFIED & FROZEN | MOPS-001 remains frozen | Operating inputs remain live
A4: MOPS-002 GOVERNANCE RECORD
A5: Field | B5: Adopted / Proposed Standard | C5: Status | D5: Operating Effect | F5: Control Principle | G5: Meaning | H5: Authority | I5: Workbook Location | J5: Implementation
A6: Operating Product | B6: MOPS-002 — Portfolio Engineering Workspace | C6: Certified & Frozen | D6: Operational architecture authorized for institutional use | F6: System of Record | G6: Certified MFPDF remains authoritative | H6: Chief Investment Steward | I6: Certified Allocation | J6: No scenario overwrite
A7: Workspace Designation | B7: PEW-001 through PEW-007 | C7: Frozen Architecture | D7: Seven controlled engineering modules | F7: Scenario Layer | G7: All changes remain hypothetical until certified | H7: Portfolio Engineering | I7: 12 Allocation Lab | J7: Separate from certified weights
A8: Certified Foundation | B8: Portfolio B — 47 positions / 100% target | C8: Preserved | D8: No target weight changed by construction of MOPS-002 | F8: Automatic Trading | G8: Not authorized | H8: Stewardship Committee | I8: Rebalancing / PEW-007 | J8: Committee review required
A9: Visual Foundation | B9: CISC-001 five-panel console | C9: Frozen | D9: MOPS-002 inherits navy/gold institutional visual standard | F9: Certification Gate | G9: New MFPDF version required | H9: Chief Investment Steward | I9: 13 Validation & Cert | J9: Only certified version operational
A10: Current Readiness | B10: Actual weights and convictions are incomplete | C10: Data Setup Required | D10: Live implementation and final certification remain blocked | F10: Valid No-Change Outcome | G10: Baseline / no redesign is an authorized conclusion | H10: Stewardship Committee | I10: 06 PEW Control Center | J10: Avoid forced activity
A12: MODULE ARCHITECTURE
A13: Module | B13: Workspace | C13: Core Question | D13: Primary Inputs | E13: Primary Output | F13: Authority | G13: System of Record | H13: Blocks Certification? | I13: Use Frequency | J13: Status
A14: PEW-001 | B14: Mandate & Constraints | C14: What must the portfolio accomplish and never violate? | D14: Objectives, risk limits, construction and governance rules | E14: Mandate compliance register | F14: Chief Investment Steward | G14: 07 Mandate & Constraints | H14: Yes — hard controls | I14: Annual / amendment / material review | J14: Active
A15: PEW-002 | B15: Sleeve Architecture | C15: Is each sleeve serving its purpose at an appropriate allocation? | D15: Certified and scenario sleeve allocations | E15: Sleeve review decision | F15: Stewardship Committee | G15: 08 Sleeve Architecture | H15: When material / unresolved | I15: Quarterly / material event | J15: Active
A16: PEW-003 | B16: Role Assignment | C16: What institutional function does every holding perform? | D16: Certified roles, functional role, evidence and duplication | E16: Retain / review / replace decision | F16: Research Committee | G16: 09 Role Assignment | H16: Yes — role unresolved | I16: Annual / candidate review | J16: Active
A17: PEW-004 | B17: Candidate Comparison | C17: Should an incumbent or candidate occupy the role? | D17: MIAR, MICS, empirical, Merrill, Zacks and role-fit evidence | E17: Advance / watch / reject / exception | F17: Stewardship Committee | G17: 10 Candidate Comparison | H17: Yes — open committee decision | I17: As needed | J17: Ready
A18: PEW-005 | B18: Conviction | C18: How strongly should the portfolio express the thesis? | D18: Conviction tier, thesis, research, risk and horizon | E18: Effective conviction and review decision | F18: Stewardship Committee | G18: 11 Conviction | H18: Yes — unassigned conviction | I18: Quarterly / material event | J18: Input Required
A19: PEW-006 | B19: Allocation Lab | C19: What funded target-weight changes are being proposed? | D19: Certified targets, actual weights, scenario weights and rationale | E19: Band-aware funded scenario | F19: Portfolio Engineering | G19: 12 Allocation Lab | H19: Yes — unbalanced / unsupported | I19: As needed | J19: Baseline
A20: PEW-007 | B20: Validation & Certification | C20: Is the proposal sufficiently evidenced and approved to become operational? | D20: Automated tests and formal approvals | E20: New certified MFPDF version | F20: Chief Investment Steward | G20: 13 Validation & Cert | H20: Sole final gate | I20: Every proposed version | J20: Not Ready
A22: OPERATING WORKFLOW
A23: Step | B23: Action | C23: Primary Sheet | D23: Input Convention | E23: Decision Rule | F23: Required Evidence | G23: Authority | H23: Output | I23: Implementation Rule | J23: Control
A24: 1 | B24: Confirm mandate and constraints | C24: 07 Mandate & Constraints | D24: Yellow / blue policy inputs only when formally changed | E24: Hard constraints cannot be optimized away | F24: Adopted governance record | G24: Chief Investment Steward | H24: Mandate-compliant design space | I24: Amendment required for hard-rule change | J24: PEW-001
A25: 2 | B25: Review sleeve purpose and capacity | C25: 08 Sleeve Architecture | D25: Scenario allocations flow from PEW-006 | E25: Material sleeve shifts require review | F25: Purpose, risk and diversification effect | G25: Stewardship Committee | H25: Sleeve decision | I25: No direct trade instruction | J25: PEW-002
A26: 3 | B26: Confirm each holding's portfolio role | C26: 09 Role Assignment | D26: Blue baseline / yellow assessment inputs | E26: No role = no allocation | F26: MIAR and thesis record | G26: Research Committee | H26: Retain / review / replace | I26: Candidate process required for replacement | J26: PEW-003
A27: 4 | B27: Compare incumbent and candidate evidence | C27: 10 Candidate Comparison | D27: Yellow cells; score 0–100 | E27: Zacks overlay only for close decisions | F27: MIAR, MICS, empirical, Merrill and role fit | G27: Stewardship Committee | H27: Candidate decision | I27: No automatic selection | J27: PEW-004
A28: 5 | B28: Assign conviction and thesis controls | C28: 11 Conviction | D28: Yellow proposed conviction and review inputs | E28: Unassigned conviction blocks certification | F28: Current research and thesis evidence | G28: Stewardship Committee | H28: Effective conviction | I28: Sizing remains scenario-only | J28: PEW-005
A29: 6 | B29: Build a fully funded scenario | C29: 12 Allocation Lab | D29: Enter only Scenario Weight Input and rationale | E29: Effective weights must total 100% | F29: Funding, bands and rationale | G29: Portfolio Engineering | H29: Engineering scenario | I29: Certified targets remain unchanged | J29: PEW-006
A30: 7 | B30: Validate, approve and issue | C30: 13 Validation & Cert | D30: Approval status, reviewers and evidence | E30: Every blocking review must be approved | F30: Empirical / Monte Carlo when triggered | G30: Chief Investment Steward | H30: New MFPDF version | I30: Only issued version becomes operational | J30: PEW-007
A31: 8 | B31: Synchronize executive publications | C31: 00 CISC Dashboard / MWIR | D31: Linked outputs after certification | E31: No publication may imply unapproved change | F31: Certified MFPDF and committee record | G31: Publication Division | H31: Updated dashboard / MWIR | I31: No automatic execution | J31: Publication protocol
A33: COLOR AND ENTRY CONVENTIONS
A34: Convention | B34: Meaning | C34: Where Used | D34: User Action | E34: Do Not | G34: Freeze Field | H34: Current State | I34: Certification Requirement | J34: Result
A35: Blue text + yellow fill | B35: Hardcoded scenario or policy input | C35: Candidate, conviction, allocation and certification inputs | D35: Enter verified information | E35: Do not paste over formula cells | G35: MOPS-001 CISC-001 | H35: Frozen | I35: No alteration without formal amendment | J35: Preserved
A36: Green text | B36: Cross-sheet link to certified or supporting data | C36: All PEW linked fields | D36: Review source sheet if value appears wrong | E36: Do not replace with hardcode | G36: MOPS-002 Architecture | H36: Certified & Frozen | I36: Version-controlled amendment required | J36: FROZEN
A37: Black text | B37: Formula or calculated output | C37: Scores, deltas, statuses and validation | D37: Allow workbook to calculate | E37: Do not overwrite | G37: Certified Portfolio | H37: MFPDF v1.0 | I37: New version required for operational change | J37: Preserved
A38: Green status | B38: Passed, aligned or no decision required | C38: Control and validation status | D38: Continue monitoring | E38: Do not create activity merely to change status | G38: Actual Weights | H38: =COUNTA('Certified Allocation'!I5:I51)&" / 47 loaded" -> 0 / 47 loaded | I38: Required before implementation review | J38: =IF(COUNTA('Certified Allocation'!I5:I51)=47,"PASS","INPUT REQUIRED") -> INPUT REQUIRED
A39: Amber status | B39: Input, review or committee attention required | C39: Decision queue and validation | D39: Resolve evidence or enter required data | E39: Do not interpret as automatic trade | G39: Conviction | H39: =COUNTIF('11 Conviction'!H5:H51,"<>Unassigned")&" / 47 assigned" -> 0 / 47 assigned | I39: Required before certification | J39: =IF(COUNTIF('11 Conviction'!H5:H51,"<>Unassigned")=47,"PASS","INPUT REQUIRED") -> INPUT REQUIRED
A41: MOPS-002 FREEZE RECORD — Effective July 26, 2026, the PEW-001 through PEW-007 architecture is certified and frozen as the Manifest Portfolio Engineering Workspace, Founders Edition v1.0. Future changes must be version-controlled and may not silently alter the certified portfolio, rebalance authority, Zacks/Merrill governance, scenario-isolation rule or prohibition on automatic trading.

Sheet 98 PEW Lists
A1: MOPS-002 — PORTFOLIO ENGINEERING VALIDATION LISTS
A2: Controlled categories used by the Portfolio Engineering Workspace
A3: MOPS-002 | PEW-001–PEW-007 | Founders Edition Production Candidate
A5: Constraint Type | B5: Functional Role | C5: Role Priority | D5: Candidate Type | E5: Merrill Status | F5: Zacks Rank | G5: Yes / No | H5: Conviction Tier
A6: Hard Constraint | B6: Constitutional Anchor | C6: Primary | D6: Incumbent | E6: Buy | F6: 1 | G6: Yes | H6: Tier 1 — Anchor
A7: Soft Objective | B7: Core Compounder | C7: Secondary | D7: Candidate | E7: Neutral | F7: 2 | G7: No | H7: Tier 2 — Core
A8: Governance Rule | B8: Growth Engine | C8: Implementation | E8: Underperform | F8: 3 | H8: Tier 3 — Opportunistic
A9: Preference | B9: Infrastructure Enabler | E9: No Rating | F9: 4 | H9: Unassigned
A10: Monitoring Control | B10: Quality Financial | E10: Not Checked | F10: 5
B11: Defensive Healthcare
B12: Resource Exposure
B13: Income Generator
B14: Volatility Moderator
B15: Diversifier
A20: Thesis Status | B20: Research Status | C20: Risk Class | D20: Holding Period | E20: Role Decision | F20: Committee Decision | G20: Certification Status | H20: Scenario Status
A21: Current | B21: Current | C21: Low | D21: 1–3 years | E21: Retain — Certified Baseline | F21: Approve | G21: Pending | H21: Open
A22: Watch | B22: Update Due | C22: Moderate | D22: 3–5 years | E22: Retain | F22: Reject | G22: Approved | H22: Ready for Validation
A23: Review Due | B23: Review Due | C23: High | D23: 5+ years | E23: Review | F23: Defer | G23: Rejected | H23: Committee Review
A24: Impaired | B24: Decision Required | C24: Not Assessed | D24: Tactical / event driven | E24: Replacement Candidate | F24: Exception Approved | G24: Not Required | H24: Certified
F25: No Decision | H25: Rejected

Sheet 15 MOPS-002 Freeze Record
A1: MOPS-002 — MANIFEST PORTFOLIO ENGINEERING WORKSPACE
A2: FOUNDERS EDITION v1.0 — CERTIFICATION AND FREEZE RECORD
A3: Resolution MOPS-002-FR-001 | Effective July 26, 2026 | Status: CERTIFIED & FROZEN
A5: FORMAL RESOLUTION
A6: By direction of the Chief Investment Steward, MOPS-002 — Portfolio Engineering Workspace is adopted, certified and frozen as the Manifest Portfolio Engineering Workspace, Founders Edition v1.0. The certified architecture comprises PEW-001 through PEW-007 and is authorized as the controlled institutional environment for mandate review, sleeve design, role assignment, candidate comparison, conviction governance, allocation engineering, and validation/certification. This resolution freezes the operating architecture and control principles; it does not approve a portfolio trade, a scenario allocation, or a replacement MFPDF version.
A12: CERTIFIED WORKSPACE RECORD
A13: Certification Field | D13: Certified Standard | H13: Status / Authority
A14: Operating Product | D14: MOPS-002 — Portfolio Engineering Workspace | H14: CERTIFIED & FROZEN
A15: Edition | D15: Founders Edition v1.0 | H15: Effective July 26, 2026
A16: Workspace Architecture | D16: PEW-001 through PEW-007 | H16: Frozen
A17: Visual Foundation | D17: CISC-001 five-panel executive console | H17: Preserved
A18: System of Record | D18: Certified MFPDF v1.0 / Portfolio B | H18: Authoritative
A19: Portfolio Foundation | D19: 47 positions | 40 equities | 7 ETFs | 100.00% target | H19: Unchanged
A20: Certification Authority | D20: Chief Investment Steward | H20: Adopted
A21: Resolution | D21: MOPS-002-FR-001 | H21: Final
A23: FROZEN CONTROL PRINCIPLES
A24: 1. The certified MFPDF remains the sole portfolio system of record.
A25: 2. The Portfolio Engineering Workspace is a scenario layer and may not overwrite certified target weights.
A26: 3. Automatic trading or automatic implementation is prohibited; committee authority is retained.
A27: 4. The PEW-001 through PEW-007 module architecture and operating sequence are frozen.
A28: 5. Zacks/Merrill governance, evidence hierarchy, and documented exception controls remain in force.
A29: 6. Any operational portfolio change requires a newly certified and issued MFPDF version.
A30: 7. CISC and MWIR publications may reflect portfolio changes only after formal certification.
A32: SCOPE EXCLUSION AND OPERATING STATE AT FREEZE
A33: This certification freezes the workspace architecture, not a portfolio transaction or new scenario. At the time of certification, actual portfolio weights loaded were 0 of 47, effective conviction tiers assigned were 0 of 47, scenario positions changed were 0, and PEW-SCN-001 remained NOT READY for implementation. These are operating-data conditions, not defects in the certified workspace. The certified Portfolio B target allocation remains unchanged and fully authoritative.
A38: VERSION CONTROL AND AMENDMENT STANDARD
A39: Future structural changes must be issued through formal version control as Founders Edition v1.1 or a later authorized version. No revision may silently modify the certified portfolio, rebalancing authority, scenario-isolation principle, Zacks/Merrill governance, validation gate, or prohibition on automatic trading. Operating inputs may be updated in designated input cells without constituting an architectural amendment.
... A44: MOPS-002-FR-001 | Manifest Portfolio Engineering Workspace | Founders Edition v1.0 | July 26, 2026

Sheet 16 RCC-001 Control Center
A1: MOPS-003 — RESEARCH COMMAND CENTER (RCC)
A2: RCC-001 EXECUTIVE RESEARCH CONTROL CENTER | FOUNDERS EDITION v1.0 — RCC-001 THROUGH RCC-004 INSTALLED
A3: MOPS-003 remains in construction: RCC-001 through RCC-004 are installed; RCC-005 — Zacks / Merrill Research Crosswalk is the next module. MOPS-004 has not commenced.
A5: EXECUTIVE RESEARCH STATE — RCC-001 INITIALIZED
A6: RESEARCH READINESS | G6: CERTIFIED HOLDINGS | K6: RCC ACTIVITY RECORDS | O6: CONVICTION ASSIGNED | S6: THESIS STATUS ASSIGNED
A7: =IF(OR(COUNTIF('11 Conviction'!$H$5:$H$51,"Unassigned")>0,COUNTBLANK('11 Conviction'!$J$5:$J$51)>0,COUNTIFS('20 RCC-003 MIAR Registry'!$B$14:$B$60,"<>",'20 RCC-003 MIAR Registry'!$AB$14:$AB$60,"<>CONTROL CLEAR")>0,COUNTIFS('23 RCC-004 MASR Registry'!$B$14:$B$163,"<>",'23 RCC-004 MASR Registry'!$AD$14:$AD$163,"<>CONTROL CLEAR",'23 RCC-004 MASR Registry'!$AD$14:$AD$163,"<>INACTIVE / CLOSED")>0),"RESEARCH SETUP INCOMPLETE",IF(COUNTA('18 RCC-002 Evidence Ledger'!$A$14:$A$213)=0,"RCC READY — NO EVIDENCE LOADED",IF(COUNTIFS('18 RCC-002 Evidence Ledger'!$A$14:$A$213,"<>",'18 RCC-002 Evidence Ledger'!$AE$14:$AE$213,"<>OPEN — ON TRACK",'18 RCC-002 Evidence Ledger'!$AE$14:$AE$213,"<>CLOSED",'18 RCC-002 Evidence Ledger'!$AE$14:$AE$213,"<>")+COUNTIFS('24 RCC-004 Candidate Pipeline'!$A$14:$A$213,"<>",'24 RCC-004 Candidate Pipeline'!$AK$14:$AK$213,"<>OPEN — ON TRACK",'24 RCC-004 Candidate Pipeline'!$AK$14:$AK$213,"<>CLOSED")>0,"RCC CONTROL EXCEPTIONS","ACTIVE"))) -> RESEARCH SETUP INCOMPLETE | G7: =COUNTA('Certified Allocation'!$B$5:$B$51) -> 47 | K7: =COUNTA('18 RCC-002 Evidence Ledger'!$A$14:$A$213) -> 0 | O7: =COUNTIFS('11 Conviction'!$H$5:$H$51,"<>Unassigned",'11 Conviction'!$H$5:$H$51,"<>") -> 0 | S7: =COUNTA('11 Conviction'!$J$5:$J$51) -> 0
A11: PRIMARY REQUIRED ACTION | G11: MFPDF RESEARCH STATUS | M11: CONTROL EXCEPTIONS | S11: GOVERNANCE
A12: Complete conviction, thesis, MIAR and canonical MASR initialization; then enter each verified research signal and candidate review through RCC-002 and RCC-004. No research record may imply a portfolio change until it passes the controlled referral gate. | G12: =COUNTIF('Certified Allocation'!$N$5:$N$51,"Current")&" CURRENT / "&COUNTIFS('Certified Allocation'!$N$5:$N$51,"<>Current",'Certified Allocation'!$N$5:$N$51,"<>")&" EXCEPTIONS" -> 47 CURRENT / 0 EXCEPTIONS | M12: =COUNTIF('11 Conviction'!$H$5:$H$51,"Unassigned")+COUNTBLANK('11 Conviction'!$J$5:$J$51)+COUNTIFS('Certified Allocation'!$N$5:$N$51,"<>Current",'Certified Allocation'!$N$5:$N$51,"<>")+COUNTIFS('18 RCC-002 Evidence Ledger'!$A$14:$A$213,"<>",'18 RCC-002 Evidence Ledger'!$AE$14:$AE$213,"<>OPEN — ON TRACK",'18 RCC-002 Evidence Ledger'!$AE$14:$AE$213,"<>CLOSED",'18 RCC-002 Evidence Ledger'!$AE$14:$AE$213,"<>")+COUNTIFS('20 RCC-003 MIAR Registry'!$B$14:$B$60,"<>",'20 RCC-003 MIAR Registry'!$AB$14:$AB$60,"<>CONTROL CLEAR")+COUNTIFS('23 RCC-004 MASR Registry'!$B$14:$B$163,"<>",'23 RCC-004 MASR Registry'!$AD$14:$AD$163,"<>CONTROL CLEAR",'23 RCC-004 MASR Registry'!$AD$14:$AD$163,"<>INACTIVE / CLOSED")+COUNTIFS('24 RCC-004 Candidate Pipeline'!$A$14:$A$213,"<>",'24 RCC-004 Candidate Pipeline'!$AK$14:$AK$213,"<>OPEN — ON TRACK",'24 RCC-004 Candidate Pipeline'!$AK$14:$AK$213,"<>CLOSED") -> 207 | S12: Research evaluates evidence and may recommend action. It may not alter certified allocations, authorize trades, or overwrite the certified MFPDF.
A16: RESEARCH CONTROL EXCEPTIONS | J16: RESEARCH INTELLIGENCE SNAPSHOT
A17: Priority | B17: Control / Trigger | C17: Count | D17: Current State | E17: Required Action | F17: Authority | G17: Destination | H17: Governance Impact | J17: Activity Type | K17: Count
A18: 1 | B18: Conviction assignments missing | C18: =COUNTIF('11 Conviction'!$H$5:$H$51,"Unassigned") -> 47 | D18: =IF(C18=0,"PASS","ACTION REQUIRED") -> ACTION REQUIRED | E18: Complete PEW-005 effective conviction | F18: Stewardship Committee | G18: 11 Conviction | H18: Blocks research and portfolio certification | J18: Company reviews | K18: =COUNTIF('18 RCC-002 Evidence Ledger'!$H$14:$H$213,"Company Review") -> 0
A19: 2 | B19: Thesis statuses missing | C19: =COUNTBLANK('11 Conviction'!$J$5:$J$51) -> 47 | D19: =IF(C19=0,"PASS","ACTION REQUIRED") -> ACTION REQUIRED | E19: Assign thesis state for every active holding | F19: Research Committee | G19: RCC-007 (planned) | H19: Blocks thesis and conviction certification | J19: Earnings / events | K19: =COUNTIF('18 RCC-002 Evidence Ledger'!$H$14:$H$213,"Earnings / Guidance")+COUNTIF('18 RCC-002 Evidence Ledger'!$H$14:$H$213,"Material Corporate Event") -> 0
A20: 3 | B20: Research status exceptions | C20: =COUNTIFS('Certified Allocation'!$N$5:$N$51,"<>Current",'Certified Allocation'!$N$5:$N$51,"<>") -> 0 | D20: =IF(C20=0,"PASS","REVIEW REQUIRED") -> PASS | E20: Review non-current MFPDF research records | F20: Research Operations | G20: Certified Allocation | H20: May trigger MIAR or thesis review | J20: Zacks changes | K20: =COUNTIF('18 RCC-002 Evidence Ledger'!$H$14:$H$213,"Zacks Rank Change") -> 0
A21: 4 | B21: Companies requiring review | C21: =COUNTIFS('18 RCC-002 Evidence Ledger'!$A$14:$A$213,"<>",'18 RCC-002 Evidence Ledger'!$J$14:$J$213,"Critical",'18 RCC-002 Evidence Ledger'!$T$14:$T$213,"<>Closed — No Action",'18 RCC-002 Evidence Ledger'!$T$14:$T$213,"<>Closed — Incorporated")+COUNTIFS('18 RCC-002 Evidence Ledger'!$A$14:$A$213,"<>",'18 RCC-002 Evidence Ledger'!$J$14:$J$213,"High",'18 RCC-002 Evidence Ledger'!$T$14:$T$213,"<>Closed — No Action",'18 RCC-002 Evidence Ledger'!$T$14:$T$213,"<>Closed — Incorporated") -> 0 | D21: =IF(C21=0,"NO ACTIVE RECORDS","OPEN QUEUE") -> NO ACTIVE RECORDS | E21: Resolve active review queue using verified evidence | F21: Research Committee | G21: 03 Research Intelligence | H21: May require PEW referral | J21: Merrill updates | K21: =COUNTIF('18 RCC-002 Evidence Ledger'!$H$14:$H$213,"Merrill Research Update") -> 0
A22: 5 | B22: MIAR dossier control exceptions | C22: =COUNTIFS('20 RCC-003 MIAR Registry'!$B$14:$B$60,"<>",'20 RCC-003 MIAR Registry'!$AB$14:$AB$60,"<>CONTROL CLEAR") -> 47 | D22: =IF(C22=0,"PASS","ACTION REQUIRED") -> ACTION REQUIRED | E22: Complete required MIAR identity, ownership, cadence, scores and review dates | F22: Research Operations | G22: 20 RCC-003 MIAR Registry | H22: Controls research freshness and dossier readiness | J22: MIAR updates | K22: =COUNTIFS('18 RCC-002 Evidence Ledger'!$A$14:$A$213,"<>",'18 RCC-002 Evidence Ledger'!$V$14:$V$213,"<>None",'18 RCC-002 Evidence Ledger'!$V$14:$V$213,"<>") -> 0
A23: 6 | B23: Earnings / event records | C23: =COUNTIF('18 RCC-002 Evidence Ledger'!$H$14:$H$213,"Earnings / Guidance")+COUNTIF('18 RCC-002 Evidence Ledger'!$H$14:$H$213,"Material Corporate Event") -> 0 | D23: =IF(C23=0,"NO ACTIVE RECORDS","CALENDAR ACTIVE") -> NO ACTIVE RECORDS | E23: Load verified forward calendar and post-event reviews | F23: Research Operations | G23: RCC-006 (planned) | H23: Controls event readiness | J23: Thesis assigned | K23: =COUNTIFS('18 RCC-002 Evidence Ledger'!$A$14:$A$213,"<>",'18 RCC-002 Evidence Ledger'!$W$14:$W$213,"<>None",'18 RCC-002 Evidence Ledger'!$W$14:$W$213,"<>") -> 0
A24: 7 | B24: Zacks / Merrill changes | C24: =COUNTIF('18 RCC-002 Evidence Ledger'!$H$14:$H$213,"Zacks Rank Change")+COUNTIF('18 RCC-002 Evidence Ledger'!$H$14:$H$213,"Merrill Research Update") -> 0 | D24: =IF(C24=0,"NO ACTIVE RECORDS","EVIDENCE UPDATE") -> NO ACTIVE RECORDS | E24: Record only verified external-research changes | F24: Research Committee | G24: RCC-005 (planned) | H24: Evidence input; never automatic authority | J24: Conviction assigned | K24: =COUNTIFS('18 RCC-002 Evidence Ledger'!$A$14:$A$213,"<>",'18 RCC-002 Evidence Ledger'!$X$14:$X$213,"<>No Change",'18 RCC-002 Evidence Ledger'!$X$14:$X$213,"<>Not Applicable",'18 RCC-002 Evidence Ledger'!$X$14:$X$213,"<>Unassigned",'18 RCC-002 Evidence Ledger'!$X$14:$X$213,"<>") -> 0
A25: 8 | B25: MASR / candidate pipeline exceptions | C25: =COUNTIFS('23 RCC-004 MASR Registry'!$B$14:$B$163,"<>",'23 RCC-004 MASR Registry'!$AD$14:$AD$163,"<>CONTROL CLEAR",'23 RCC-004 MASR Registry'!$AD$14:$AD$163,"<>INACTIVE / CLOSED")+COUNTIFS('24 RCC-004 Candidate Pipeline'!$A$14:$A$213,"<>",'24 RCC-004 Candidate Pipeline'!$AK$14:$AK$213,"<>OPEN — ON TRACK",'24 RCC-004 Candidate Pipeline'!$AK$14:$AK$213,"<>CLOSED") -> 66 | D25: =IF(C25=0,"PASS","ACTION REQUIRED") -> ACTION REQUIRED | E25: Complete canonical registry setup and resolve candidate stage-gate exceptions | F25: Research Committee | G25: 22–24 RCC-004 | H25: Controls security admission and PEW referral | J25: Active candidate records | K25: =COUNTIFS('24 RCC-004 Candidate Pipeline'!$A$14:$A$213,"<>",'24 RCC-004 Candidate Pipeline'!$Y$14:$Y$213,"<>Rejected",'24 RCC-004 Candidate Pipeline'!$Y$14:$Y$213,"<>Closed",'24 RCC-004 Candidate Pipeline'!$Y$14:$Y$213,"<>Removed") -> 10
A27: MOPS-003 MODULE ROADMAP
A28: Module | B28: Workspace | C28: Institutional Function | D28: Status | E28: Current Source / Dependency | F28: Next Required Action | G28: Authority | H28: Operating Effect | J28: RCC-004 INSTALLED — MASR REGISTRY & CANDIDATE PIPELINE
A29: RCC-001 | B29: Executive Research Control Center | C29: Aggregates research readiness, exceptions and referrals | D29: ACTIVE — INSTALLED | E29: Certified MFPDF, Research Intelligence, PEW-005 | F29: Operate dashboard and preserve verified-data discipline | G29: Chief Investment Steward | H29: Research command view; no trading authority | J29: RCC-003 remains active as the MIAR dossier gate; RCC-005 is next.
A30: RCC-002 | B30: Research Intake & Evidence Ledger | C30: Captures every material research signal and source | D30: ACTIVE — INSTALLED | E30: Verified internal and external evidence | F30: Operate the controlled evidence register and verification/referral gates | G30: Research Committee | H30: Creates an auditable chain of evidence and controlled referrals | J30: Purpose: preserve canonical MASR identity, distinguish certified holdings from approved non-holdings and candidates, apply eligibility and external-research exception gates, record committee disposition, and route qualified candidates to PEW-004 without creating automatic selection authority.
A31: RCC-003 | B31: MIAR Dossier Control | C31: Controls research freshness and asset-record status | D31: ACTIVE — INSTALLED | E31: MIAR registry and update cadence | F31: Operate MIAR registry, review log, freshness controls and dossier exception queue | G31: Research Operations | H31: Controls company-level research completeness and MIAR maintenance | J31: REQUIRED ADMISSION FIELDS | O31: HARD CONTROLS | T31: CONTROLLED OUTPUT
A32: RCC-004 | B32: MASR Candidate Pipeline | C32: Administers approved, conditional and replacement candidates | D32: ACTIVE — INSTALLED | E32: RCC-002 evidence, RCC-003 MIAR, canonical MASR source and PEW-004 | F32: Operate the controlled registry, eligibility gates, candidate stages and committee / PEW referrals | G32: Research Committee | H32: Controls entry into Candidate Comparison and preserves auditable admission / removal history | J32: Canonical MASR ID Record class and status Admission basis Sleeve and portfolio role MIAR / Integrity / MICS Empirical rank Committee disposition | O32: No fabricated MASR membership One active record per security Exceptions documented No PEW referral before stage gates No direct allocation or trading authority | T32: Controlled MASR registry Candidate stage history Eligibility / exception state Committee disposition PEW-004 referral readiness
A33: RCC-005 | B33: Zacks / Merrill Crosswalk | C33: Applies external-research governance and exceptions | D33: NEXT MODULE | E33: Verified Zacks and Merrill research | F33: Install verified Zacks / Merrill current-state register, change log and exception controls | G33: Stewardship Committee | H33: External input; never automatic authority
A34: RCC-006 | B34: Earnings & Material-Event Monitor | C34: Coordinates pre-event and post-event review | D34: PLANNED | E34: Verified event calendar | F34: Build event workflow and thesis-sensitivity flags | G34: Research Operations | H34: Prevents missed thesis-sensitive events
A35: RCC-007 | B35: Thesis & Conviction Review Center | C35: Certifies thesis state and conviction recommendations | D35: PLANNED | E35: MIAR, evidence ledger and PEW-005 | F35: Build thesis-state and conviction decision workflow | G35: Research Committee | H35: Supports retain, watch, reduce or refer decisions
A36: RCC-008 | B36: Research Certification & Referral | C36: Certifies research conclusion and PEW referral | D36: PLANNED | E36: RCC-002 through RCC-007 | F36: Build evidence sufficiency and referral gates | G36: Chief Investment Steward | H36: Only certified research reaches engineering or committee
A39: MOPS-003 OPERATING SEQUENCE
A40: RESEARCH SIGNAL → EVIDENCE REVIEW → MIAR UPDATE → THESIS ASSESSMENT → CONVICTION DECISION → PORTFOLIO-ENGINEERING REFERRAL
A43: MOPS-003 CONTROL PRINCIPLE — Research identifies and evaluates change. Portfolio Engineering designs the response. Committee governance authorizes the response. The certified MFPDF remains the sole portfolio system of record. RCC-001 may display, prioritize and refer research matters, but it may not change allocations or authorize implementation.

Sheet 97 RCC Lists
A1: MOPS-003 — RCC CONTROLLED VALIDATION LISTS
A2: Controlled categories for RCC-002 Evidence Ledger, RCC-003 MIAR Dossier Control and RCC-004 MASR Registry / Candidate Pipeline. Do not modify without a documented MOPS-003 amendment.
A4: Record Type | B4: Activity Type | C4: Evidence Category | D4: Materiality | E4: Direction | F4: Reliability | G4: Source Type | H4: Thesis Sensitivity | I4: Status | J4: Verification | K4: MIAR Action | L4: Thesis Impact | M4: Conviction Recommendation | N4: Candidate / Replacement | O4: PEW Referral | P4: Disposition | Q4: MIAR Record Status | R4: Review Cadence | S4: MIAR Review Type | T4: Thesis Assessment | U4: Certification Recommendation | V4: RCC-007 Referral State | W4: MIAR Control Status | X4: Research Freshness | Y4: Required MIAR Action | Z4: MASR Record Class | AA4: MASR Registry Status | AB4: Admission Basis | AC4: Candidate Type | AD4: Candidate Stage | AE4: Eligibility Gate | AF4: Merrill Status | AG4: Candidate Source / Referral | AH4: Committee Disposition | AI4: PEW Referral State | AJ4: MASR Control Status | AK4: Required MASR Action | AL4: Candidate Control Status | AM4: Required Candidate Action | AN4: Closure / Removal Reason | AO4: Security Type
A5: Certified Holding | B5: Company Review | C5: Earnings and Guidance | D5: Critical | E5: Positive | F5: Primary — Verified | G5: Company Filing | H5: High | I5: New | J5: Yes | K5: None | L5: None | M5: No Change | N5: None | O5: No | P5: Pending | Q5: Not Initiated | R5: Quarterly — 90 Days | S5: Full Review | T5: Strengthening | U5: Certify Current | V5: No Referral | W5: CONTROL CLEAR | X5: CURRENT | Y5: Maintain scheduled cadence | Z5: Certified Portfolio Holding | AA5: Active — Certified Holding | AB5: Certified MFPDF / Founders Edition | AC5: New Candidate | AD5: Intake | AE5: CERTIFIED HOLDING | AF5: Buy | AG5: RCC-002 Evidence Referral | AH5: Pending | AI5: No | AJ5: SETUP REQUIRED | AK5: Assign canonical MASR ID and complete registry setup | AL5: INCOMPLETE | AM5: Complete required candidate intake fields | AN5: Approved / Advanced | AO5: Equity
A6: MASR Non-Holding | B6: Earnings / Guidance | C6: Revenue and Margin | D6: High | E6: Neutral | F6: Secondary — Verified | G6: Earnings Release | H6: Medium | I6: Under Review | J6: No | K6: Incremental Update | L6: Strengthening | M6: Increase | N6: Candidate Review | O6: Yes — PEW-003 Role | P6: No Action | Q6: Draft | R6: Semiannual — 180 Days | S6: Incremental Update | T6: Intact | U6: Certify with Exception | V6: Refer to RCC-007 | W6: INCOMPLETE | X6: UPDATE DUE | Y6: Complete MIAR setup | Z6: MASR Approved Non-Holding | AA6: Active — Approved Non-Holding | AB6: Manifest Research | AC6: Replacement Candidate | AD6: Evidence Gathering | AE6: ELIGIBLE | AF6: Neutral | AG6: RCC-003 MIAR Referral | AH6: Approve MASR Admission | AI6: Yes — Refer to PEW-004 | AJ6: DUPLICATE MASR ID | AK6: Resolve duplicate canonical MASR identifier | AL6: DUPLICATE CANDIDATE ID | AM6: Resolve duplicate candidate identifier | AN6: Rejected — Evidence | AO6: ETF
A7: Research Candidate | B7: Material Corporate Event | C7: Balance Sheet / Credit | D7: Moderate | E7: Negative | F7: Internal Analysis | G7: Company Presentation | H7: Low | I7: Awaiting Verification | J7: Exception Approved | K7: Full Review | L7: Intact | M7: Reduce | N7: Replacement Review | O7: Yes — PEW-004 Candidate | P7: MIAR Updated | Q7: Active | R7: Annual — 365 Days | S7: Material Event Review | T7: Under Review | U7: Return for Revision | V7: Hold Pending MIAR Update | W7: DUPLICATE MIAR ID | X7: REVIEW DUE | Y7: Assign unique canonical MIAR ID | Z7: Conditional Candidate | AA7: Conditional | AB7: Empirical Screen | AC7: Retention Review | AD7: MIAR Review | AE7: ELIGIBLE WITH EXCEPTION | AF7: Underperform | AG7: RCC-007 Thesis / Conviction Referral | AH7: Approve Conditional Admission | AI7: Referred — Pending PEW Record | AJ7: DUPLICATE TICKER | AK7: Resolve duplicate active ticker record | AL7: MASR RECORD REQUIRED | AM7: Create or reconcile the RCC-004 MASR registry record | AN7: Rejected — Eligibility | AO7: Other
A8: Portfolio-Level | B8: Zacks Rank Change | C8: Capital Allocation | D8: Low | E8: Mixed | F8: Unverified — Pending | G8: Earnings / Investor Call | H8: Not Assessed | I8: Escalated | K8: Material Event Review | L8: Under Review | M8: Watch | N8: MASR Addition Review | O8: Yes — PEW-005 Conviction | P8: Thesis Updated | Q8: Update Due | R8: Event-Driven | S8: Certification Review | T8: Weakening | U8: Escalate to RCC-007 | W8: CERTIFICATION REQUIRED | X8: OVERDUE | Y8: Enter certifier and certification date | Z8: Research Candidate | AA8: Candidate — Under Research | AB8: Zacks Election | AC8: MASR Addition Review | AD8: Eligibility Review | AE8: NOT ELIGIBLE | AF8: No Rating | AG8: Committee Referral | AH8: Advance to PEW-004 | AI8: Referred — PEW Record Linked | AJ8: INCOMPLETE | AK8: Complete required registry classification and role fields | AL8: ELIGIBILITY BLOCK | AM8: Resolve eligibility gate or close candidate | AN8: Rejected — Role Fit
